Workbook
Name Agro: Agro!$B$8
Name Simulação_deCarteiras: 'Simulador de Aportes (R$)'!$B$5
Name Simulação_deCarteiras: 'Simulador de Carteiras (R$)'!$B$5
Name Simulação_deCarteiras: 'Simulador de Carteiras (%)'!$B$5
Name SimulaçãoFin: 'Simulador de Carteiras (%)'!$B$5

Sheet Menu
D5: Indicadores de Fundos Listados (FIIs, Fiagros e FI-Infras) | F5: Comparativo Setorial | H5: Indicadores de Fiagros | J5: Indicadores de FI-Infras | L5: Recebíveis | N5: Galpões Logísticos | P5: Lajes Corporativas
F8: Shopping Centers | H8: Híbridos | J8: Educacional | L8: Hospital | N8: Residencial | P8: Fundo de Fundos
B10: Stock Guide de Fundos Listados
F11: Hedge Funds | H11: Agronegócio | J11: Desenvolvimento | L11: Hotel | N11: Renda Urbana | P11: Outros
D16: Simulador de Carteira (%) | F16: Simulador de Carteira (R$) | H16: Simulador de Aporte (R$)
B19: Daniel Marinelli
B20: BTG Pactual - Equity Research
B22: Matheus Oliveira
B23: BTG Pactual - Equity Research
B25: Frederico Khouri
B26: BTG Pactual - Credit Research
D27: Acesse nosso site | F27: Glossário | H27: Disclaimer
B28: Luis Gonçalves
B29: BTG Pactual - Credit Research
B33: • Filtramos os fundos que possuem um volume de negociação, em média, acima de R$ 30 mil por dia.

Sheet Stock Guide
D2: Menu | I2: Menu
U3: Retorno
E4: Características | H4: Part. IFIX | I4: Volume de Negociação | J4: Fechamento | K4: Máximo | M4: Valor de Mercado | N4: Valor Patrimonial | O4: P/VPA | Q4: Dividend Yield (% ao ano) | U4: No Mês | V4: No Ano | W4: LTM | X4: Análises
B5: Código | C5: CNPJ | D5: Nome | E5: Gestor | F5: Administrador | G5: Segmento | H5: % | I5: Média - 3 Meses (R$) | J5: R$ | K5: R$ | L5: % | M5: R$ | N5: R$ | O5: Atual | P5: 2025 | Q5: LTM | R5: Anualizado | S5: Última Dist. (%) | T5: Div. do Mês (R$) | U5: % | V5: % | W5: % | X5: -
B6: AAZQ11 | C6: 44625826000111 | D6: Az Quest Sole Fiagro-FII | E6: AZ Quest | F6: XP Investimentos | G6: FIAgro - FII | H6: - | I6: 383825.05 | J6: 6.31 | K6: 8.0364233 | L6: 0.78517517 | M6: 1.5167526e+08 | N6: 2.0764849e+08 | O6: 0.73044239 | P6: 1.0183375 | Q6: 0.20166403 | R6: 0.17115689 | S6: 0.014263074 | T6: 0.09 | U6: -0.049698795 | V6: -0.20007913 | W6: -0.0079482424 | X6: =IF(OR(B6="",G6="FI-Infra"),"",HYPERLINK("https://content.btgpactual.com/research/ativo/https://content.btgpactual.com/research/ativo/"&B6,"Link")) -> Link
B7: ABCP11 | C7: 1201140000190 | D7: Grand Plaza Shopping FII | E7: Rio Bravo | F7: Rio Bravo | G7: Shopping Center | H7: 0 | I7: 56028.05 | J7: 74 | K7: 81.165236 | L7: 0.91172038 | M7: 348472068 | N7: 5.2143601e+08 | O7: 0.66829306 | P7: 0.71951994 | Q7: 0.095945946 | R7: 0.089189189 | S7: 0.0074324324 | T7: 0.55 | U7: 0.012035011 | V7: -0.021690115 | W7: -0.040048699 | X7: =IF(OR(B7="",G7="FI-Infra"),"",HYPERLINK("https://content.btgpactual.com/research/ativo/https://content.btgpactual.com/research/ativo/"&B7,"Link")) -> Link
B8: ADSH11 | C8: 63375304000153 | D8: - | E8: Capitânia | F8: Oliveira Trust | G8: Shopping Center | H8: 0 | I8: 17169251 | J8: 10.84 | K8: 0 | M8: 5.0917817e+08 | N8: 4.6846971e+08 | O8: 1.0868967 | P8: - | Q8: - | R8: 0.022140221 | S8: 0.0018450185 | T8: 0.02 | U8: 0.0055504446 | V8: - | W8: - | X8: =IF(OR(B8="",G8="FI-Infra"),"",HYPERLINK("https://content.btgpactual.com/research/ativo/https://content.btgpactual.com/research/ativo/"&B8,"Link")) -> Link
B9: AFHF11 | C9: 60077386000161 | D9: - | E9: AF Invest | F9: Banco Daycoval | G9: Hedge Fund | H9: 0 | I9: 89403.425 | J9: 10 | K9: 10.02 | L9: 0.99800399 | M9: 50000000 | N9: 51025266 | O9: 0.9799067 | P9: 0.97724501 | Q9: 0.1615 | R9: 0.144 | S9: 0.012 | T9: 0.12 | U9: 0.011134614 | V9: 0.1147934 | W9: 0.17553394 | X9: =IF(OR(B9="",G9="FI-Infra"),"",HYPERLINK("https://content.btgpactual.com/research/ativo/https://content.btgpactual.com/research/ativo/"&B9,"Link")) -> Link
B10: AFHI11 | C10: 36642293000158 | D10: AF Invest CRI Recebíveis FII | E10: AF Invest | F10: BTG Pactual | G10: Recebível | H10: 0.00354 | I10: 681268.43 | J10: 93.15 | K10: 93.95284 | L10: 0.99145486 | M10: 4.9265274e+08 | N10: 5.0353984e+08 | O10: 0.97837887 | P10: 1.0130099 | Q10: 0.1294686 | R10: 0.12882448 | S10: 0.010735373 | T10: 1 | U10: -0.002619798 | V10: 0.058189061 | W10: 0.16238602 | X10: =IF(OR(B10="",G10="FI-Infra"),"",HYPERLINK("https://content.btgpactual.com/research/ativo/https://content.btgpactual.com/research/ativo/"&B10,"Link")) -> Link
B11: AGRX11 | C11: 43951911000107 | D11: Exes Araguaia Fiagro-FII | E11: Éxes Gestora de Recursos | F11: Genial | G11: FIAgro - FII | H11: - | I11: 274096.55 | J11: 7.81 | K11: 8.5693506 | L11: 0.91138761 | M11: - | N11: 1.8898605e+08 | O11: - | P11: - | Q11: 0.18693982 | R11: 0.184379 | S11: 0.015364917 | T11: 0.12 | U11: -0.0090326633 | V11: 0.041360238 | W11: 0.16925284 | X11: =IF(OR(B11="",G11="FI-Infra"),"",HYPERLINK("https://content.btgpactual.com/research/ativo/https://content.btgpactual.com/research/ativo/"&B11,"Link")) -> Link
B12: AIEC11 | C12: 35765826000126 | D12: Autonomy Edifícios Corporativos FII | E12: - | F12: MAF | G12: Laje Corporativa | H12: 0 | I12: 293365.47 | J12: 64.6 | K12: 64.6 | L12: 1 | M12: 3.1169416e+08 | N12: 3.6570645e+08 | O12: 0.85230697 | P12: 0.68757596 | Q12: 0.064396285 | R12: 0.070588235 | S12: 0.0058823529 | T12: 0.38 | U12: 0.065654899 | V12: 0.27851466 | W12: 0.50746662 | X12: =IF(OR(B12="",G12="FI-Infra"),"",HYPERLINK("https://content.btgpactual.com/research/ativo/https://content.btgpactual.com/research/ativo/"&B12,"Link")) -> Link
B13: AJFI11 | C13: 51472985000199 | D13: AJ Malls FII | E13: Capitânia | F13: XP Investimentos | G13: Shopping Center | H13: 0 | I13: 934554.58 | J13: 8.3 | K13: 8.3822129 | L13: 0.99019198 | M13: 2.7909562e+08 | N13: 3.5154771e+08 | O13: 0.79390537 | P13: 0.72528443 | Q13: 0.072650602 | R13: 0.083855422 | S13: 0.0069879518 | T13: 0.058 | U13: 0.023157678 | V13: 0.083783368 | W13: 0.19234408 | X13: =IF(OR(B13="",G13="FI-Infra"),"",HYPERLINK("https://content.btgpactual.com/research/ativo/https://content.btgpactual.com/research/ativo/"&B13,"Link")) -> Link
B14: ALZC11 | C14: 40011324000140 | D14: Alianza Crédito Imobiliário FII | E14: Alianza Investimentos | F14: BTG Pactual | G14: Recebível | H14: 0 | I14: 225645.14 | J14: 7.47 | K14: 7.47 | L14: 1 | M14: 1.8189573e+08 | N14: 2.2282429e+08 | O14: 0.81631911 | P14: 0.82419992 | Q14: 0.16291834 | R14: 0.16064257 | S14: 0.013386881 | T14: 0.1 | U14: 0.019347241 | V14: 0.072841592 | W14: 0.16597329 | X14: =IF(OR(B14="",G14="FI-Infra"),"",HYPERLINK("https://content.btgpactual.com/research/ativo/https://content.btgpactual.com/research/ativo/"&B14,"Link")) -> Link
B15: ALZR11 | C15: 28737771000185 | D15: Alianza Trust Renda Imobiliária FII | E15: Alianza Investimentos | F15: BTG Pactual | G15: Híbrido | H15: 0.01161 | I15: 3349769.8 | J15: 9.97 | K15: 10.348441 | L15: 0.96343017 | M15: 1639511675 | N15: 1.7730147e+09 | O15: 0.92470283 | P15: 1.0121543 | Q15: 0.10076229 | R15: 0.10110331 | S15: 0.0084252758 | T15: 0.084 | U15: 0.0026472876 | V15: -0.011066424 | W15: 0.099154964 | X15: =IF(OR(B15="",G15="FI-Infra"),"",HYPERLINK("https://content.btgpactual.com/research/ativo/https://content.btgpactual.com/research/ativo/"&B15,"Link")) -> Link
B16: APXM11 | C16: 43010485000107 | D16: Apex Malls FII | E16: Carbyne Investimentos | F16: BTG Pactual | G16: Shopping Center | H16: 0 | I16: 106699.62 | J16: 39.5 | K16: 85.704342 | L16: 0.4608868 | M16: 111751109 | N16: 3.5465979e+08 | O16: 0.31509383 | P16: 0.70719826 | Q16: 0.11956441 | R16: 0.08323839 | S16: 0.0069365325 | T16: 0.27399303 | U16: -0.37285088 | V16: -0.5391132 | W16: -0.50857475 | X16: =IF(OR(B16="",G16="FI-Infra"),"",HYPERLINK("https://content.btgpactual.com/research/ativo/https://content.btgpactual.com/research/ativo/"&B16,"Link")) -> Link
B17: ARRI11 | C17: 32006821000121 | D17: Open K Ativos e Recebíveis Imobiliários FII | E17: Open Kapital | F17: Oliveira Trust | G17: Recebível | H17: 0 | I17: 176289.94 | J17: 4.64 | K17: 6.5043155 | L17: 0.71337253 | M17: 96173155 | N17: 1.7512428e+08 | O17: 0.54917088 | P17: 0.808837 | Q17: 0.2112069 | R17: 0.18103448 | S17: 0.015086207 | T17: 0.07 | U17: 0.01754386 | V17: -0.24690251 | W17: -0.18560782 | X17: =IF(OR(B17="",G17="FI-Infra"),"",HYPERLINK("https://content.btgpactual.com/research/ativo/https://content.btgpactual.com/research/ativo/"&B17,"Link")) -> Link
B18: ARTE11 | C18: 53193237000100 | D18: - | E18: - | F18: BTG Pactual | G18: Recebível | H18: 0 | I18: 67940.721 | J18: 7.15 | K18: 0 | M18: 67922447 | N18: 96287693 | O18: 0.70541152 | P18: - | Q18: - | R18: 0.18461538 | S18: 0.015384615 | T18: 0.11 | U18: -0.011385885 | V18: - | W18: - | X18: =IF(OR(B18="",G18="FI-Infra"),"",HYPERLINK("https://content.btgpactual.com/research/ativo/https://content.btgpactual.com/research/ativo/"&B18,"Link")) -> Link
B19: ARXD11 | C19: 44527494000132 | D19: ARX Dover Recebíveis FII | E19: ARX Investimentos | F19: Hedge | G19: Recebível | H19: 0 | I19: 63631.76 | J19: 7.58 | K19: 8.2884391 | L19: 0.91452684 | M19: 65596797 | N19: 78715004 | O19: 0.83334553 | P19: 0.84061424 | Q19: 0.14577836 | R19: 0.14248021 | S19: 0.011873351 | T19: 0.09 | U19: -0.023195876 | V19: 0.07392603 | W19: 0.17499247 | X19: =IF(OR(B19="",G19="FI-Infra"),"",HYPERLINK("https://content.btgpactual.com/research/ativo/https://content.btgpactual.com/research/ativo/"&B19,"Link")) -> Link
B20: AZPL11 | C20: 51890054000100 | D20: Az Quest Panorama Logística FII | E20: - | F20: Banco Daycoval | G20: Galpão Logístico | H20: 0.00208 | I20: 663731.47 | J20: 7.35 | K20: 7.5173945 | L20: 0.97773238 | M20: 3.0813176e+08 | N20: 3.60754e+08 | O20: 0.85413263 | P20: 0.89178953 | Q20: 0.12380952 | R20: 0.12244898 | S20: 0.010204082 | T20: 0.075 | U20: -0.0033898305 | V20: 0.030628095 | W20: 0.0908164 | X20: =IF(OR(B20="",G20="FI-Infra"),"",HYPERLINK("https://content.btgpactual.com/research/ativo/https://content.btgpactual.com/research/ativo/"&B20,"Link")) -> Link
B21: BBFO11 | C21: 37180091000102 | D21: BB Fundo de Fundos Imobiliários FII | E21: BB Asset Management | F21: BB Asset Management | G21: Fundo de Fundos | H21: 0 | I21: 405080.61 | J21: 66.1 | K21: 70.094947 | L21: 0.94300663 | M21: 264657790 | N21: 2.8134132e+08 | O21: 0.94070005 | P21: 0.83033553 | Q21: 0.15173979 | R21: 0.17246596 | S21: 0.014372163 | T21: 0.95 | U21: -0.025504939 | V21: 0.13847616 | W21: 0.23566117 | X21: =IF(OR(B21="",G21="FI-Infra"),"",HYPERLINK("https://content.btgpactual.com/research/ativo/https://content.btgpactual.com/research/ativo/"&B21,"Link")) -> Link
B22: BBGO11 | C22: 42592257000120 | D22: BB Fundo de Investimento de Crédito Fiagro-FII | E22: BB Asset Management | F22: BB Asset Management | G22: FIAgro - FII | H22: - | I22: 322826.9 | J22: 61.74 | K22: 74.979858 | L22: 0.82342114 | M22: 2.4727883e+08 | N22: 3.7340021e+08 | O22: 0.66223537 | P22: 0.83319821 | Q22: 0.17039197 | R22: 0.15549077 | S22: 0.012957564 | T22: 0.8 | U22: -0.045602102 | V22: -0.022997524 | W22: 0.10553178 | X22: =IF(OR(B22="",G22="FI-Infra"),"",HYPERLINK("https://content.btgpactual.com/research/ativo/https://content.btgpactual.com/research/ativo/"&B22,"Link")) -> Link
B23: BBIG11 | C23: 54375187000137 | D23: BB Premium Malls FII | E23: BB Asset Management | F23: BB Asset Management | G23: Shopping Center | H23: 0.00309 | I23: 1108337.9 | J23: 4.61 | K23: 7.2890515 | L23: 0.6324554 | M23: 4.5694778e+08 | N23: 9.7073328e+08 | O23: 0.47072434 | P23: 0.73113652 | Q23: 0.17787419 | R23: 0.078091106 | S23: 0.0065075922 | T23: 0.03 | U23: -0.15722121 | V23: -0.31901698 | W23: -0.25527842 | X23: =IF(OR(B23="",G23="FI-Infra"),"",HYPERLINK("https://content.btgpactual.com/research/ativo/https://content.btgpactual.com/research/ativo/"&B23,"Link")) -> Link
B24: BBRC11 | C24: 12681340000104 | D24: BB Renda Corporativa FII | E24: Tivio Capital | F24: Bem | G24: Agência Bancária | H24: 0 | I24: 70678.016 | J24: 102.06 | K24: 103.94305 | L24: 0.98188379 | M24: 162275400 | N24: 1.6472335e+08 | O24: 0.98513902 | P24: 0.96302072 | Q24: 0.14452283 | R24: 0.12345679 | S24: 0.010288066 | T24: 1.05 | U24: -0.01162115 | V24: 0.097308533 | W24: 0.18693957 | X24: =IF(OR(B24="",G24="FI-Infra"),"",HYPERLINK("https://content.btgpactual.com/research/ativo/https://content.btgpactual.com/research/ativo/"&B24,"Link")) -> Link
B25: BCIA11 | C25: 20216935000117 | D25: Bradesco Carteira Imobiliária Ativa FII | E25: - | F25: - | G25: Fundo de Fundos | H25: 0.00218 | I25: 360065.12 | J25: 86.8 | K25: 92.977744 | L25: 0.93355674 | M25: 3.228125e+08 | N25: 3.6329199e+08 | O25: 0.88857588 | P25: 0.85258465 | Q25: 0.11970046 | R25: 0.11889401 | S25: 0.0099078341 | T25: 0.86 | U25: -0.010938924 | V25: 0.054525614 | W25: 0.19145502 | X25: =IF(OR(B25="",G25="FI-Infra"),"",HYPERLINK("https://content.btgpactual.com/research/ativo/https://content.btgpactual.com/research/ativo/"&B25,"Link")) -> Link
B26: BCRI11 | C26: 22219335000138 | D26: Banestes Recebíveis Imobiliários FII | E26: Banestes DTVM | F26: BRL Trust | G26: Recebível | H26: 0.00244 | I26: 346838.47 | J26: 57.5 | K26: 65.541663 | L26: 0.87730456 | M26: 3.598277e+08 | N26: 5.3406451e+08 | O26: 0.67375325 | P26: 0.80474643 | Q26: 0.16713043 | R26: 0.16695652 | S26: 0.013913043 | T26: 0.8 | U26: -0.026908106 | V26: -0.082624692 | W26: 0.048343213 | X26: =IF(OR(B26="",G26="FI-Infra"),"",HYPERLINK("https://content.btgpactual.com/research/ativo/https://content.btgpactual.com/research/ativo/"&B26,"Link")) -> Link
B27: BDIF11 | C27: 40502607000194 | D27: BTG Pactual Dívida Infra FIC FI-Infra | E27: BTG Pactual | F27: BTG Pactual | G27: FI-Infra | H27: - | I27: 2152614.5 | J27: 68.34 | K27: 73.712369 | L27: 0.92711712 | M27: 1.2386611e+09 | N27: 1.4272615e+09 | O27: 0.86785855 | P27: - | Q27: 0.13974246 | R27: 0.14925373 | S27: 0.012437811 | T27: 0.85 | U27: -0.013921388 | V27: 0.026322057 | W27: 0.07456221 | X27: =IF(OR(B27="",G27="FI-Infra"),"",HYPERLINK("https://content.btgpactual.com/research/ativo/https://content.btgpactual.com/research/ativo/"&B27,"Link"))
B28: BIDB11 | C28: 42294971000131 | D28: Inter Infra FIC FI - Infra listado | E28: Inter | F28: Inter | G28: FI-Infra | H28: - | I28: 201660.78 | J28: 74 | K28: 78.148844 | L28: 0.946911 | M28: 1.8468646e+08 | N28: 1.9481402e+08 | O28: 0.94801424 | P28: - | Q28: 0.16216216 | R28: 0.16216216 | S28: 0.013513514 | T28: 1 | U28: -0.043927649 | V28: 0.021997345 | W28: 0.10698394 | X28: =IF(OR(B28="",G28="FI-Infra"),"",HYPERLINK("https://content.btgpactual.com/research/ativo/https://content.btgpactual.com/research/ativo/"&B28,"Link"))
B29: BINC11 | C29: 55239865000105 | D29: Bradesco FIC FI Renda Fixa Infra CDI | E29: Bradesco Asset Management | F29: Banco Bradesco | G29: FI-Infra | H29: - | I29: 785178.16 | J29: 102.9 | K29: 105.99 | L29: 0.97084631 | M29: 1.1953158e+09 | N29: 1.1703078e+09 | O29: 1.0213688 | P29: - | Q29: 0.17006803 | R29: 0.17492711 | S29: 0.014577259 | T29: 1.5 | U29: -0.010957324 | V29: 0.13091287 | W29: 0.26665811 | X29: =IF(OR(B29="",G29="FI-Infra"),"",HYPERLINK("https://content.btgpactual.com/research/ativo/https://content.btgpactual.com/research/ativo/"&B29,"Link"))
B30: BLCA11 | C30: 41076748000155 | D30: Catuaí VBI Triple A FII | E30: Patria | F30: BTG Pactual | G30: Laje Corporativa | H30: 0 | I30: 82219.908 | J30: 102.52 | K30: 104.99 | L30: 0.97647395 | M30: 164032000 | N30: 1.9902566e+08 | O30: 0.82417514 | P30: 0.73769599 | Q30: 0.099492782 | R30: 0.52672649 | S30: 0.043893874 | T30: 4.5 | U30: 0.14381806 | V30: 0.17240821 | W30: 0.21023195 | X30: =IF(OR(B30="",G30="FI-Infra"),"",HYPERLINK("https://content.btgpactual.com/research/ativo/https://content.btgpactual.com/research/ativo/"&B30,"Link")) -> Link
B31: BLMG11 | C31: 34081637000171 | D31: Bluemacaw Logística FII | E31: Bluemacaw | F31: Vórtx | G31: Galpão Logístico | H31: 0 | I31: 273254.03 | J31: 30.69 | K31: 34.309673 | L31: 0.89449993 | M31: 142555050 | N31: 2.1348918e+08 | O31: 0.667739 | P31: 0.74207244 | Q31: 0.1517074 | R31: 0.15249267 | S31: 0.012707722 | T31: 0.39 | U31: -0.10446835 | V31: -0.026455113 | W31: 0.11035084 | X31: =IF(OR(B31="",G31="FI-Infra"),"",HYPERLINK("https://content.btgpactual.com/research/ativo/https://content.btgpactual.com/research/ativo/"&B31,"Link")) -> Link
B32: BNFS11 | C32: 15570431000160 | D32: Banrisul Novas Fronteiras FII | E32: Oliveira Trust | F32: Oliveira Trust | G32: Agência Bancária | H32: 0 | I32: 33422.893 | J32: 39.3 | K32: 70.710092 | L32: 0.55579054 | M32: 27510000 | N32: 48056176 | O32: 0.57245504 | P32: 0.94645405 | Q32: 0.20992366 | R32: 0.15267176 | S32: 0.012722646 | T32: 0.5 | U32: -0.0020314881 | V32: -0.42548165 | W32: -0.36419539 | X32: =IF(OR(B32="",G32="FI-Infra"),"",HYPERLINK("https://content.btgpactual.com/research/ativo/https://content.btgpactual.com/research/ativo/"&B32,"Link")) -> Link
B33: BODB11 | C33: 41771670000199 | D33: Bocaina FIC FI-Infra | E33: Bocaina Capital | F33: BTG Pactual | G33: FI-Infra | H33: - | I33: 921585.67 | J33: 7.13 | K33: 7.7079948 | L33: 0.9250136 | M33: 4.6257371e+08 | N33: 5.1896933e+08 | O33: 0.8913315 | P33: - | Q33: 0.1598878 | R33: 0.15147265 | S33: 0.012622721 | T33: 0.09 | U33: -0.054376658 | V33: -0.01110907 | W33: 0.14308479 | X33: =IF(OR(B33="",G33="FI-Infra"),"",HYPERLINK("https://content.btgpactual.com/research/ativo/https://content.btgpactual.com/research/ativo/"&B33,"Link"))
B34: BPML11 | C34: 33046142000149 | D34: BTG Pactual Shoppings FII | E34: BTG Pactual | F34: BTG Pactual | G34: Shopping Center | H34: 0.00417 | I34: 831205.56 | J34: 82.82 | K34: 93.957069 | L34: 0.8814664 | M34: 6.1632532e+08 | N34: 8.889312e+08 | O34: 0.69333298 | P34: 0.68751429 | Q34: 0.13330113 | R34: 0.13330113 | S34: 0.011108428 | T34: 0.92 | U34: -0.0096524074 | V34: 0.056117074 | W34: 0.20957866 | X34: =IF(OR(B34="",G34="FI-Infra"),"",HYPERLINK("https://content.btgpactual.com/research/ativo/https://content.btgpactual.com/research/ativo/"&B34,"Link")) -> Link
B35: BRCO11 | C35: 20748515000181 | D35: Bresco Logística FII | E35: - | F35: Oliveira Trust | G35: Galpão Logístico | H35: 0.01363 | I35: 5135986.4 | J35: 111.84 | K35: 118.10233 | L35: 0.94697537 | M35: 2.0155025e+09 | N35: 2.0701321e+09 | O35: 0.97361058 | P35: 1.0053638 | Q35: 0.097639485 | R35: 0.097639485 | S35: 0.0081366237 | T35: 0.91 | U35: -0.019291477 | V35: 0.010814626 | W35: 0.12894551 | X35: =IF(OR(B35="",G35="FI-Infra"),"",HYPERLINK("https://content.btgpactual.com/research/ativo/https://content.btgpactual.com/research/ativo/"&B35,"Link")) -> Link
B36: BRCR11 | C36: 8924783000101 | D36: BTG Pactual Corporate Offices FII | E36: BTG Pactual | F36: BTG Pactual | G36: Laje Corporativa | H36: 0.00706 | I36: 1254897.8 | J36: 39.19 | K36: 47.523353 | L36: 0.82464719 | M36: 1.0439511e+09 | N36: 2.1579131e+09 | O36: 0.48377811 | P36: 0.53699018 | Q36: 0.12554223 | R36: 0.12554223 | S36: 0.010461853 | T36: 0.41 | U36: -0.018103263 | V36: -0.082991445 | W36: 0.084784476 | X36: =IF(OR(B36="",G36="FI-Infra"),"",HYPERLINK("https://content.btgpactual.com/research/ativo/https://content.btgpactual.com/research/ativo/"&B36,"Link")) -> Link
B37: BRFT11 | C37: 52512069000106 | D37: Bradesco Farmtech Fiagro-FIDC | E37: Bradesco Asset Management | F37: Oliveira Trust | G37: FIAgro - FIDC | H37: - | I37: 133161.37 | J37: 65 | K37: 87.439805 | L37: 0.74336854 | M37: - | O37: - | P37: - | Q37: 0.20169231 | R37: - | S37: - | T37: - | U37: -0.14453516 | V37: -0.16017564 | W37: -0.10927219 | X37: =IF(OR(B37="",G37="FI-Infra"),"",HYPERLINK("https://content.btgpactual.com/research/ativo/https://content.btgpactual.com/research/ativo/"&B37,"Link")) -> Link
B38: BROF11 | C38: 48978859000104 | D38: BRPR Corporate Offices FII | E38: BGR Asset | F38: BTG Pactual | G38: Laje Corporativa | H38: 0.00458 | I38: 760023.75 | J38: 58.3 | K38: 62.957466 | L38: 0.92602202 | M38: 6.7691034e+08 | N38: 1.259238e+09 | O38: 0.53755553 | P38: 0.51209534 | Q38: 0.11132075 | R38: 0.11526587 | S38: 0.0096054889 | T38: 0.56 | U38: -0.019307355 | V38: 0.11714695 | W38: 0.20502185 | X38: =IF(OR(B38="",G38="FI-Infra"),"",HYPERLINK("https://content.btgpactual.com/research/ativo/https://content.btgpactual.com/research/ativo/"&B38,"Link")) -> Link
B39: BSLT11 | C39: 60373688000187 | D39: - | E39: - | F39: - | G39: Outros | H39: 0 | I39: 94102.874 | J39: 58.22 | K39: 104 | L39: 0.55980769 | M39: 78597000 | N39: 1.5478162e+08 | O39: 0.50779285 | P39: 0.79255463 | Q39: - | R39: - | S39: - | T39: - | U39: -0.22373333 | V39: -0.315381 | W39: -0.42127237 | X39: =IF(OR(B39="",G39="FI-Infra"),"",HYPERLINK("https://content.btgpactual.com/research/ativo/https://content.btgpactual.com/research/ativo/"&B39,"Link")) -> Link
B40: BTAG11 | C40: 40771109000147 | D40: BTG Pactual Crédito Agrícola Fiagro FIDC | E40: BTG Pactual | F40: BTG Pactual | G40: FIAgro - FIDC | H40: - | I40: 382757.88 | J40: 97.99 | K40: 112.45192 | L40: 0.87139462 | M40: - | N40: 1.6272754e+08 | O40: - | P40: - | Q40: 0.16124094 | R40: 0.15919992 | S40: 0.01326666 | T40: 1.3 | U40: -0.017023283 | V40: -0.0093838131 | W40: 0.21600428 | X40: =IF(OR(B40="",G40="FI-Infra"),"",HYPERLINK("https://content.btgpactual.com/research/ativo/https://content.btgpactual.com/research/ativo/"&B40,"Link")) -> Link
B41: BTAL11 | C41: 36642244000115 | D41: BTG Pactual Agro Logística FII | E41: BTG Pactual | F41: BTG Pactual | G41: Agronegócio | H41: 0.00321 | I41: 510778.95 | J41: 79.44 | K41: 87.640203 | L41: 0.90643332 | M41: 4.7526855e+08 | N41: 6.9376503e+08 | O41: 0.68505694 | P41: 0.72307831 | Q41: 0.14791037 | R41: 0.1510574 | S41: 0.012588117 | T41: 1 | U41: -0.044015176 | V41: 0.034292129 | W41: 0.18625102 | X41: =IF(OR(B41="",G41="FI-Infra"),"",HYPERLINK("https://content.btgpactual.com/research/ativo/https://content.btgpactual.com/research/ativo/"&B41,"Link")) -> Link
B42: BTCI11 | C42: 9552812000114 | D42: BTG Pactual Crédito Imobiliário FII | E42: BTG Pactual | F42: BTG Pactual | G42: Recebível | H42: 0.00606 | I42: 3504861.6 | J42: 9 | K42: 9.1156418 | L42: 0.98731392 | M42: 895690548 | N42: 1.0039604e+09 | O42: 0.89215724 | P42: 0.92960381 | Q42: 0.13055556 | R42: 0.13733333 | S42: 0.011444444 | T42: 0.103 | U42: -0.0040443824 | V42: 0.048974723 | W42: 0.12285468 | X42: =IF(OR(B42="",G42="FI-Infra"),"",HYPERLINK("https://content.btgpactual.com/research/ativo/https://content.btgpactual.com/research/ativo/"&B42,"Link")) -> Link
B43: BTHF11 | C43: 45188176000157 | D43: BTG Pactual Real Estate Hedge Fund FII | E43: BTG Pactual | F43: BTG Pactual | G43: Hedge Fund | H43: 0.01187 | I43: 3245456.8 | J43: 8.53 | K43: 9.072999 | L43: 0.9401522 | M43: 1.7558744e+09 | N43: 2.0106237e+09 | O43: 0.87329839 | P43: 0.88130506 | Q43: 0.13845135 | R43: 0.14208675 | S43: 0.011840563 | T43: 0.101 | U43: -0.025157172 | V43: 0.0320575 | W43: 0.18934659 | X43: =IF(OR(B43="",G43="FI-Infra"),"",HYPERLINK("https://content.btgpactual.com/research/ativo/https://content.btgpactual.com/research/ativo/"&B43,"Link")) -> Link
B44: BTLG11 | C44: 11839593000109 | D44: BTG Pactual Logística FII | E44: BTG Pactual | F44: BTG Pactual | G44: Galpão Logístico | H44: 0.04584 | I44: 12468438 | J44: 98.37 | K44: 101.86788 | L44: 0.96566258 | M44: 6.9783935e+09 | N44: 7.5809217e+09 | O44: 0.92052045 | P44: 0.9953827 | Q44: 0.097590729 | R44: 0.098810613 | S44: 0.0082342177 | T44: 0.81 | U44: -0.016233044 | V44: 0.022844674 | W44: 0.093649125 | X44: =IF(OR(B44="",G44="FI-Infra"),"",HYPERLINK("https://content.btgpactual.com/research/ativo/https://content.btgpactual.com/research/ativo/"&B44,"Link")) -> Link
B45: BTRA11 | C45: 41076607000132 | D45: BTG Pactual Terras Agrícolas FII | E45: BTG Pactual | F45: BTG Pactual | G45: Agronegócio | H45: 0 | I45: 213741.89 | J45: 70.28 | K45: 71 | L45: 0.98985915 | M45: 2.3646121e+08 | N45: 3.8137884e+08 | O45: 0.62001659 | P45: 0.54000022 | Q45: 0.11525327 | R45: 0.15367103 | S45: 0.012805919 | T45: 0.9 | U45: 0.056683206 | V45: 0.26057853 | W45: 0.5830601 | X45: =IF(OR(B45="",G45="FI-Infra"),"",HYPERLINK("https://content.btgpactual.com/research/ativo/https://content.btgpactual.com/research/ativo/"&B45,"Link")) -> Link
B46: BTRU11 | C46: 8098114000128 | D46: - | E46: BTG Pactual | F46: BTG Pactual | H46: 0 | I46: 907818.42 | J46: 83.14 | K46: 101.20591 | L46: 0.8214935 | M46: 7.3983991e+08 | N46: 7.7297419e+08 | O46: 0.95713405 | P46: 1.2004401 | Q46: 0.12689439 | R46: 0.12268463 | S46: 0.010223719 | T46: 0.85 | U46: -0.039924468 | V46: -0.1594382 | W46: -0.052204561 | X46: =IF(OR(B46="",G46="FI-Infra"),"",HYPERLINK("https://content.btgpactual.com/research/ativo/https://content.btgpactual.com/research/ativo/"&B46,"Link")) -> Link
B47: CACR11 | C47: 32065364000146 | D47: Cartesia Recebíveis Imobiliários FII | E47: Cartesia Capital | F47: BRL Trust | G47: Recebível | H47: 0.0005 | I47: 883117.86 | J47: 16.51 | K47: 82.338338 | L47: 0.20051413 | M47: 79847709 | N47: 4.9405528e+08 | O47: 0.16161695 | P47: 1.0516692 | Q47: 0.6359782 | R47: - | S47: - | T47: - | U47: 0.048253968 | V47: -0.77838584 | W47: -0.76894412 | X47: =IF(OR(B47="",G47="FI-Infra"),"",HYPERLINK("https://content.btgpactual.com/research/ativo/https://content.btgpactual.com/research/ativo/"&B47,"Link")) -> Link
B48: CCME11 | C48: 43010844000126 | D48: Canuma Capital Multiestratégia FII | E48: Canuma Capital | F48: BTG Pactual | G48: Hedge Fund | H48: 0 | I48: 223966.74 | J48: 8.42 | K48: 8.9793 | L48: 0.93771229 | M48: 5.7085119e+08 | N48: 7.164744e+08 | O48: 0.7967503 | P48: 0.85830024 | Q48: 0.12232779 | R48: 0.12256532 | S48: 0.010213777 | T48: 0.086 | U48: -0.024650171 | V48: 0.0047164543 | W48: 0.093599503 | X48: =IF(OR(B48="",G48="FI-Infra"),"",HYPERLINK("https://content.btgpactual.com/research/ativo/https://content.btgpactual.com/research/ativo/"&B48,"Link")) -> Link
B49: CDII11 | C49: 48973783000116 | D49: Sparta Infra CDI FIC FI-Infra | E49: Sparta | F49: BTG Pactual | G49: FI-Infra | H49: - | I49: 7124571 | J49: 95.71 | K49: 101.91327 | L49: 0.93913188 | M49: 2.6302197e+09 | N49: 2.7939017e+09 | O49: 0.94141454 | P49: - | Q49: 0.16926131 | R49: 0.12537875 | S49: 0.010448229 | T49: 1 | U49: -0.029408782 | V49: -0.060782865 | W49: 0.042360146 | X49: =IF(OR(B49="",G49="FI-Infra"),"",HYPERLINK("https://content.btgpactual.com/research/ativo/https://content.btgpactual.com/research/ativo/"&B49,"Link"))
B50: CLIN11 | C50: 49005348000160 | D50: Clave Índices de Preços FII | E50: Clave | F50: BTG Pactual | G50: Recebível | H50: 0.00247 | I50: 2115819.4 | J50: 83.99 | K50: 90.246145 | L50: 0.93067687 | M50: 3.6508462e+08 | N50: 4.2944977e+08 | O50: 0.85012184 | P50: 0.90246951 | Q50: 0.14358852 | R50: 0.14287415 | S50: 0.011906179 | T50: 1 | U50: -0.038184029 | V50: 0.043573507 | W50: 0.082571829 | X50: =IF(OR(B50="",G50="FI-Infra"),"",HYPERLINK("https://content.btgpactual.com/research/ativo/https://content.btgpactual.com/research/ativo/"&B50,"Link")) -> Link
B51: CNES11 | C51: 13551286000145 | D51: FII CENESP | E51: BTG Pactual | F51: BTG Pactual | G51: Laje Corporativa | H51: 0 | I51: 33767.869 | J51: 1.38 | K51: 2.2310042 | L51: 0.61855553 | M51: 47106058 | N51: 2.1814576e+08 | O51: 0.21593846 | P51: 0.2728862 | Q51: 0.066568612 | R51: - | S51: - | T51: - | U51: 0.061538462 | V51: -0.19493271 | W51: 0.19170021 | X51: =IF(OR(B51="",G51="FI-Infra"),"",HYPERLINK("https://content.btgpactual.com/research/ativo/https://content.btgpactual.com/research/ativo/"&B51,"Link")) -> Link
B52: CPLG11 | C52: 52371756000140 | D52: Capitânia Logística FII | E52: Capitânia | F52: Vórtx | G52: Galpão Logístico | H52: 0 | I52: 124916.47 | J52: 10.95 | K52: 11.635994 | L52: 0.94104554 | M52: 6.1709546e+08 | N52: 6.0366466e+08 | O52: 1.0222488 | P52: 1.187815 | Q52: 0.15799087 | R52: 0.14246575 | S52: 0.011872146 | T52: 0.13 | U52: -0.0014690586 | V52: -0.049507667 | W52: 0.13296678 | X52: =IF(OR(B52="",G52="FI-Infra"),"",HYPERLINK("https://content.btgpactual.com/research/ativo/https://content.btgpactual.com/research/ativo/"&B52,"Link")) -> Link
B53: CPOF11 | C53: 48916699000160 | D53: Capitânia Office FII | E53: Capitânia | F53: BTG Pactual | G53: Laje Corporativa | H53: 0 | I53: 11259742 | J53: 115 | K53: 115 | L53: 1 | M53: 631267660 | N53: 6.9064514e+08 | O53: 0.91402606 | P53: 1.0258316 | Q53: 0.025565217 | R53: - | S53: - | T53: - | U53: 0 | V53: 0.057915577 | W53: 0.093962081 | X53: =IF(OR(B53="",G53="FI-Infra"),"",HYPERLINK("https://content.btgpactual.com/research/ativo/https://content.btgpactual.com/research/ativo/"&B53,"Link")) -> Link
B54: CPSH11 | C54: 47896665000199 | D54: Capitânia Shoppings FII | E54: Capitânia | F54: BTG Pactual | G54: Shopping Center | H54: 0.00518 | I54: 2208787.7 | J54: 9.61 | K54: 10.227467 | L54: 0.93962664 | M54: 1.1836045e+09 | N54: 1.4490783e+09 | O54: 0.81679821 | P54: 0.95091004 | Q54: 0.14047867 | R54: 0.13735692 | S54: 0.01144641 | T54: 0.11 | U54: 3.5439058e-05 | V54: -0.055173872 | W54: 0.17260799 | X54: =IF(OR(B54="",G54="FI-Infra"),"",HYPERLINK("https://content.btgpactual.com/research/ativo/https://content.btgpactual.com/research/ativo/"&B54,"Link")) -> Link
B55: CPTI11 | C55: 38065012000177 | D55: Capitânia Infra FIC FIRF | E55: Capitânia | F55: BTG Pactual | G55: FI-Infra | H55: - | I55: 2258273.3 | J55: 81.9 | K55: 86.075775 | L55: 0.95148722 | M55: 1.1124226e+09 | N55: 1.226901e+09 | O55: 0.90669298 | P55: - | Q55: 0.15934066 | R55: 0.16849817 | S55: 0.014041514 | T55: 1.15 | U55: -0.041924296 | V55: 0.036045659 | W55: 0.17733016 | X55: =IF(OR(B55="",G55="FI-Infra"),"",HYPERLINK("https://content.btgpactual.com/research/ativo/https://content.btgpactual.com/research/ativo/"&B55,"Link"))
B56: CPTR11 | C56: 42537579000176 | D56: Capitania Agro Strategies - Fiagro-FII | E56: Capitânia | F56: BTG Pactual | G56: FIAgro - FII | H56: - | I56: 217046.76 | J56: 7.42 | K56: 8.1002747 | L56: 0.91601832 | M56: 1.4709911e+08 | N56: 1.9560432e+08 | O56: 0.75202385 | P56: 1.0043868 | Q56: 0.17991914 | R56: 0.17789757 | S56: 0.014824798 | T56: 0.11 | U56: -0.038877571 | V56: 0.024099856 | W56: 0.17696391 | X56: =IF(OR(B56="",G56="FI-Infra"),"",HYPERLINK("https://content.btgpactual.com/research/ativo/https://content.btgpactual.com/research/ativo/"&B56,"Link")) -> Link
B57: CPTS11 | C57: 18979895000113 | D57: Capitânia Securities II FII | E57: Capitânia | F57: BTG Pactual | G57: Hedge Fund | H57: 0.01804 | I57: 7710742.7 | J57: 7.34 | K57: 7.6526571 | L57: 0.95914398 | M57: 2668113099 | N57: 3.1341999e+09 | O57: 0.85129001 | P57: 0.84417395 | Q57: 0.14645777 | R57: 0.14713896 | S57: 0.01226158 | T57: 0.09 | U57: -0.011984368 | V57: 0.039467904 | W57: 0.16024144 | X57: =IF(OR(B57="",G57="FI-Infra"),"",HYPERLINK("https://content.btgpactual.com/research/ativo/https://content.btgpactual.com/research/ativo/"&B57,"Link")) -> Link
B58: CPUR11 | C58: 34691520000100 | D58: HBC II FII | E58: Capitânia | F58: BTG Pactual | G58: Renda Urbana | H58: 0 | I58: 782631.7 | J58: 10.93 | K58: 11 | L58: 0.99363636 | M58: 7.4133539e+08 | N58: 6.7249402e+08 | O58: 1.1023673 | P58: 1.1112217 | Q58: 0.10603843 | R58: 0.10978957 | S58: 0.0091491308 | T58: 0.1 | U58: 0.026106471 | V58: 0.078789678 | W58: 0.18594127 | X58: =IF(OR(B58="",G58="FI-Infra"),"",HYPERLINK("https://content.btgpactual.com/research/ativo/https://content.btgpactual.com/research/ativo/"&B58,"Link")) -> Link
B59: CRAA11 | C59: 48903610000121 | D59: Sparta Fiagro-FII | E59: - | F59: - | G59: FIAgro - FII | H59: - | I59: 639760.12 | J59: 91 | K59: 98.718462 | L59: 0.92181339 | M59: 215655076 | N59: 2.4203231e+08 | O59: 0.89101772 | P59: - | Q59: 0.15989011 | R59: 0.16483516 | S59: 0.013736264 | T59: 1.25 | U59: 0.0014723678 | V59: 0.049417314 | W59: 0.11972667 | X59: =IF(OR(B59="",G59="FI-Infra"),"",HYPERLINK("https://content.btgpactual.com/research/ativo/https://content.btgpactual.com/research/ativo/"&B59,"Link")) -> Link
B60: CXAG11 | C60: 40189596000134 | D60: Caixa Agências FII | E60: RB Asset | F60: Oliveira Trust | G60: Agência Bancária | H60: 0 | I60: 230387.04 | J60: 72.61 | K60: 77.252197 | L60: 0.93990854 | M60: 1.5179999e+08 | N60: 2.1631902e+08 | O60: 0.70174132 | P60: 0.68768064 | Q60: 0.12009365 | R60: 0.11899187 | S60: 0.0099159895 | T60: 0.72 | U60: -0.02379672 | V60: 0.020017367 | W60: 0.12018267 | X60: =IF(OR(B60="",G60="FI-Infra"),"",HYPERLINK("https://content.btgpactual.com/research/ativo/https://content.btgpactual.com/research/ativo/"&B60,"Link")) -> Link
B61: CXCI11 | C61: 42066916000194 | D61: Caixa Carteira Imobiliária FII | E61: Caixa | F61: Caixa | G61: Fundo de Fundos | H61: 0 | I61: 102739.91 | J61: 63.5 | K61: 71.728544 | L61: 0.88528216 | M61: 130665601 | N61: 1.6188754e+08 | O61: 0.80713808 | P61: 0.7957179 | Q61: 0.14488189 | R61: 0.14173228 | S61: 0.011811024 | T61: 0.75 | U61: -0.017717964 | V61: 0.002928589 | W61: 0.12010087 | X61: =IF(OR(B61="",G61="FI-Infra"),"",HYPERLINK("https://content.btgpactual.com/research/ativo/https://content.btgpactual.com/research/ativo/"&B61,"Link")) -> Link
B62: CXCO11 | C62: 38658984000175 | D62: Caixa Imóveis Corporativos FII | E62: Patagônia Capital | F62: Vórtx | G62: Laje Corporativa | H62: 0 | I62: 192737.11 | J62: 69.88 | K62: 72.817586 | L62: 0.95965829 | M62: 274244060 | N62: 3.8159002e+08 | O62: 0.71868771 | P62: 0.69635709 | Q62: 0.12757584 | R62: 0.12879222 | S62: 0.010732685 | T62: 0.75 | U62: -0.0018568776 | V62: 0.12180258 | W62: 0.40220287 | X62: =IF(OR(B62="",G62="FI-Infra"),"",HYPERLINK("https://content.btgpactual.com/research/ativo/https://content.btgpactual.com/research/ativo/"&B62,"Link")) -> Link
B63: CXTL11 | C63: 12887506000143 | D63: Caixa Sequóia Logística FII | E63: Caixa | F63: Caixa | G63: Galpão Logístico | H63: 0 | I63: 69439.177 | J63: 220 | K63: 351.39094 | L63: 0.6260833 | M63: 11791340 | N63: 22181157 | O63: 0.53159264 | P63: 0.83198748 | Q63: 0.035160541 | R63: 0.053968024 | S63: 0.0044973353 | T63: 0.98941377 | U63: -0.026551198 | V63: -0.35022425 | W63: -0.20818249 | X63: =IF(OR(B63="",G63="FI-Infra"),"",HYPERLINK("https://content.btgpactual.com/research/ativo/https://content.btgpactual.com/research/ativo/"&B63,"Link")) -> Link
B64: CYCR11 | C64: 36501233000115 | D64: Cyrela Crédito FII | E64: CyCapital Gestora de Recursos | F64: Genial | G64: Recebível | H64: 0.00206 | I64: 617540.53 | J64: 8.35 | K64: 8.7410453 | L64: 0.95526333 | M64: 3.0518787e+08 | N64: 3.4608618e+08 | O64: 0.88182621 | P64: 0.92843586 | Q64: 0.15233533 | R64: 0.15233533 | S64: 0.012694611 | T64: 0.106 | U64: -0.018109125 | V64: 0.037433233 | W64: 0.12705179 | X64: =IF(OR(B64="",G64="FI-Infra"),"",HYPERLINK("https://content.btgpactual.com/research/ativo/https://content.btgpactual.com/research/ativo/"&B64,"Link")) -> Link
B65: CYLD11 | C65: 43010601000198 | D65: Cyrela Desenvolvimento Logístico FII | E65: CyCapital Gestora de Recursos | F65: BTG Pactual | G65: Desenvolvimento | H65: 0 | I65: 164577.2 | J65: 114.48 | K65: 125.48451 | L65: 0.91230384 | M65: 1.4216664e+08 | N65: 1.565323e+08 | O65: 0.9082256 | P65: 0.66440612 | Q65: 0.22611498 | R65: 0.68448637 | S65: 0.057040531 | T65: 6.53 | U65: 0.055190975 | V65: - | W65: 1.2087357 | X65: =IF(OR(B65="",G65="FI-Infra"),"",HYPERLINK("https://content.btgpactual.com/research/ativo/https://content.btgpactual.com/research/ativo/"&B65,"Link")) -> Link
B66: DCRA11 | C66: 42888360000111 | D66: Devant Fiagro-FII | E66: Devant Asset | F66: Banco Daycoval | G66: FIAgro - FII | H66: - | I66: 67361.249 | J66: 6.18 | K66: 7.1951357 | L66: 0.85891362 | M66: 41646433 | N66: 65332307 | O66: 0.63745541 | P66: 0.95266676 | Q66: 0.1828479 | R66: 0.17475728 | S66: 0.014563107 | T66: 0.09 | U66: -0.092458638 | V66: -0.072936 | W66: 0.030944567 | X66: =IF(OR(B66="",G66="FI-Infra"),"",HYPERLINK("https://content.btgpactual.com/research/ativo/https://content.btgpactual.com/research/ativo/"&B66,"Link")) -> Link
B67: DEVA11 | C67: 37087810000137 | D67: Devant Recebíveis Imobiliários FII | E67: Devant Asset | F67: Vórtx | G67: Recebível | H67: 0.00159 | I67: 523631.75 | J67: 16.78 | K67: 25.139857 | L67: 0.66746602 | M67: 2.3567356e+08 | N67: 1.3548673e+09 | O67: 0.17394585 | P67: 0.26498992 | Q67: 0.23718713 | R67: 0.21454112 | S67: 0.017878427 | T67: 0.3 | U67: -0.092178394 | V67: -0.27469494 | W67: -0.29300822 | X67: =IF(OR(B67="",G67="FI-Infra"),"",HYPERLINK("https://content.btgpactual.com/research/ativo/https://content.btgpactual.com/research/ativo/"&B67,"Link")) -> Link
B68: DIVS11 | C68: 58390457000130 | D68: Sparta Inflação Longa | E68: Sparta | F68: BNY | G68: FI-Infra | H68: - | I68: 1335708 | J68: 92.96 | K68: 106.36944 | L68: 0.87393519 | M68: 9.5342381e+08 | N68: 9.9434637e+08 | O68: 0.95884477 | P68: - | Q68: - | R68: - | S68: 0.012908778 | T68: 1.2 | U68: -0.017855256 | V68: 0.027603186 | W68: 0.030152803 | X68: =IF(OR(B68="",G68="FI-Infra"),"",HYPERLINK("https://content.btgpactual.com/research/ativo/https://content.btgpactual.com/research/ativo/"&B68,"Link"))
B69: DVFF11 | C69: 39863059000149 | D69: Devant Fundo de Fundos Imobiliários FII | E69: Devant Asset | F69: BRL Trust | G69: Fundo de Fundos | H69: 0 | I69: 51788.52 | J69: 5.12 | K69: 5.2780854 | L69: 0.97004872 | M69: 56368640 | N69: 88109343 | O69: 0.63975781 | P69: 0.67456035 | Q69: 0.20703125 | R69: 0.15234375 | S69: 0.012695312 | T69: 0.065 | U69: 0.0027437426 | V69: 0.0052319217 | W69: 0.030877301 | X69: =IF(OR(B69="",G69="FI-Infra"),"",HYPERLINK("https://content.btgpactual.com/research/ativo/https://content.btgpactual.com/research/ativo/"&B69,"Link")) -> Link
B70: EDGA11 | C70: 15333306000137 | D70: BM Edifício Galeria FII | E70: BTG Pactual | F70: BTG Pactual | G70: Laje Corporativa | H70: 0 | I70: 43946.297 | J70: 13 | K70: 15.490248 | L70: 0.83923769 | M70: 49556715 | N70: 1.6274962e+08 | O70: 0.30449666 | P70: 0.30373063 | Q70: 0.027022957 | R70: 0.036923077 | S70: 0.0030769231 | T70: 0.04 | U70: -0.033457249 | V70: -0.026771909 | W70: -0.091588081 | X70: =IF(OR(B70="",G70="FI-Infra"),"",HYPERLINK("https://content.btgpactual.com/research/ativo/https://content.btgpactual.com/research/ativo/"&B70,"Link")) -> Link
B71: EGAF11 | C71: 41224330000148 | D71: Ecoagro I Fiagro-FII | E71: Eco Gestão de Ativos | F71: Vórtx | G71: FIAgro - FII | H71: - | I71: 936990.99 | J71: 82.21 | K71: 92.495098 | L71: 0.88880386 | M71: 2.5747465e+08 | N71: 3.101973e+08 | O71: 0.83003511 | P71: 1.0237113 | Q71: 0.20411142 | R71: 0.2043547 | S71: 0.017029558 | T71: 1.4 | U71: -0.041137762 | V71: -0.02638018 | W71: 0.043364073 | X71: =IF(OR(B71="",G71="FI-Infra"),"",HYPERLINK("https://content.btgpactual.com/research/ativo/https://content.btgpactual.com/research/ativo/"&B71,"Link")) -> Link
B72: EMET11 | C72: 53523736000100 | D72: Emet Multiestratégia FII | E72: V2 Investimentos | F72: BRL Trust | G72: Outros | H72: 0 | I72: 160474.1 | J72: 9.95 | K72: 11.25183 | L72: 0.88430061 | M72: 49750000 | N72: 45275215 | O72: 1.0988352 | P72: 1.1510081 | Q72: 0.13869347 | R72: 0.12060302 | S72: 0.010050251 | T72: 0.1 | U72: 0.14364835 | V72: -0.034252616 | W72: 0.144186 | X72: =IF(OR(B72="",G72="FI-Infra"),"",HYPERLINK("https://content.btgpactual.com/research/ativo/https://content.btgpactual.com/research/ativo/"&B72,"Link")) -> Link
B73: EQIR11 | C73: 41076380000125 | D73: EQI Recebíveis Imobiliários FII | E73: Euqueroinvestir Gestão de Recursos | F73: BTG Pactual | G73: Recebível | H73: 0 | I73: 61523.661 | J73: 7.9 | K73: 8.3296302 | L73: 0.94842146 | M73: 86183588 | N73: 1.0515852e+08 | O73: 0.81955878 | P73: 0.85865282 | Q73: 0.15198666 | R73: 0.15189873 | S73: 0.012658228 | T73: 0.1 | U73: -0.036190158 | V73: 0.052225671 | W73: 0.18929684 | X73: =IF(OR(B73="",G73="FI-Infra"),"",HYPERLINK("https://content.btgpactual.com/research/ativo/https://content.btgpactual.com/research/ativo/"&B73,"Link")) -> Link
B74: EURO11 | C74: 5437916000127 | D74: Europar FII | E74: Coinvalores | F74: Coinvalores | G74: Galpão Logístico | H74: 0 | I74: 42870.036 | J74: 288.62 | K74: 346.38837 | L74: 0.8332266 | M74: 1.1830043e+08 | N74: 1.6189506e+08 | O74: 0.73072291 | P74: 0.74930508 | Q74: 0.091019333 | R74: 0.078996605 | S74: 0.0065830504 | T74: 1.9 | U74: -0.063226225 | V74: 0.018431161 | W74: 0.36310229 | X74: =IF(OR(B74="",G74="FI-Infra"),"",HYPERLINK("https://content.btgpactual.com/research/ativo/https://content.btgpactual.com/research/ativo/"&B74,"Link")) -> Link
B75: EXES11 | C75: 41076851000103 | D75: Éxes FII | E75: Éxes Gestora de Recursos | F75: BTG Pactual | G75: Recebível | H75: 0 | I75: 92661.431 | J75: 9.57 | K75: 9.57 | L75: 1 | M75: 1.3495092e+08 | N75: 1.3645182e+08 | O75: 0.98900052 | P75: 0.96165413 | Q75: 0.1630094 | R75: 0.1630094 | S75: 0.013584117 | T75: 0.13 | U75: 0.01579269 | V75: 0.12885357 | W75: 0.22113173 | X75: =IF(OR(B75="",G75="FI-Infra"),"",HYPERLINK("https://content.btgpactual.com/research/ativo/https://content.btgpactual.com/research/ativo/"&B75,"Link")) -> Link
B76: FAED11 | C76: 11179118000145 | D76: FII Anhanguera Educacional | E76: BTG Pactual | F76: BTG Pactual | G76: Educacional | H76: 0 | I76: 112635.41 | J76: 152.45 | K76: 155.70263 | L76: 0.97910999 | M76: 1.0555287e+08 | N76: 1.5494494e+08 | O76: 0.68122825 | P76: 0.69419027 | Q76: 0.13440502 | R76: 0.13538865 | S76: 0.011282388 | T76: 1.72 | U76: 0.014400888 | V76: 0.079130335 | W76: 0.20997868 | X76: =IF(OR(B76="",G76="FI-Infra"),"",HYPERLINK("https://content.btgpactual.com/research/ativo/https://content.btgpactual.com/research/ativo/"&B76,"Link")) -> Link
B77: FATN11 | C77: 30567216000102 | D77: BRC Renda Corporativa FII | E77: BR Capital | F77: BR Capital | G77: Laje Corporativa | H77: 0.00271 | I77: 2171285.6 | J77: 77.58 | K77: 84.671105 | L77: 0.91625118 | M77: 5.469916e+08 | N77: 6.8539561e+08 | O77: 0.79806697 | P77: 0.88997074 | Q77: 0.12374323 | R77: 0.12374323 | S77: 0.010311936 | T77: 0.8 | U77: -0.021412063 | V77: -0.022305955 | W77: 0.060009908 | X77: =IF(OR(B77="",G77="FI-Infra"),"",HYPERLINK("https://content.btgpactual.com/research/ativo/https://content.btgpactual.com/research/ativo/"&B77,"Link")) -> Link
B78: FCFL11 | C78: 11602654000101 | D78: FII Campus Faria Lima | E78: BTG Pactual | F78: BTG Pactual | G78: Educacional | H78: 0 | I78: 136280 | J78: 119.5 | K78: 125.13333 | L78: 0.95498136 | M78: 415144195 | N78: 4.3461248e+08 | O78: 0.95520542 | P78: 1.0113516 | Q78: 0.092534854 | R78: 0.093389121 | S78: 0.0077824268 | T78: 0.93 | U78: -0.012809062 | V78: 0.0068879743 | W78: 0.0448589 | X78: =IF(OR(B78="",G78="FI-Infra"),"",HYPERLINK("https://content.btgpactual.com/research/ativo/https://content.btgpactual.com/research/ativo/"&B78,"Link")) -> Link
B79: FGAA11 | C79: 42405905000191 | D79: Fg/Agro Fiagro-FII | E79: FG/A Gestora de Recursos | F79: BRL Trust | G79: FIAgro - FII | H79: - | I79: 730606.68 | J79: 7.8 | K79: 8.8233398 | L79: 0.884019 | M79: 3.516119e+08 | N79: 4.2418194e+08 | O79: 0.82891766 | P79: 1.0392226 | Q79: 0.17884615 | R79: 0.16923077 | S79: 0.014102564 | T79: 0.11 | U79: -0.032241879 | V79: -0.046815881 | W79: 0.086886567 | X79: =IF(OR(B79="",G79="FI-Infra"),"",HYPERLINK("https://content.btgpactual.com/research/ativo/https://content.btgpactual.com/research/ativo/"&B79,"Link")) -> Link
B80: FIGS11 | C80: 17590518000125 | D80: General Shopping Ativo e Renda FII | E80: Hedge Investments | F80: Hedge | G80: Shopping Center | H80: 0 | I80: 123064.97 | J80: 47.55 | K80: 50.501539 | L80: 0.94155546 | M80: 135517500 | N80: 1.99988e+08 | O80: 0.67762815 | P80: 0.66141198 | Q80: 0.12155626 | R80: 0.12113565 | S80: 0.010094637 | T80: 0.48 | U80: -0.024014778 | V80: 0.092484226 | W80: 0.13490407 | X80: =IF(OR(B80="",G80="FI-Infra"),"",HYPERLINK("https://content.btgpactual.com/research/ativo/https://content.btgpactual.com/research/ativo/"&B80,"Link")) -> Link
B81: FIIB11 | C81: 14217108000145 | D81: Industrial Do Brasil FII | E81: Coinvalores | F81: Coinvalores | G81: Galpão Logístico | H81: 0 | I81: 243546.42 | J81: 420.6 | K81: 474.46108 | L81: 0.88647946 | M81: 288111000 | N81: 4.0786124e+08 | O81: 0.70639466 | P81: 0.8044994 | Q81: 0.089491203 | R81: 0.07703281 | S81: 0.0064194009 | T81: 2.7 | U81: -0.037836849 | V81: -0.076574404 | W81: -0.099890723 | X81: =IF(OR(B81="",G81="FI-Infra"),"",HYPERLINK("https://content.btgpactual.com/research/ativo/https://content.btgpactual.com/research/ativo/"&B81,"Link")) -> Link
B82: FIIP11 | C82: 8696175000197 | D82: RB Capital Renda I FII | E82: Oliveira Trust | F82: Oliveira Trust | G82: Híbrido | H82: 0 | I82: 266143.18 | J82: 123.5 | K82: 160.15517 | L82: 0.77112717 | M82: 114504507 | N82: 1.8539616e+08 | O82: 0.61762072 | P82: 0.78840344 | Q82: 0.13651822 | R82: 0.13797571 | S82: 0.011497976 | T82: 1.42 | U82: -0.050584256 | V82: -0.1565174 | W82: -0.071509718 | X82: =IF(OR(B82="",G82="FI-Infra"),"",HYPERLINK("https://content.btgpactual.com/research/ativo/https://content.btgpactual.com/research/ativo/"&B82,"Link")) -> Link
B83: FLCR11 | C83: 33884145000151 | D83: Faria Lima Capital Recebíveis Imobiliários I FII | E83: Faria Lima Capital | F83: BRL Trust | G83: Recebível | H83: 0 | I83: 182326.08 | J83: 90.4 | K83: 93.117337 | L83: 0.97081814 | M83: 67966698 | N83: 71014333 | O83: 0.95708422 | P83: 1.0203294 | Q83: 0.1449115 | R83: 0.13938053 | S83: 0.011615044 | T83: 1.05 | U83: -0.027426501 | V83: 0.028416491 | W83: 0.10008132 | X83: =IF(OR(B83="",G83="FI-Infra"),"",HYPERLINK("https://content.btgpactual.com/research/ativo/https://content.btgpactual.com/research/ativo/"&B83,"Link")) -> Link
B84: FLMA11 | C84: 4141645000103 | D84: Continental Square Faria Lima FII | E84: BR Capital | F84: BR Capital | G84: Laje Corporativa | H84: 0 | I84: 46743.643 | J84: 151.99 | K84: 156.48418 | L84: 0.97128031 | M84: 2.0984803e+08 | N84: 3.4589388e+08 | O84: 0.60668327 | P84: 0.63523566 | Q84: 0.091650766 | R84: 0.090795447 | S84: 0.0075662873 | T84: 1.15 | U84: 0.020983275 | V84: 0.015168084 | W84: 0.23554927 | X84: =IF(OR(B84="",G84="FI-Infra"),"",HYPERLINK("https://content.btgpactual.com/research/ativo/https://content.btgpactual.com/research/ativo/"&B84,"Link")) -> Link
B85: FTCA11 | C85: 42537438000153 | D85: Fyto Recebíveis do Agro Fiagro-FII | E85: Fyto Capital | F85: BTG Pactual | G85: FIAgro - FII | H85: - | I85: 65696.942 | J85: 6.73 | K85: 9.0827236 | L85: 0.74096717 | M85: 30015477 | N85: 47318287 | O85: 0.63433144 | P85: 0.95597437 | Q85: 0.21040119 | R85: 0.14799406 | S85: 0.012332838 | T85: 0.083 | U85: -0.047196338 | V85: -0.19167391 | W85: -0.051780273 | X85: =IF(OR(B85="",G85="FI-Infra"),"",HYPERLINK("https://content.btgpactual.com/research/ativo/https://content.btgpactual.com/research/ativo/"&B85,"Link")) -> Link
B86: FVPQ11 | C86: 332266000131 | D86: Via Parque Shopping FII | E86: Hedge Investments | F86: Hedge | G86: Shopping Center | H86: 0 | I86: 40751.556 | J86: 52.99 | K86: 75.658088 | L86: 0.70038778 | M86: 1.483799e+08 | N86: 2.5803731e+08 | O86: 0.57503271 | P86: 0.76524614 | Q86: 0.068880921 | R86: 0.10190602 | S86: 0.0084921683 | T86: 0.45 | U86: 0.016302263 | V86: -0.21371962 | W86: -0.19963235 | X86: =IF(OR(B86="",G86="FI-Infra"),"",HYPERLINK("https://content.btgpactual.com/research/ativo/https://content.btgpactual.com/research/ativo/"&B86,"Link")) -> Link
B87: FYTO11 | C87: 18085673000157 | D87: Fyto Recebíveis Imobiliários FII | E87: Fyto Capital | F87: BTG Pactual | G87: Recebível | H87: 0 | I87: 124217.64 | J87: 7.96 | K87: 8.3283921 | L87: 0.95576672 | M87: 1.2163985e+08 | N87: 1.5261974e+08 | O87: 0.79701257 | P87: 0.86103866 | Q87: 0.15189698 | R87: 0.15075377 | S87: 0.012562814 | T87: 0.1 | U87: -0.016996084 | V87: 0.029000433 | W87: 0.15979949 | X87: =IF(OR(B87="",G87="FI-Infra"),"",HYPERLINK("https://content.btgpactual.com/research/ativo/https://content.btgpactual.com/research/ativo/"&B87,"Link")) -> Link
B88: GAME11 | C88: 41269052000145 | D88: Guardian Multiestratégia I FII | E88: Guardian | F88: Banco Daycoval | G88: Recebível | H88: 0 | I88: 291521.05 | J88: 8.36 | K88: 8.724531 | L88: 0.9582177 | M88: 2.3764242e+08 | N88: 2.6514462e+08 | O88: 0.89627473 | P88: 0.91961559 | Q88: 0.14055024 | R88: 0.14354067 | S88: 0.011961722 | T88: 0.1 | U88: 0.023047362 | V88: 0.03071472 | W88: 0.12841394 | X88: =IF(OR(B88="",G88="FI-Infra"),"",HYPERLINK("https://content.btgpactual.com/research/ativo/https://content.btgpactual.com/research/ativo/"&B88,"Link")) -> Link
B89: GARE11 | C89: 37295919000160 | D89: Guardian Real Estate FII | E89: Guardian | F89: Banco Daycoval | G89: Renda Urbana | H89: 0.01609 | I89: 10182116 | J89: 8.23 | K89: 8.4667229 | L89: 0.97204079 | M89: 2.3800044e+09 | N89: 2.6338417e+09 | O89: 0.90362468 | P89: 0.96270049 | Q89: 0.12102066 | R89: 0.12102066 | S89: 0.010085055 | T89: 0.083 | U89: 0.010187799 | V89: -0.01755215 | W89: 0.0168923 | X89: =IF(OR(B89="",G89="FI-Infra"),"",HYPERLINK("https://content.btgpactual.com/research/ativo/https://content.btgpactual.com/research/ativo/"&B89,"Link")) -> Link
B90: GCRA11 | C90: 37037297000170 | D90: Galapagos Recebiveis do Agronegocio Fiagro-FII | E90: Galapagos Capital | F90: Singulare | G90: FIAgro - FII | H90: - | I90: 175486.44 | J90: 47.6 | K90: 60.261123 | L90: 0.78989567 | M90: 83341174 | N90: 1.4906844e+08 | O90: 0.55907993 | P90: 0.98534229 | Q90: 0.1710084 | R90: 0.17142857 | S90: 0.014285714 | T90: 0.68 | U90: -0.04157792 | V90: -0.0022174866 | W90: 0.08876723 | X90: =IF(OR(B90="",G90="FI-Infra"),"",HYPERLINK("https://content.btgpactual.com/research/ativo/https://content.btgpactual.com/research/ativo/"&B90,"Link")) -> Link
B91: GCRI11 | C91: 38293897000161 | D91: Galapagos Recebíveis Imobiliários FII | E91: Galapagos Capital | F91: BTG Pactual | G91: Recebível | H91: 0 | I91: 195513.29 | J91: 65.5 | K91: 67.539785 | L91: 0.96979877 | M91: 95227764 | N91: 1.341895e+08 | O91: 0.70965137 | P91: 0.71912245 | Q91: 0.15465649 | R91: 0.15572519 | S91: 0.012977099 | T91: 0.85 | U91: 0.0095420332 | V91: 0.10162364 | W91: 0.21820784 | X91: =IF(OR(B91="",G91="FI-Infra"),"",HYPERLINK("https://content.btgpactual.com/research/ativo/https://content.btgpactual.com/research/ativo/"&B91,"Link")) -> Link
B92: GGRC11 | C92: 26614291000100 | D92: GGR Covepi Renda FII | E92: Zagros Capital | F92: Vórtx | G92: Galpão Logístico | H92: 0.01312 | I92: 14955584 | J92: 9.06 | K92: 10.002555 | L92: 0.90576856 | M92: 1.9410748e+09 | N92: 2.3784936e+09 | O92: 0.81609417 | P92: 0.88231354 | Q92: 0.13245033 | R92: 0.13245033 | S92: 0.011037528 | T92: 0.1 | U92: -0.087548713 | V92: -0.0089866662 | W92: 0.067338015 | X92: =IF(OR(B92="",G92="FI-Infra"),"",HYPERLINK("https://content.btgpactual.com/research/ativo/https://content.btgpactual.com/research/ativo/"&B92,"Link")) -> Link
B93: GLPF11 | C93: 58378463000171 | D93: - | E93: Galapagos Capital | F93: Vórtx | G93: Galpão Logístico | H93: 0 | I93: 52862.427 | J93: 109.45 | K93: 109.45 | L93: 1 | M93: 164722250 | N93: 1.6099578e+08 | O93: 1.0231464 | P93: 1.0455133 | Q93: 0.093695751 | R93: 0.1589767 | S93: 0.013248058 | T93: 1.45 | U93: 0.0096630274 | V93: 0.099966569 | W93: 0.14652299 | X93: =IF(OR(B93="",G93="FI-Infra"),"",HYPERLINK("https://content.btgpactual.com/research/ativo/https://content.btgpactual.com/research/ativo/"&B93,"Link")) -> Link
B94: GRUL11 | C94: 54483412000159 | D94: Icatu Vanguarda GRU Logístico FII | E94: Icatu Vanguarda | F94: Banco Daycoval | G94: Galpão Logístico | H94: 0 | I94: 238942 | J94: 8.06 | K94: 8.95424 | L94: 0.90013222 | M94: 199082000 | N94: 2.3932546e+08 | O94: 0.8318463 | P94: 0.93999129 | Q94: 0.1191067 | R94: 0.1191067 | S94: 0.0099255583 | T94: 0.08 | U94: -0.026570048 | V94: -0.045293107 | W94: 0.12255916 | X94: =IF(OR(B94="",G94="FI-Infra"),"",HYPERLINK("https://content.btgpactual.com/research/ativo/https://content.btgpactual.com/research/ativo/"&B94,"Link")) -> Link
B95: GSFI11 | C95: 11769604000113 | D95: General Shopping e Outlets do Brasil FII | E95: Capitânia | F95: Planner | G95: Shopping Center | H95: 0 | I95: 11013194 | J95: 11.1 | K95: 11.99 | L95: 0.92577148 | M95: 1.0668221e+09 | N95: 1.2198244e+09 | O95: 0.87457028 | P95: 0.8103367 | Q95: - | R95: - | S95: - | T95: - | U95: -0.071129707 | V95: 0.012045993 | W95: 0.23283565 | X95: =IF(OR(B95="",G95="FI-Infra"),"",HYPERLINK("https://content.btgpactual.com/research/ativo/https://content.btgpactual.com/research/ativo/"&B95,"Link")) -> Link
B96: GTWR11 | C96: 23740527000158 | D96: Green Towers FII | E96: Tivio Capital | F96: Bem | G96: Laje Corporativa | H96: 0.00634 | I96: 683578.76 | J96: 78.05 | K96: 83.308849 | L96: 0.93687526 | M96: 936600000 | N96: 1.2164542e+09 | O96: 0.76994266 | P96: 0.80962466 | Q96: 0.13837284 | R96: 0.014606022 | S96: 0.0012171685 | T96: 0.095 | U96: -0.016135132 | V96: 0.02537863 | W96: 0.17107412 | X96: =IF(OR(B96="",G96="FI-Infra"),"",HYPERLINK("https://content.btgpactual.com/research/ativo/https://content.btgpactual.com/research/ativo/"&B96,"Link")) -> Link
B97: GZIT11 | C97: 15447108000102 | D97: Gazit Malls FII | E97: BTG Pactual | F97: BTG Pactual | G97: Shopping Center | H97: 0.00547 | I97: 408066.77 | J97: 37.03 | K97: 47.157719 | L97: 0.78523731 | M97: 8.6271887e+08 | N97: 2.0244509e+09 | O97: 0.42614957 | P97: 0.51023189 | Q97: 0.19443694 | R97: 0.13610586 | S97: 0.011342155 | T97: 0.42 | U97: -0.086581154 | V97: -0.14218843 | W97: -0.0020717713 | X97: =IF(OR(B97="",G97="FI-Infra"),"",HYPERLINK("https://content.btgpactual.com/research/ativo/https://content.btgpactual.com/research/ativo/"&B97,"Link")) -> Link
B98: HABT11 | C98: 30578417000105 | D98: Habitat II FII | E98: Vista Real Estate | F98: XP Investimentos | G98: Recebível | H98: 0.00358 | I98: 1102674.7 | J98: 65.2 | K98: 74.385294 | L98: 0.87651734 | M98: 5.2986625e+08 | N98: 7.6639117e+08 | O98: 0.69137833 | P98: 0.79269858 | Q98: 0.17668712 | R98: 0.17484663 | S98: 0.014570552 | T98: 0.95 | U98: -0.077532541 | V98: -0.055531933 | W98: -0.037804542 | X98: =IF(OR(B98="",G98="FI-Infra"),"",HYPERLINK("https://content.btgpactual.com/research/ativo/https://content.btgpactual.com/research/ativo/"&B98,"Link")) -> Link
B99: HCRI11 | C99: 4066582000160 | D99: FII Hospital da Criança | E99: BTG Pactual | F99: BTG Pactual | G99: Hospital | H99: 0 | I99: 37732.931 | J99: 279.5 | K99: 309.28325 | L99: 0.90370236 | M99: 55900000 | N99: 65911172 | O99: 0.84811116 | P99: 1.0311693 | Q99: 0.18171962 | R99: 0.10948122 | S99: 0.0091234348 | T99: 2.55 | U99: 0.045031023 | V99: 0.054640545 | W99: 0.29712593 | X99: =IF(OR(B99="",G99="FI-Infra"),"",HYPERLINK("https://content.btgpactual.com/research/ativo/https://content.btgpactual.com/research/ativo/"&B99,"Link")) -> Link
B100: HCTR11 | C100: 30248180000196 | D100: Hectare CE FII | E100: Hectare Capital | F100: Vórtx | G100: Recebível | H100: 0.00206 | I100: 606898.75 | J100: 13.75 | K100: 20.977021 | L100: 0.65547914 | M100: 3.0365779e+08 | N100: 2.2378511e+09 | O100: 0.13569169 | P100: 0.1984928 | Q100: 0.24654545 | R100: 0.20945455 | S100: 0.017454545 | T100: 0.24 | U100: -0.15415885 | V100: -0.26293308 | W100: -0.26060396 | X100: =IF(OR(B100="",G100="FI-Infra"),"",HYPERLINK("https://content.btgpactual.com/research/ativo/https://content.btgpactual.com/research/ativo/"&B100,"Link")) -> Link
B101: HFOF11 | C101: 18307582000119 | D101: Hedge Top FOFII 3 FII | E101: Hedge Investments | F101: Hedge | G101: Fundo de Fundos | H101: 0.00943 | I101: 2090390.7 | J101: 6.18 | K101: 6.7292444 | L101: 0.91837948 | M101: 1349897400 | N101: 1.6664009e+09 | O101: 0.81006759 | P101: 0.8410921 | Q101: 0.11326861 | R101: 0.11650485 | S101: 0.0097087379 | T101: 0.06 | U101: -0.026771654 | V101: 0.0004361858 | W101: 0.17611109 | X101: =IF(OR(B101="",G101="FI-Infra"),"",HYPERLINK("https://content.btgpactual.com/research/ativo/https://content.btgpactual.com/research/ativo/"&B101,"Link")) -> Link
...

Sheet FIAgro
D2: Menu | H2: Menu
T3: Retorno
E4: Características | H4: Volume de Negociação | I4: Fechamento | J4: Máximo | L4: Valor de Mercado | M4: Valor Patrimonial | N4: P/VPA | P4: Dividend Yield (% ao ano) | T4: No Mês | U4: No Ano | V4: LTM | W4: Análises
B5: Código | C5: CNPJ | D5: Nome | E5: Gestor | F5: Administrador | G5: Tipo | H5: Média - 3 Meses (R$) | I5: R$ | J5: R$ | K5: % | L5: R$ | M5: R$ | N5: Atual | O5: 2025 | P5: LTM | Q5: Anualizado | R5: Última Dist. (%) | S5: Div. do Mês (R$) | T5: % | U5: % | V5: % | W5: -
B6: AAZQ11 | C6: 44625826000111 | D6: Az Quest Sole Fiagro-FII | E6: AZ Quest | F6: XP Investimentos | G6: FIAgro - FII | H6: 383825.05 | I6: 6.31 | J6: 8.0364233 | K6: 0.78517517 | L6: 1.5167526e+08 | M6: 2.0764849e+08 | N6: 0.73044239 | O6: 1.0183375 | P6: 0.20166403 | Q6: 0.17115689 | R6: 0.014263074 | S6: 0.09 | T6: -0.049698795 | U6: -0.20007913 | V6: -0.0079482424 | W6: =IF(OR(B6="",G6="FI-Infra"),"",HYPERLINK("https://content.btgpactual.com/research/ativo/https://content.btgpactual.com/research/ativo/"&B6,"Link")) -> Link
B7: AGRX11 | C7: 43951911000107 | D7: Exes Araguaia Fiagro-FII | E7: Éxes Gestora de Recursos | F7: Genial | G7: FIAgro - FII | H7: 274096.55 | I7: 7.81 | J7: 8.5693506 | K7: 0.91138761 | L7: - | M7: 1.8898605e+08 | N7: - | O7: - | P7: 0.18693982 | Q7: 0.184379 | R7: 0.015364917 | S7: 0.12 | T7: -0.0090326633 | U7: 0.041360238 | V7: 0.16925284 | W7: =IF(OR(B7="",G7="FI-Infra"),"",HYPERLINK("https://content.btgpactual.com/research/ativo/https://content.btgpactual.com/research/ativo/"&B7,"Link")) -> Link
B8: BBGO11 | C8: 42592257000120 | D8: BB Fundo de Investimento de Crédito Fiagro-FII | E8: BB Asset Management | F8: BB Asset Management | G8: FIAgro - FII | H8: 322826.9 | I8: 61.74 | J8: 74.979858 | K8: 0.82342114 | L8: 2.4727883e+08 | M8: 3.7340021e+08 | N8: 0.66223537 | O8: 0.83319821 | P8: 0.17039197 | Q8: 0.15549077 | R8: 0.012957564 | S8: 0.8 | T8: -0.045602102 | U8: -0.022997524 | V8: 0.10553178 | W8: =IF(OR(B8="",G8="FI-Infra"),"",HYPERLINK("https://content.btgpactual.com/research/ativo/https://content.btgpactual.com/research/ativo/"&B8,"Link")) -> Link
B9: BRFT11 | C9: 52512069000106 | D9: Bradesco Farmtech Fiagro-FIDC | E9: Bradesco Asset Management | F9: Oliveira Trust | G9: FIAgro - FIDC | H9: 133161.37 | I9: 65 | J9: 87.439805 | K9: 0.74336854 | L9: - | N9: - | O9: - | P9: 0.20169231 | Q9: - | R9: - | S9: - | T9: -0.14453516 | U9: -0.16017564 | V9: -0.10927219 | W9: =IF(OR(B9="",G9="FI-Infra"),"",HYPERLINK("https://content.btgpactual.com/research/ativo/https://content.btgpactual.com/research/ativo/"&B9,"Link")) -> Link
B10: BTAG11 | C10: 40771109000147 | D10: BTG Pactual Crédito Agrícola Fiagro FIDC | E10: BTG Pactual | F10: BTG Pactual | G10: FIAgro - FIDC | H10: 382757.88 | I10: 97.99 | J10: 112.45192 | K10: 0.87139462 | L10: - | M10: 1.6272754e+08 | N10: - | O10: - | P10: 0.16124094 | Q10: 0.15919992 | R10: 0.01326666 | S10: 1.3 | T10: -0.017023283 | U10: -0.0093838131 | V10: 0.21600428 | W10: =IF(OR(B10="",G10="FI-Infra"),"",HYPERLINK("https://content.btgpactual.com/research/ativo/https://content.btgpactual.com/research/ativo/"&B10,"Link")) -> Link
B11: CPTR11 | C11: 42537579000176 | D11: Capitania Agro Strategies - Fiagro-FII | E11: Capitânia | F11: BTG Pactual | G11: FIAgro - FII | H11: 217046.76 | I11: 7.42 | J11: 8.1002747 | K11: 0.91601832 | L11: 1.4709911e+08 | M11: 1.9560432e+08 | N11: 0.75202385 | O11: 1.0043868 | P11: 0.17991914 | Q11: 0.17789757 | R11: 0.014824798 | S11: 0.11 | T11: -0.038877571 | U11: 0.024099856 | V11: 0.17696391 | W11: =IF(OR(B11="",G11="FI-Infra"),"",HYPERLINK("https://content.btgpactual.com/research/ativo/https://content.btgpactual.com/research/ativo/"&B11,"Link")) -> Link
B12: CRAA11 | C12: 48903610000121 | D12: Sparta Fiagro-FII | E12: - | F12: - | G12: FIAgro - FII | H12: 639760.12 | I12: 91 | J12: 98.718462 | K12: 0.92181339 | L12: 215655076 | M12: 2.4203231e+08 | N12: 0.89101772 | O12: - | P12: 0.15989011 | Q12: 0.16483516 | R12: 0.013736264 | S12: 1.25 | T12: 0.0014723678 | U12: 0.049417314 | V12: 0.11972667 | W12: =IF(OR(B12="",G12="FI-Infra"),"",HYPERLINK("https://content.btgpactual.com/research/ativo/https://content.btgpactual.com/research/ativo/"&B12,"Link")) -> Link
B13: DCRA11 | C13: 42888360000111 | D13: Devant Fiagro-FII | E13: Devant Asset | F13: Banco Daycoval | G13: FIAgro - FII | H13: 67361.249 | I13: 6.18 | J13: 7.1951357 | K13: 0.85891362 | L13: 41646433 | M13: 65332307 | N13: 0.63745541 | O13: 0.95266676 | P13: 0.1828479 | Q13: 0.17475728 | R13: 0.014563107 | S13: 0.09 | T13: -0.092458638 | U13: -0.072936 | V13: 0.030944567 | W13: =IF(OR(B13="",G13="FI-Infra"),"",HYPERLINK("https://content.btgpactual.com/research/ativo/https://content.btgpactual.com/research/ativo/"&B13,"Link")) -> Link
B14: EGAF11 | C14: 41224330000148 | D14: Ecoagro I Fiagro-FII | E14: Eco Gestão de Ativos | F14: Vórtx | G14: FIAgro - FII | H14: 936990.99 | I14: 82.21 | J14: 92.495098 | K14: 0.88880386 | L14: 2.5747465e+08 | M14: 3.101973e+08 | N14: 0.83003511 | O14: 1.0237113 | P14: 0.20411142 | Q14: 0.2043547 | R14: 0.017029558 | S14: 1.4 | T14: -0.041137762 | U14: -0.02638018 | V14: 0.043364073 | W14: =IF(OR(B14="",G14="FI-Infra"),"",HYPERLINK("https://content.btgpactual.com/research/ativo/https://content.btgpactual.com/research/ativo/"&B14,"Link")) -> Link
B15: FGAA11 | C15: 42405905000191 | D15: Fg/Agro Fiagro-FII | E15: FG/A Gestora de Recursos | F15: BRL Trust | G15: FIAgro - FII | H15: 730606.68 | I15: 7.8 | J15: 8.8233398 | K15: 0.884019 | L15: 3.516119e+08 | M15: 4.2418194e+08 | N15: 0.82891766 | O15: 1.0392226 | P15: 0.17884615 | Q15: 0.16923077 | R15: 0.014102564 | S15: 0.11 | T15: -0.032241879 | U15: -0.046815881 | V15: 0.086886567 | W15: =IF(OR(B15="",G15="FI-Infra"),"",HYPERLINK("https://content.btgpactual.com/research/ativo/https://content.btgpactual.com/research/ativo/"&B15,"Link")) -> Link
B16: FTCA11 | C16: 42537438000153 | D16: Fyto Recebíveis do Agro Fiagro-FII | E16: Fyto Capital | F16: BTG Pactual | G16: FIAgro - FII | H16: 65696.942 | I16: 6.73 | J16: 9.0827236 | K16: 0.74096717 | L16: 30015477 | M16: 47318287 | N16: 0.63433144 | O16: 0.95597437 | P16: 0.21040119 | Q16: 0.14799406 | R16: 0.012332838 | S16: 0.083 | T16: -0.047196338 | U16: -0.19167391 | V16: -0.051780273 | W16: =IF(OR(B16="",G16="FI-Infra"),"",HYPERLINK("https://content.btgpactual.com/research/ativo/https://content.btgpactual.com/research/ativo/"&B16,"Link")) -> Link
B17: GCRA11 | C17: 37037297000170 | D17: Galapagos Recebiveis do Agronegocio Fiagro-FII | E17: Galapagos Capital | F17: Singulare | G17: FIAgro - FII | H17: 175486.44 | I17: 47.6 | J17: 60.261123 | K17: 0.78989567 | L17: 83341174 | M17: 1.4906844e+08 | N17: 0.55907993 | O17: 0.98534229 | P17: 0.1710084 | Q17: 0.17142857 | R17: 0.014285714 | S17: 0.68 | T17: -0.04157792 | U17: -0.0022174866 | V17: 0.08876723 | W17: =IF(OR(B17="",G17="FI-Infra"),"",HYPERLINK("https://content.btgpactual.com/research/ativo/https://content.btgpactual.com/research/ativo/"&B17,"Link")) -> Link
B18: IAAG11 | C18: 42692399000169 | D18: Inter Amerra - Fiagro-FII | E18: - | F18: - | G18: FIAgro - FII | H18: 214195.09 | I18: 7.13 | J18: 8.4284745 | K18: 0.84594193 | L18: 74538275 | M18: 1.0254469e+08 | N18: 0.72688575 | O18: - | P18: 0.20056101 | Q18: 0.16830295 | R18: 0.014025245 | S18: 0.1 | T18: -0.11975309 | U18: -0.10514327 | V18: 0.10768676 | W18: =IF(OR(B18="",G18="FI-Infra"),"",HYPERLINK("https://content.btgpactual.com/research/ativo/https://content.btgpactual.com/research/ativo/"&B18,"Link")) -> Link
B19: JGPX11 | C19: 42888292000190 | D19: JGP Fiagro-FII | E19: JGP Gestão de Crédito | F19: Banco Daycoval | G19: FIAgro - FII | H19: 460275.61 | I19: 57.6 | J19: 68.139568 | K19: 0.84532382 | L19: 1.2333588e+08 | M19: 2.0592887e+08 | N19: 0.5989247 | O19: 0.99470902 | P19: 0.19965278 | Q19: 0.20833333 | R19: 0.017361111 | S19: 1 | T19: -0.018739353 | U19: -0.15467618 | V19: -0.046783319 | W19: =IF(OR(B19="",G19="FI-Infra"),"",HYPERLINK("https://content.btgpactual.com/research/ativo/https://content.btgpactual.com/research/ativo/"&B19,"Link")) -> Link
B20: KDOL11 | C20: 51641681000108 | D20: Kinea Agro Income USD Fiagro-FII | E20: Kinea | F20: Intrag | G20: FIAgro - FII | H20: 77320.659 | I20: 87 | J20: 96.533234 | K20: 0.90124402 | L20: 58375434 | M20: 65919150 | N20: 0.88556109 | O20: - | P20: 0.060574713 | Q20: 0.062068966 | R20: 0.0051724138 | S20: 0.45 | T20: 0.035098156 | U20: -0.041723508 | V20: -0.013177087 | W20: =IF(OR(B20="",G20="FI-Infra"),"",HYPERLINK("https://content.btgpactual.com/research/ativo/https://content.btgpactual.com/research/ativo/"&B20,"Link")) -> Link
B21: KNCA11 | C21: 41745701000137 | D21: Kinea Crédito Agro Fiagro-FII | E21: Kinea | F21: Intrag | G21: FIAgro - FII | H21: 3436877.5 | I21: 87 | J21: 92.570243 | K21: 0.93982685 | L21: 1879192953 | M21: 2.2175578e+09 | N21: 0.84741553 | O21: 1.0372589 | P21: 0.14816092 | Q21: 0.13793103 | R21: 0.011494253 | S21: 1 | T21: -0.025100852 | U21: -0.022068097 | V21: 0.07401949 | W21: =IF(OR(B21="",G21="FI-Infra"),"",HYPERLINK("https://content.btgpactual.com/research/ativo/https://content.btgpactual.com/research/ativo/"&B21,"Link")) -> Link
B22: KOPA11 | C22: 51475461000151 | D22: Kinea Oportunidades Agro I Fiagro-FII | E22: Kinea | F22: Intrag | G22: FIAgro - FII | H22: 150651.8 | I22: 222.22 | J22: 272.72078 | K22: 0.81482605 | L22: 78816323 | M22: 3.4988538e+08 | N22: 0.22526326 | O22: - | P22: 0.47092971 | Q22: 0.21600216 | R22: 0.01800018 | S22: 4 | T22: -0.16844318 | U22: -0.013127368 | V22: 0.061449462 | W22: =IF(OR(B22="",G22="FI-Infra"),"",HYPERLINK("https://content.btgpactual.com/research/ativo/https://content.btgpactual.com/research/ativo/"&B22,"Link")) -> Link
B23: LSAG11 | C23: 42592476000109 | D23: Leste Fiagro | E23: Leste Credit Gestão de Recursos | F23: Genial | G23: FIAgro - FII | H23: 71105.448 | I23: 74.24 | J23: 82.935557 | K23: 0.89515285 | L23: 74932956 | M23: 99162873 | N23: 0.75565536 | O23: 1.121254 | P23: 0.17281789 | Q23: 0.16163793 | R23: 0.013469828 | S23: 1 | T23: -0.039710257 | U23: -0.026481475 | V23: 0.16157391 | W23: =IF(OR(B23="",G23="FI-Infra"),"",HYPERLINK("https://content.btgpactual.com/research/ativo/https://content.btgpactual.com/research/ativo/"&B23,"Link")) -> Link
B24: NEXG11 | C24: 52044477000172 | D24: NEX Crédito Agro Fiagro-FII | E24: NEX Gestão de Recursos | F24: Vórtx | G24: FIAgro - FII | H24: 273021.86 | I24: 129.5 | J24: 133.07308 | K24: 0.97314947 | L24: 159614448 | M24: 69989312 | N24: 1.2924223 | O24: - | P24: 0.085482625 | Q24: 0.085250965 | R24: 0.0071042471 | S24: 0.92 | T24: -0.026850529 | U24: 0.099007518 | V24: 0.29527162 | W24: =IF(OR(B24="",G24="FI-Infra"),"",HYPERLINK("https://content.btgpactual.com/research/ativo/https://content.btgpactual.com/research/ativo/"&B24,"Link")) -> Link
B25: OIAG11 | C25: 41218352000103 | D25: Ourinvest Innovation Fiagro-FII | E25: Fator ORE | F25: Singulare | G25: FIAgro - FII | H25: 122735.86 | I25: 7.83 | J25: 8.8064094 | K25: 0.88912514 | L25: 70728382 | M25: 88536764 | N25: 0.79885891 | O25: 1.0433465 | P25: 0.18199234 | Q25: 0.17624521 | R25: 0.014687101 | S25: 0.115 | T25: -0.023047154 | U25: 0.013168618 | V25: 0.20520693 | W25: =IF(OR(B25="",G25="FI-Infra"),"",HYPERLINK("https://content.btgpactual.com/research/ativo/https://content.btgpactual.com/research/ativo/"&B25,"Link")) -> Link
B26: PLCA11 | C26: 41272747000186 | D26: Plural BRB Crédito Agro Fiagro-FII | E26: Plural Gestão de Recursos | F26: Genial | G26: FIAgro - FII | H26: 54387.55 | I26: 69.4 | J26: 75.932367 | K26: 0.91397124 | L26: 38657119 | M26: 53136654 | N26: 0.72750382 | O26: 0.99815874 | P26: 0.17795389 | Q26: 0.1815562 | R26: 0.015129683 | S26: 1.05 | T26: -0.045916965 | U26: 0.063663994 | V26: 0.16435742 | W26: =IF(OR(B26="",G26="FI-Infra"),"",HYPERLINK("https://content.btgpactual.com/research/ativo/https://content.btgpactual.com/research/ativo/"&B26,"Link")) -> Link
B27: RURA11 | C27: 42479593000160 | D27: Itaú Asset Rural Fiagro-FII | E27: Itaú Unibanco | F27: Intrag | G27: FIAgro - FII | H27: 2726907.4 | I27: 8.15 | J27: 8.6817948 | K27: 0.93874598 | L27: 1.304811e+09 | M27: 1.6388061e+09 | N27: 0.79619607 | O27: 1.0206706 | P27: 0.16539877 | Q27: 0.16196319 | R27: 0.013496933 | S27: 0.11 | T27: 0.0024600246 | U27: 0.028984216 | V27: 0.18608605 | W27: =IF(OR(B27="",G27="FI-Infra"),"",HYPERLINK("https://content.btgpactual.com/research/ativo/https://content.btgpactual.com/research/ativo/"&B27,"Link")) -> Link
B28: RZAG11 | C28: 40413979000144 | D28: Riza Fiagro-FII | E28: Riza | F28: Genial | G28: FIAgro - FII | H28: 1357714.3 | I28: 8.31 | J28: 8.8756433 | K28: 0.93627017 | L28: 5.6541593e+08 | M28: 6.549998e+08 | N28: 0.86323069 | O28: 0.96392798 | P28: 0.17990373 | Q28: 0.18050542 | R28: 0.015042118 | S28: 0.125 | T28: -0.00060132291 | U28: -0.026865784 | V28: 0.11965199 | W28: =IF(OR(B28="",G28="FI-Infra"),"",HYPERLINK("https://content.btgpactual.com/research/ativo/https://content.btgpactual.com/research/ativo/"&B28,"Link")) -> Link
B29: SNAG11 | C29: 28152777000190 | D29: Suno Agro Fiagro-FII | E29: Suno | F29: Singulare | G29: FIAgro - FII | H29: 1954324.8 | I29: 9.69 | J29: 10.307168 | K29: 0.94012245 | L29: 5.8857402e+08 | M29: 6.2655227e+08 | N29: 0.93938535 | O29: 1.0063385 | P29: 0.1630547 | Q29: 0.14860681 | R29: 0.012383901 | S29: 0.12 | T29: -0.0062154953 | U29: -0.027556445 | V29: 0.19626793 | W29: =IF(OR(B29="",G29="FI-Infra"),"",HYPERLINK("https://content.btgpactual.com/research/ativo/https://content.btgpactual.com/research/ativo/"&B29,"Link")) -> Link
B30: SNFZ11 | C30: 53313475000102 | D30: Suno Fazendas Fiagro-FII | E30: Suno | F30: Singulare | G30: FIAgro - FII | H30: 218214.23 | I30: 9.12 | J30: 9.5432075 | K30: 0.95565354 | L30: 1.1025995e+08 | M30: 62625277 | N30: 0.90324983 | O30: - | P30: 0.13157895 | Q30: 0.13157895 | R30: 0.010964912 | S30: 0.1 | T30: -0.0088666552 | U30: -0.018741558 | V30: 0.059048197 | W30: =IF(OR(B30="",G30="FI-Infra"),"",HYPERLINK("https://content.btgpactual.com/research/ativo/https://content.btgpactual.com/research/ativo/"&B30,"Link")) -> Link
B31: VCRA11 | C31: 42502827000143 | D31: Vectis Datagro Crédito Agronegócio Fiagro-FII | E31: Vectis | F31: Intrag | G31: FIAgro - FII | H31: 667907.5 | I31: 51.32 | J31: 63.460844 | K31: 0.80868764 | L31: 2.3575992e+08 | M31: 4.6851258e+08 | N31: 0.50320937 | O31: 1.0268476 | P31: 0.22213562 | Q31: 0.17537023 | R31: 0.014614186 | S31: 0.75 | T31: -0.10248339 | U31: -0.10274633 | V31: 0.00018462308 | W31: =IF(OR(B31="",G31="FI-Infra"),"",HYPERLINK("https://content.btgpactual.com/research/ativo/https://content.btgpactual.com/research/ativo/"&B31,"Link")) -> Link
B32: VGIA11 | C32: 41081088000109 | D32: Valora CRA Fiagro-FII | E32: Valora | F32: BTG Pactual | G32: FIAgro - FII | H32: 2956539.2 | I32: 8.42 | J32: 9.5380985 | K32: 0.88277554 | L32: 7.2795209e+08 | M32: 8.354651e+08 | N32: 0.87131358 | O32: 1.0339267 | P32: 0.195962 | Q32: 0.18527316 | R32: 0.01543943 | S32: 0.13 | T32: 0.033089127 | U32: -0.044357046 | V32: 0.12187365 | W32: =IF(OR(B32="",G32="FI-Infra"),"",HYPERLINK("https://content.btgpactual.com/research/ativo/https://content.btgpactual.com/research/ativo/"&B32,"Link")) -> Link
B33: XPCA11 | C33: 41269527000101 | D33: XP Crédito Agrícola Fiagro-FII | E33: XP | F33: XP Investimentos | G33: FIAgro - FII | H33: 602436.99 | I33: 7.16 | J33: 8.2248992 | K33: 0.87052738 | L33: 3.2594522e+08 | M33: 4.3900465e+08 | N33: 0.74246417 | O33: 0.99799629 | P33: 0.18156425 | Q33: 0.16759777 | R33: 0.01396648 | S33: 0.1 | T33: -0.057894737 | U33: -0.060006581 | V33: 0.088638648 | W33: =IF(OR(B33="",G33="FI-Infra"),"",HYPERLINK("https://content.btgpactual.com/research/ativo/https://content.btgpactual.com/research/ativo/"&B33,"Link")) -> Link

Sheet FI-Infra
D2: Menu | H2: Menu
Q3: Retorno
E4: Características | H4: Volume de Negociação | I4: Fechamento | J4: Máximo | L4: Valor de Mercado | M4: Valor Patrimonial | N4: P/VPA | O4: Pagamentos | P4: Pagamentos | Q4: No Mês | R4: No Ano | S4: LTM
B5: Código | C5: CNPJ | D5: Nome | E5: Gestor | F5: Administrador | G5: Tipo | H5: Média - 3 Meses (R$) | I5: R$ | J5: R$ | K5: % | L5: R$ | M5: R$ | N5: Atual | O5: % | P5: R$/cota | Q5: % | R5: % | S5: %
B6: BDIF11 | C6: 40502607000194 | D6: BTG Pactual Dívida Infra FIC FI-Infra | E6: BTG Pactual | F6: BTG Pactual | G6: FI-Infra | H6: 2152614.5 | I6: 68.34 | J6: 73.712369 | K6: 0.92711712 | L6: 1.2386611e+09 | M6: 1.4272615e+09 | N6: 0.86785855 | O6: 0.012437811 | P6: 0.85 | Q6: -0.013921388 | R6: 0.026322057 | S6: 0.07456221
B7: BIDB11 | C7: 42294971000131 | D7: Inter Infra FIC FI - Infra listado | E7: Inter | F7: Inter | G7: FI-Infra | H7: 201660.78 | I7: 74 | J7: 78.148844 | K7: 0.946911 | L7: 1.8468646e+08 | M7: 1.9481402e+08 | N7: 0.94801424 | O7: 0.013513514 | P7: 1 | Q7: -0.043927649 | R7: 0.021997345 | S7: 0.10698394
B8: BINC11 | C8: 55239865000105 | D8: Bradesco FIC FI Renda Fixa Infra CDI | E8: Bradesco Asset Management | F8: Banco Bradesco | G8: FI-Infra | H8: 785178.16 | I8: 102.9 | J8: 105.99 | K8: 0.97084631 | L8: 1.1953158e+09 | M8: 1.1703078e+09 | N8: 1.0213688 | O8: 0.014577259 | P8: 1.5 | Q8: -0.010957324 | R8: 0.13091287 | S8: 0.26665811
B9: BODB11 | C9: 41771670000199 | D9: Bocaina FIC FI-Infra | E9: Bocaina Capital | F9: BTG Pactual | G9: FI-Infra | H9: 921585.67 | I9: 7.13 | J9: 7.7079948 | K9: 0.9250136 | L9: 4.6257371e+08 | M9: 5.1896933e+08 | N9: 0.8913315 | O9: 0.012622721 | P9: 0.09 | Q9: -0.054376658 | R9: -0.01110907 | S9: 0.14308479
B10: CDII11 | C10: 48973783000116 | D10: Sparta Infra CDI FIC FI-Infra | E10: Sparta | F10: BTG Pactual | G10: FI-Infra | H10: 7124571 | I10: 95.71 | J10: 101.91327 | K10: 0.93913188 | L10: 2.6302197e+09 | M10: 2.7939017e+09 | N10: 0.94141454 | O10: 0.010448229 | P10: 1 | Q10: -0.029408782 | R10: -0.060782865 | S10: 0.042360146
B11: CPTI11 | C11: 38065012000177 | D11: Capitânia Infra FIC FIRF | E11: Capitânia | F11: BTG Pactual | G11: FI-Infra | H11: 2258273.3 | I11: 81.9 | J11: 86.075775 | K11: 0.95148722 | L11: 1.1124226e+09 | M11: 1.226901e+09 | N11: 0.90669298 | O11: 0.014041514 | P11: 1.15 | Q11: -0.041924296 | R11: 0.036045659 | S11: 0.17733016
B12: DIVS11 | C12: 58390457000130 | D12: Sparta Inflação Longa | E12: Sparta | F12: BNY | G12: FI-Infra | H12: 1335708 | I12: 92.96 | J12: 106.36944 | K12: 0.87393519 | L12: 9.5342381e+08 | M12: 9.9434637e+08 | N12: 0.95884477 | O12: 0.012908778 | P12: 1.2 | Q12: -0.017855256 | R12: 0.027603186 | S12: 0.030152803
B13: IFRA11 | C13: 34633510000118 | D13: Itaú FIC FI de Infraestrutura | E13: Itaú Unibanco | F13: Intrag | G13: FI-Infra | H13: 2172046.6 | I13: 89.5 | J13: 98.079426 | K13: 0.91252574 | L13: 1.3865382e+09 | M13: 1.4775307e+09 | N13: 0.93841583 | O13: 0.010055866 | P13: 0.9 | Q13: -0.033477322 | R13: -0.032459095 | S13: 0.062158534
B14: IFRI11 | C14: 53556099000179 | D14: Itaú FIC FI de Infraestrutura CDI | E14: Itaú Unibanco | F14: Intrag | G14: FI-Infra | H14: 1877729.8 | I14: 99.93 | J14: 102 | K14: 0.97970588 | L14: 1.4965015e+09 | M14: 1.4890543e+09 | N14: 1.0050013 | O14: 0.013009106 | P14: 1.3 | Q14: -0.016824085 | R14: 0.060621152 | S14: 0.18162034
B15: IRIF11 | C15: 55940336000126 | D15: Iridium Infra | E15: Iridium | F15: BTG Pactual | G15: FI-Infra | H15: 52186.328 | I15: 8.14 | J15: 9.2630781 | K15: 0.87875757 | L15: 36260021 | M15: 45619674 | N15: 0.79483296 | O15: 0.012285012 | P15: 0.1 | Q15: -0.037744771 | R15: -0.043184509 | S15: 0.11760096
B16: JMBI11 | C16: 55276939000175 | D16: Jive Mauá Bossanova FIC FI-Infra | E16: Jive | F16: XP | G16: FI-Infra | H16: 970935.4 | I16: 81.18 | J16: 87.704456 | K16: 0.92560861 | L16: 3.551625e+08 | M16: 4.4283852e+08 | N16: 0.80201356 | O16: 0.015028332 | P16: 1.22 | Q16: -0.02263424 | R16: 0.038905521 | S16: 0.10506249
B17: JURO11 | C17: 42730834000100 | D17: Sparta Infra FIC FI-Infra | E17: Sparta | F17: BTG Pactual | G17: FI-Infra | H17: 5495610.7 | I17: 94.05 | J17: 102.27267 | K17: 0.91960051 | L17: 1.9347662e+09 | M17: 2.0770137e+09 | N17: 0.93151348 | O17: 0.0079744817 | P17: 0.75 | Q17: -0.024377593 | R17: -0.034731463 | S17: 0.07546793
... B23: XPID11 | C23: 37404867000112 | D23: XP FIC FI-Infra | E23: XP | F23: Genial | G23: FI-Infra | H23: 108940.24 | I23: 48.89 | J23: 61.921475 | K23: 0.78954837 | L23: 1.5475953e+08 | M23: 2.3241536e+08 | N23: 0.66587483 | O23: 0.01534056 | P23: 0.75 | Q23: 0.011587006 | R23: 0.16803078 | S23: 0.041548098

Sheet Segmentos
L2: Menu | M2: Stock Guide
B4: Análise Segmentos
B5: Segmento | C5: Part. IFIX | D5: Volume de Negociação | E5: Valor de Mercado | F5: Valor Patrimonial | G5: P/VPA Atual | H5: P/VPA 2025 | I5: Dividend Yield LTM | J5: Dividend Yield Anualizado | K5: Retorno no Mês | L5: Retorno no Ano | M5: Retorno LTM
B6: Nome | C6: Total (%) | D6: Média Diária (R$) | E6: Total (R$) | F6: Total (R$) | G6: Média | H6: Média | I6: Média (% ao ano) | J6: Média (% ao ano) | K6: Média (%) | L6: Média (%) | M6: Média (%)
B7: Recebível | C7: =SUMIFS('Stock Guide'!H:H,'Stock Guide'!$G:$G,Segmentos!$B7) -> 0.36761 | D7: =AVERAGEIFS('Stock Guide'!I:I,'Stock Guide'!$G:$G,Segmentos!$B7) -> 1876793.9 | E7: =SUMIFS('Stock Guide'!M:M,'Stock Guide'!$G:$G,Segmentos!$B7) -> 5.6870845e+10 | F7: =SUMIFS('Stock Guide'!N:N,'Stock Guide'!$G:$G,Segmentos!$B7) -> 6.6479083e+10 | G7: =AVERAGEIFS('Stock Guide'!O:O,'Stock Guide'!$G:$G,Segmentos!$B7) -> 0.78179103 | H7: =AVERAGEIFS('Stock Guide'!P:P,'Stock Guide'!$G:$G,Segmentos!$B7) -> 0.86063519 | I7: =AVERAGEIFS('Stock Guide'!Q:Q,'Stock Guide'!$G:$G,Segmentos!$B7) -> 0.16614556 | J7: =AVERAGEIFS('Stock Guide'!R:R,'Stock Guide'!$G:$G,Segmentos!$B7) -> 0.15990203 | K7: =AVERAGEIFS('Stock Guide'!U:U,'Stock Guide'!$G:$G,Segmentos!$B7) -> -0.03196602 | L7: =AVERAGEIFS('Stock Guide'!V:V,'Stock Guide'!$G:$G,Segmentos!$B7) -> -0.027109577 | M7: =AVERAGEIFS('Stock Guide'!W:W,'Stock Guide'!$G:$G,Segmentos!$B7) -> 0.048648218
B8: Galpão Logístico | C8: =SUMIFS('Stock Guide'!H:H,'Stock Guide'!$G:$G,Segmentos!$B8) -> 0.18024 | D8: =AVERAGEIFS('Stock Guide'!I:I,'Stock Guide'!$G:$G,Segmentos!$B8) -> 3125206.6 | E8: =SUMIFS('Stock Guide'!M:M,'Stock Guide'!$G:$G,Segmentos!$B8) -> 3.2929979e+10 | F8: =SUMIFS('Stock Guide'!N:N,'Stock Guide'!$G:$G,Segmentos!$B8) -> 3.8725582e+10 | G8: =AVERAGEIFS('Stock Guide'!O:O,'Stock Guide'!$G:$G,Segmentos!$B8) -> 0.79534334 | H8: =AVERAGEIFS('Stock Guide'!P:P,'Stock Guide'!$G:$G,Segmentos!$B8) -> 0.8761547 | I8: =AVERAGEIFS('Stock Guide'!Q:Q,'Stock Guide'!$G:$G,Segmentos!$B8) -> 0.11209998 | J8: =AVERAGEIFS('Stock Guide'!R:R,'Stock Guide'!$G:$G,Segmentos!$B8) -> 0.10854653 | K8: =AVERAGEIFS('Stock Guide'!U:U,'Stock Guide'!$G:$G,Segmentos!$B8) -> -0.027476579 | L8: =AVERAGEIFS('Stock Guide'!V:V,'Stock Guide'!$G:$G,Segmentos!$B8) -> -0.045070883 | M8: =AVERAGEIFS('Stock Guide'!W:W,'Stock Guide'!$G:$G,Segmentos!$B8) -> 0.076591985
B9: Shopping Center | C9: =SUMIFS('Stock Guide'!H:H,'Stock Guide'!$G:$G,Segmentos!$B9) -> 0.11835 | D9: =AVERAGEIFS('Stock Guide'!I:I,'Stock Guide'!$G:$G,Segmentos!$B9) -> 3558069.7 | E9: =SUMIFS('Stock Guide'!M:M,'Stock Guide'!$G:$G,Segmentos!$B9) -> 2.4299827e+10 | F9: =SUMIFS('Stock Guide'!N:N,'Stock Guide'!$G:$G,Segmentos!$B9) -> 2.959225e+10 | G9: =AVERAGEIFS('Stock Guide'!O:O,'Stock Guide'!$G:$G,Segmentos!$B9) -> 0.79206712 | H9: =AVERAGEIFS('Stock Guide'!P:P,'Stock Guide'!$G:$G,Segmentos!$B9) -> 0.81495066 | I9: =AVERAGEIFS('Stock Guide'!Q:Q,'Stock Guide'!$G:$G,Segmentos!$B9) -> 0.10760615 | J9: =AVERAGEIFS('Stock Guide'!R:R,'Stock Guide'!$G:$G,Segmentos!$B9) -> 0.092415897 | K9: =AVERAGEIFS('Stock Guide'!U:U,'Stock Guide'!$G:$G,Segmentos!$B9) -> -0.034986054 | L9: =AVERAGEIFS('Stock Guide'!V:V,'Stock Guide'!$G:$G,Segmentos!$B9) -> -0.03700172 | M9: =AVERAGEIFS('Stock Guide'!W:W,'Stock Guide'!$G:$G,Segmentos!$B9) -> 0.057332756
B10: Hedge Fund | C10: =SUMIFS('Stock Guide'!H:H,'Stock Guide'!$G:$G,Segmentos!$B10) -> 0.07365 | D10: =AVERAGEIFS('Stock Guide'!I:I,'Stock Guide'!$G:$G,Segmentos!$B10) -> 1633937.1 | E10: =SUMIFS('Stock Guide'!M:M,'Stock Guide'!$G:$G,Segmentos!$B10) -> 1.2270998e+10 | F10: =SUMIFS('Stock Guide'!N:N,'Stock Guide'!$G:$G,Segmentos!$B10) -> 1.5065138e+10 | G10: =AVERAGEIFS('Stock Guide'!O:O,'Stock Guide'!$G:$G,Segmentos!$B10) -> 0.83859445 | H10: =AVERAGEIFS('Stock Guide'!P:P,'Stock Guide'!$G:$G,Segmentos!$B10) -> 0.89496964 | I10: =AVERAGEIFS('Stock Guide'!Q:Q,'Stock Guide'!$G:$G,Segmentos!$B10) -> 0.15013515 | J10: =AVERAGEIFS('Stock Guide'!R:R,'Stock Guide'!$G:$G,Segmentos!$B10) -> 0.14486763 | K10: =AVERAGEIFS('Stock Guide'!U:U,'Stock Guide'!$G:$G,Segmentos!$B10) -> -0.027127969 | L10: =AVERAGEIFS('Stock Guide'!V:V,'Stock Guide'!$G:$G,Segmentos!$B10) -> -0.015378938 | M10: =AVERAGEIFS('Stock Guide'!W:W,'Stock Guide'!$G:$G,Segmentos!$B10) -> 0.081350971
B11: Laje Corporativa | C11: =SUMIFS('Stock Guide'!H:H,'Stock Guide'!$G:$G,Segmentos!$B11) -> 0.06532 | D11: =AVERAGEIFS('Stock Guide'!I:I,'Stock Guide'!$G:$G,Segmentos!$B11) -> 1307854.4 | E11: =SUMIFS('Stock Guide'!M:M,'Stock Guide'!$G:$G,Segmentos!$B11) -> 1.2424207e+10 | F11: =SUMIFS('Stock Guide'!N:N,'Stock Guide'!$G:$G,Segmentos!$B11) -> 1.9888354e+10 | G11: =AVERAGEIFS('Stock Guide'!O:O,'Stock Guide'!$G:$G,Segmentos!$B11) -> 0.6322556 | H11: =AVERAGEIFS('Stock Guide'!P:P,'Stock Guide'!$G:$G,Segmentos!$B11) -> 0.67987344 | I11: =AVERAGEIFS('Stock Guide'!Q:Q,'Stock Guide'!$G:$G,Segmentos!$B11) -> 0.11182231 | J11: =AVERAGEIFS('Stock Guide'!R:R,'Stock Guide'!$G:$G,Segmentos!$B11) -> 0.13073001 | K11: =AVERAGEIFS('Stock Guide'!U:U,'Stock Guide'!$G:$G,Segmentos!$B11) -> -0.019245959 | L11: =AVERAGEIFS('Stock Guide'!V:V,'Stock Guide'!$G:$G,Segmentos!$B11) -> -0.0082131217 | M11: =AVERAGEIFS('Stock Guide'!W:W,'Stock Guide'!$G:$G,Segmentos!$B11) -> 0.12871187
B12: Renda Urbana | C12: =SUMIFS('Stock Guide'!H:H,'Stock Guide'!$G:$G,Segmentos!$B12) -> 0.08267 | D12: =AVERAGEIFS('Stock Guide'!I:I,'Stock Guide'!$G:$G,Segmentos!$B12) -> 5061768.8 | E12: =SUMIFS('Stock Guide'!M:M,'Stock Guide'!$G:$G,Segmentos!$B12) -> 1.2827437e+10 | F12: =SUMIFS('Stock Guide'!N:N,'Stock Guide'!$G:$G,Segmentos!$B12) -> 1.5074284e+10 | G12: =AVERAGEIFS('Stock Guide'!O:O,'Stock Guide'!$G:$G,Segmentos!$B12) -> 0.87504221 | H12: =AVERAGEIFS('Stock Guide'!P:P,'Stock Guide'!$G:$G,Segmentos!$B12) -> 0.95833695 | I12: =AVERAGEIFS('Stock Guide'!Q:Q,'Stock Guide'!$G:$G,Segmentos!$B12) -> 0.14673631 | J12: =AVERAGEIFS('Stock Guide'!R:R,'Stock Guide'!$G:$G,Segmentos!$B12) -> 0.11614244 | K12: =AVERAGEIFS('Stock Guide'!U:U,'Stock Guide'!$G:$G,Segmentos!$B12) -> -0.043774239 | L12: =AVERAGEIFS('Stock Guide'!V:V,'Stock Guide'!$G:$G,Segmentos!$B12) -> -0.016001281 | M12: =AVERAGEIFS('Stock Guide'!W:W,'Stock Guide'!$G:$G,Segmentos!$B12) -> 0.1186824
B13: Híbrido | C13: =SUMIFS('Stock Guide'!H:H,'Stock Guide'!$G:$G,Segmentos!$B13) -> 0.04733 | D13: =AVERAGEIFS('Stock Guide'!I:I,'Stock Guide'!$G:$G,Segmentos!$B13) -> 1719745.4 | E13: =SUMIFS('Stock Guide'!M:M,'Stock Guide'!$G:$G,Segmentos!$B13) -> 7.3838433e+09 | F13: =SUMIFS('Stock Guide'!N:N,'Stock Guide'!$G:$G,Segmentos!$B13) -> 8.4335581e+09 | G13: =AVERAGEIFS('Stock Guide'!O:O,'Stock Guide'!$G:$G,Segmentos!$B13) -> 0.7588104 | H13: =AVERAGEIFS('Stock Guide'!P:P,'Stock Guide'!$G:$G,Segmentos!$B13) -> 0.82167984 | I13: =AVERAGEIFS('Stock Guide'!Q:Q,'Stock Guide'!$G:$G,Segmentos!$B13) -> 0.11421085 | J13: =AVERAGEIFS('Stock Guide'!R:R,'Stock Guide'!$G:$G,Segmentos!$B13) -> 0.11086549 | K13: =AVERAGEIFS('Stock Guide'!U:U,'Stock Guide'!$G:$G,Segmentos!$B13) -> -0.024056091 | L13: =AVERAGEIFS('Stock Guide'!V:V,'Stock Guide'!$G:$G,Segmentos!$B13) -> -0.014951237 | M13: =AVERAGEIFS('Stock Guide'!W:W,'Stock Guide'!$G:$G,Segmentos!$B13) -> 0.11084411
B14: Fundo de Fundos | C14: =SUMIFS('Stock Guide'!H:H,'Stock Guide'!$G:$G,Segmentos!$B14) -> 0.02417 | D14: =AVERAGEIFS('Stock Guide'!I:I,'Stock Guide'!$G:$G,Segmentos!$B14) -> 568847.14 | E14: =SUMIFS('Stock Guide'!M:M,'Stock Guide'!$G:$G,Segmentos!$B14) -> 5.4280166e+09 | F14: =SUMIFS('Stock Guide'!N:N,'Stock Guide'!$G:$G,Segmentos!$B14) -> 6.6673863e+09 | G14: =AVERAGEIFS('Stock Guide'!O:O,'Stock Guide'!$G:$G,Segmentos!$B14) -> 0.82129622 | H14: =AVERAGEIFS('Stock Guide'!P:P,'Stock Guide'!$G:$G,Segmentos!$B14) -> 0.83882072 | I14: =AVERAGEIFS('Stock Guide'!Q:Q,'Stock Guide'!$G:$G,Segmentos!$B14) -> 0.14336735 | J14: =AVERAGEIFS('Stock Guide'!R:R,'Stock Guide'!$G:$G,Segmentos!$B14) -> 0.13768934 | K14: =AVERAGEIFS('Stock Guide'!U:U,'Stock Guide'!$G:$G,Segmentos!$B14) -> -0.024372758 | L14: =AVERAGEIFS('Stock Guide'!V:V,'Stock Guide'!$G:$G,Segmentos!$B14) -> 0.0075174358 | M14: =AVERAGEIFS('Stock Guide'!W:W,'Stock Guide'!$G:$G,Segmentos!$B14) -> 0.11882949
B15: Agronegócio | C15: =SUMIFS('Stock Guide'!H:H,'Stock Guide'!$G:$G,Segmentos!$B15) -> 0.01396 | D15: =AVERAGEIFS('Stock Guide'!I:I,'Stock Guide'!$G:$G,Segmentos!$B15) -> 982889.21 | E15: =SUMIFS('Stock Guide'!M:M,'Stock Guide'!$G:$G,Segmentos!$B15) -> 2.6351965e+09 | F15: =SUMIFS('Stock Guide'!N:N,'Stock Guide'!$G:$G,Segmentos!$B15) -> 3.2791753e+09 | G15: =AVERAGEIFS('Stock Guide'!O:O,'Stock Guide'!$G:$G,Segmentos!$B15) -> 0.77154218 | H15: =AVERAGEIFS('Stock Guide'!P:P,'Stock Guide'!$G:$G,Segmentos!$B15) -> 0.77861192 | I15: =AVERAGEIFS('Stock Guide'!Q:Q,'Stock Guide'!$G:$G,Segmentos!$B15) -> 0.12846861 | J15: =AVERAGEIFS('Stock Guide'!R:R,'Stock Guide'!$G:$G,Segmentos!$B15) -> 0.14006193 | K15: =AVERAGEIFS('Stock Guide'!U:U,'Stock Guide'!$G:$G,Segmentos!$B15) -> -0.010602859 | L15: =AVERAGEIFS('Stock Guide'!V:V,'Stock Guide'!$G:$G,Segmentos!$B15) -> 0.12914134 | M15: =AVERAGEIFS('Stock Guide'!W:W,'Stock Guide'!$G:$G,Segmentos!$B15) -> 0.30807177
B16: Desenvolvimento | C16: =SUMIFS('Stock Guide'!H:H,'Stock Guide'!$G:$G,Segmentos!$B16) -> 0.00845 | D16: =AVERAGEIFS('Stock Guide'!I:I,'Stock Guide'!$G:$G,Segmentos!$B16) -> 1260937 | E16: =SUMIFS('Stock Guide'!M:M,'Stock Guide'!$G:$G,Segmentos!$B16) -> 1.6006086e+09 | F16: =SUMIFS('Stock Guide'!N:N,'Stock Guide'!$G:$G,Segmentos!$B16) -> 3.606676e+09 | G16: =AVERAGEIFS('Stock Guide'!O:O,'Stock Guide'!$G:$G,Segmentos!$B16) -> 0.72542782 | H16: =AVERAGEIFS('Stock Guide'!P:P,'Stock Guide'!$G:$G,Segmentos!$B16) -> 0.84389661 | I16: =AVERAGEIFS('Stock Guide'!Q:Q,'Stock Guide'!$G:$G,Segmentos!$B16) -> 0.24162841 | J16: =AVERAGEIFS('Stock Guide'!R:R,'Stock Guide'!$G:$G,Segmentos!$B16) -> 0.25826212 | K16: =AVERAGEIFS('Stock Guide'!U:U,'Stock Guide'!$G:$G,Segmentos!$B16) -> -0.083223892 | L16: =AVERAGEIFS('Stock Guide'!V:V,'Stock Guide'!$G:$G,Segmentos!$B16) -> -0.20292075 | M16: =AVERAGEIFS('Stock Guide'!W:W,'Stock Guide'!$G:$G,Segmentos!$B16) -> 0.042485033
B17: Agência Bancária | C17: =SUMIFS('Stock Guide'!H:H,'Stock Guide'!$G:$G,Segmentos!$B17) -> 0.00951 | D17: =AVERAGEIFS('Stock Guide'!I:I,'Stock Guide'!$G:$G,Segmentos!$B17) -> 320210.97 | E17: =SUMIFS('Stock Guide'!M:M,'Stock Guide'!$G:$G,Segmentos!$B17) -> 1.7479308e+09 | F17: =SUMIFS('Stock Guide'!N:N,'Stock Guide'!$G:$G,Segmentos!$B17) -> 2.027914e+09 | G17: =AVERAGEIFS('Stock Guide'!O:O,'Stock Guide'!$G:$G,Segmentos!$B17) -> 0.78473812 | H17: =AVERAGEIFS('Stock Guide'!P:P,'Stock Guide'!$G:$G,Segmentos!$B17) -> 0.88774273 | I17: =AVERAGEIFS('Stock Guide'!Q:Q,'Stock Guide'!$G:$G,Segmentos!$B17) -> 0.15429272 | J17: =AVERAGEIFS('Stock Guide'!R:R,'Stock Guide'!$G:$G,Segmentos!$B17) -> 0.13443779 | K17: =AVERAGEIFS('Stock Guide'!U:U,'Stock Guide'!$G:$G,Segmentos!$B17) -> -0.017890658 | L17: =AVERAGEIFS('Stock Guide'!V:V,'Stock Guide'!$G:$G,Segmentos!$B17) -> -0.08733346 | M17: =AVERAGEIFS('Stock Guide'!W:W,'Stock Guide'!$G:$G,Segmentos!$B17) -> 0.010780355
B18: Hotel | C18: =SUMIFS('Stock Guide'!H:H,'Stock Guide'!$G:$G,Segmentos!$B18) -> 0.00265 | D18: =AVERAGEIFS('Stock Guide'!I:I,'Stock Guide'!$G:$G,Segmentos!$B18) -> 458137.14 | E18: =SUMIFS('Stock Guide'!M:M,'Stock Guide'!$G:$G,Segmentos!$B18) -> 3.9165443e+08 | F18: =SUMIFS('Stock Guide'!N:N,'Stock Guide'!$G:$G,Segmentos!$B18) -> 4.2811527e+08 | G18: =AVERAGEIFS('Stock Guide'!O:O,'Stock Guide'!$G:$G,Segmentos!$B18) -> 0.91483406 | H18: =AVERAGEIFS('Stock Guide'!P:P,'Stock Guide'!$G:$G,Segmentos!$B18) -> 0.98994817 | I18: =AVERAGEIFS('Stock Guide'!Q:Q,'Stock Guide'!$G:$G,Segmentos!$B18) -> 0.12661308 | J18: =AVERAGEIFS('Stock Guide'!R:R,'Stock Guide'!$G:$G,Segmentos!$B18) -> 0.10618686 | K18: =AVERAGEIFS('Stock Guide'!U:U,'Stock Guide'!$G:$G,Segmentos!$B18) -> -0.022066777 | L18: =AVERAGEIFS('Stock Guide'!V:V,'Stock Guide'!$G:$G,Segmentos!$B18) -> -0.024129605 | M18: =AVERAGEIFS('Stock Guide'!W:W,'Stock Guide'!$G:$G,Segmentos!$B18) -> 0.10230253
... B22: Residencial | C22: =SUMIFS('Stock Guide'!H:H,'Stock Guide'!$G:$G,Segmentos!$B22) -> 0 | D22: =AVERAGEIFS('Stock Guide'!I:I,'Stock Guide'!$G:$G,Segmentos!$B22) -> 90714.567 | E22: =SUMIFS('Stock Guide'!M:M,'Stock Guide'!$G:$G,Segmentos!$B22) -> 2.7509447e+08 | F22: =SUMIFS('Stock Guide'!N:N,'Stock Guide'!$G:$G,Segmentos!$B22) -> 4.9808968e+08 | G22: =AVERAGEIFS('Stock Guide'!O:O,'Stock Guide'!$G:$G,Segmentos!$B22) -> 0.55623795 | H22: =AVERAGEIFS('Stock Guide'!P:P,'Stock Guide'!$G:$G,Segmentos!$B22) -> 0.63688044 | I22: =AVERAGEIFS('Stock Guide'!Q:Q,'Stock Guide'!$G:$G,Segmentos!$B22) -> 0.098142503 | J22: =AVERAGEIFS('Stock Guide'!R:R,'Stock Guide'!$G:$G,Segmentos!$B22) -> 0.10101128 | K22: =AVERAGEIFS('Stock Guide'!U:U,'Stock Guide'!$G:$G,Segmentos!$B22) -> 0.0066340762 | L22: =AVERAGEIFS('Stock Guide'!V:V,'Stock Guide'!$G:$G,Segmentos!$B22) -> -0.089378632 | M22: =AVERAGEIFS('Stock Guide'!W:W,'Stock Guide'!$G:$G,Segmentos!$B22) -> 0.056502603
B26: Valor mercado vs. valor patrimonial
O33: 0.82328219 | P33: 0.079246247 | Q33: 0.084151473 | R33: 0.5 | S33: 0.12391618 | T33: -0.13692794 | U33: -0.12808499
O34: 0 | P34: 0 | Q34: 0.097759674 | R34: 0.8 | S34: 0.11270063 | T34: 0 | U34: 0
O35: 0.92755848 | P35: 0.091495288 | Q35: 0.11732754 | R35: 0.9 | S35: 0.042382454 | T35: 0.12046971 | U35: 0.14919643
O36: 1.103278 | P36: 0.078065134 | Q36: 0.082758621 | R36: 0.72 | S36: 0.043781926 | T36: 0.019388846 | U36: 0.024442149
O37: 0 | P37: 0 | Q37: 0.11134021 | R37: 0.9 | S37: 0.084377326 | T37: 0 | U37: 0
O38: 1.0511327 | P38: 0.12857143 | Q38: 0.16808905 | R38: 1.51 | S38: 0.059043128 | T38: 0.12845688 | U38: 0.17104016
O39: 0.94280494 | P39: 0.12593323 | Q39: 0.077757431 | R39: 0.46 | S39: 0.035597671 | T39: -0.026943965 | U39: -0.0086991639
O40: 1.1049199 | P40: 0.12795755 | Q40: 0.12607691 | R40: 1 | S40: 0.0037770818 | T40: 0.054595403 | U40: 0.069901726
O41: 1.0498016 | P41: 0.13482701 | Q41: 0.1332408 | R41: 1.12 | S41: 0.043062699 | T41: 0.12211911 | U41: 0.14615905
O42: 1.2726899 | P42: 0.22280393 | Q42: 0.099260991 | R42: 0.36139273 | S42: 0.11714538 | T42: -0.52214659 | U42: -0.52214659
O43: 0 | P43: 0 | Q43: 0.098222778 | R43: 0.654 | S43: 0.12304276 | T43: 0 | U43: 0
O44: 1.1831857 | P44: 0.17704066 | Q44: 0.17024678 | R44: 1.42 | S44: 0.033880712 | T44: 0.20443913 | U44: 0.17525449
... O48: 0.96608126 | P48: 0.10882708 | Q48: 0.12844677 | R48: 0.92 | S48: 0.076252982 | T48: 0.0051450133 | U48: 0.049476737
B49: Distribuição P/VPA | O49: 0.69642606 | P49: 0.054506968 | Q49: 0.067736814 | R49: 0.32 | S49: 0.15153362 | T49: -0.097975206 | U49: -0.10808004
O50: 1.2070211 | P50: 0.084629279 | Q50: 0.088814485 | R50: 3.36 | S50: 0.049325074 | T50: -0.086653132 | U50: -0.10694567
O51: 1.0320729 | P51: 0.089789659 | Q51: 0.095110352 | R51: 1.3 | S51: 0.033522369 | T51: -0.11335261 | U51: -0.11912264
O52: 0 | P52: 0 | Q52: 0.18897638 | R52: 1.6 | S52: 0.032848121 | T52: 0 | U52: 0
O53: 0 | P53: 0 | Q53: 0.10106276 | R53: 0.84 | S53: 0.0062550444 | T53: 0 | U53: 0
O54: 0 | P54: 0 | Q54: 0.13752174 | R54: 1.12 | S54: 0.020692054 | T54: 0 | U54: 0
O55: 1.1248562 | P55: 0.083811084 | Q55: 0.087360087 | R55: 0.8 | S55: 0.053927902 | T55: -0.15077375 | U55: -0.12836015
O56: 0.2514411 | P56: 0 | Q56: 0.0076239854 | R56: 0.002789108 | S56: 0.052757794 | T56: 0.25787966 | U56: 0.31437126
O57: 1.1003671 | P57: 0.098479902 | Q57: 0.09804878 | R57: 0.67 | S57: 0.14926419 | T57: -0.20209936 | U57: -0.20059659
O58: 1.1848057 | P58: 0.17372724 | Q58: 0.16722408 | R58: 1.5 | S58: -0.018151966 | T58: 0.067167011 | U58: 0.089317452
O59: 1.0178091 | P59: 0.095071614 | Q59: 0.17322657 | R59: 1.28 | S59: 0.10217526 | T59: -0.037518518 | U59: -0.037613813
O60: 1.2513773 | P60: 0.18007663 | Q60: 0.15651749 | R60: 1.6 | S60: 0.042790037 | T60: 0.14410466 | U60: 0.17890784
O61: 1.0529461 | P61: 0.089012346 | Q61: 0.088888889 | R61: 0.6 | S61: 0.041131105 | T61: -0.16573343 | U61: -0.15298791
... O70: 1.0265284 | P70: 0.075295442 | Q70: 0.078334271 | R70: 0.58 | S70: 0.13343539 | T70: -0.12146375 | U70: -0.12389288
B71: Distribuição Dividendos LTM | O71: 0.69642606 | P71: 0.054506968 | Q71: 0.067736814 | R71: 0.32 | S71: 0.15153362 | T71: -0.097975206 | U71: -0.10808004
O72: 1.2070211 | P72: 0.084629279 | Q72: 0.088814485 | R72: 3.36 | S72: 0.049325074 | T72: -0.086653132 | U72: -0.10694567
O73: 1.0320729 | P73: 0.089789659 | Q73: 0.095110352 | R73: 1.3 | S73: 0.033522369 | T73: -0.11335261 | U73: -0.11912264
O74: 0 | P74: 0 | Q74: 0.18897638 | R74: 1.6 | S74: 0.032848121 | T74: 0 | U74: 0
O75: 0 | P75: 0 | Q75: 0.10106276 | R75: 0.84 | S75: 0.0062550444 | T75: 0 | U75: 0
O76: 0 | P76: 0 | Q76: 0.13752174 | R76: 1.12 | S76: 0.020692054 | T76: 0 | U76: 0
O77: 1.1248562 | P77: 0.083811084 | Q77: 0.087360087 | R77: 0.8 | S77: 0.053927902 | T77: -0.15077375 | U77: -0.12836015
O78: 0.2514411 | P78: 0 | Q78: 0.0076239854 | R78: 0.002789108 | S78: 0.052757794 | T78: 0.25787966 | U78: 0.31437126
O79: 1.1003671 | P79: 0.098479902 | Q79: 0.09804878 | R79: 0.67 | S79: 0.14926419 | T79: -0.20209936 | U79: -0.20059659
O80: 1.1848057 | P80: 0.17372724 | Q80: 0.16722408 | R80: 1.5 | S80: -0.018151966 | T80: 0.067167011 | U80: 0.089317452
O81: 1.0178091 | P81: 0.095071614 | Q81: 0.17322657 | R81: 1.28 | S81: 0.10217526 | T81: -0.037518518 | U81: -0.037613813
O82: 1.2513773 | P82: 0.18007663 | Q82: 0.15651749 | R82: 1.6 | S82: 0.042790037 | T82: 0.14410466 | U82: 0.17890784
O83: 1.0529461 | P83: 0.089012346 | Q83: 0.088888889 | R83: 0.6 | S83: 0.041131105 | T83: -0.16573343 | U83: -0.15298791
... O100: 1.3295216 | P100: 0.09591472 | Q100: 0.10100203 | R100: 1.9611228 | S100: 0.10894886 | T100: -0.10430786 | U100: -0.083664012

Sheet Simulador de Carteiras (%)
Q2: Menu | R2: Stock Guide
B5: Simulação de Carteira
B6: Montante | D6: 1000000
B7: Fundo | C7: Peso | D7: Financeiro | E7: Cotas | F7: Características | H7: Preço | I7: Liquidez | J7: P/VPA | K7: Dividend Yield | N7: Dividendos¹ | P7: Performance
B8: Ticker | C8: (%) | D8: R$ | E8: Qtde. | F8: Nome do Fundo | G8: Segmento | H8: R$/Cota | I8: Média (R$ milhares 3M) | J8: - | K8: Mês (%) | L8: 12M (%) | M8: Anualizado (%) | N8: R$/Cota | O8: Montante | P8: 1M (%) | Q8: No ano (%) | R8: LTM (%)
B9: BTCI11 | C9: 0.06 | D9: =IF(C9*$D$6=0,"",C9*$D$6) -> 60000 | E9: =IFERROR(ROUNDDOWN(D9/H9,0),"") -> 6666 | F9: =IFERROR(VLOOKUP($B9,'Stock Guide'!$B:$W,3,0),"") -> BTG Pactual Crédito Imobiliário FII | G9: =IFERROR(VLOOKUP($B9,'Stock Guide'!$B:$W,6,0),"") -> Recebível | H9: =IFERROR(VLOOKUP($B9,'Stock Guide'!$B:$W,9,0),"") -> 9 | I9: =IFERROR(VLOOKUP($B9,'Stock Guide'!$B:$W,8,0)/1000,"") -> 3504.8616 | J9: =IFERROR(VLOOKUP($B9,'Stock Guide'!$B:$W,14,0),"") -> 0.89215724 | K9: =IFERROR(N9/H9,"") -> 0.011444444 | L9: =IFERROR(VLOOKUP($B9,'Stock Guide'!$B:$W,16,0),"") -> 0.13055556 | M9: =IFERROR((N9/H9)*12,"") -> 0.13733333 | N9: =IFERROR(VLOOKUP($B9,'Stock Guide'!$B:$W,19,0),"") -> 0.103 | O9: =IFERROR(N9*E9,"") -> 686.598 | P9: =IFERROR(VLOOKUP($B9,'Stock Guide'!$B:$W,20,0),"") -> -0.0040443824 | Q9: =IFERROR(VLOOKUP($B9,'Stock Guide'!$B:$W,21,0),"") -> 0.048974723 | R9: =IFERROR(VLOOKUP($B9,'Stock Guide'!$B:$W,22,0),"") -> 0.12285468
B10: KNCR11 | C10: 0.13 | D10: =IF(C10*$D$6=0,"",C10*$D$6) -> 130000 | E10: =IFERROR(ROUNDDOWN(D10/H10,0),"") -> 1219 | F10: =IFERROR(VLOOKUP($B10,'Stock Guide'!$B:$W,3,0),"") -> Kinea Rendimentos Imobiliários FII | G10: =IFERROR(VLOOKUP($B10,'Stock Guide'!$B:$W,6,0),"") -> Recebível | H10: =IFERROR(VLOOKUP($B10,'Stock Guide'!$B:$W,9,0),"") -> 106.6 | I10: =IFERROR(VLOOKUP($B10,'Stock Guide'!$B:$W,8,0)/1000,"") -> 21474.426 | J10: =IFERROR(VLOOKUP($B10,'Stock Guide'!$B:$W,14,0),"") -> 1.0398102 | K10: =IFERROR(N10/H10,"") -> 0.011726079 | L10: =IFERROR(VLOOKUP($B10,'Stock Guide'!$B:$W,16,0),"") -> 0.13452158 | M10: =IFERROR((N10/H10)*12,"") -> 0.14071295 | N10: =IFERROR(VLOOKUP($B10,'Stock Guide'!$B:$W,19,0),"") -> 1.25 | O10: =IFERROR(N10*E10,"") -> 1523.75 | P10: =IFERROR(VLOOKUP($B10,'Stock Guide'!$B:$W,20,0),"") -> -0.0020595394 | Q10: =IFERROR(VLOOKUP($B10,'Stock Guide'!$B:$W,21,0),"") -> 0.080907164 | R10: =IFERROR(VLOOKUP($B10,'Stock Guide'!$B:$W,22,0),"") -> 0.18083758
B11: KNIP11 | C11: 0.13 | D11: =IF(C11*$D$6=0,"",C11*$D$6) -> 130000 | E11: =IFERROR(ROUNDDOWN(D11/H11,0),"") -> 1455 | F11: =IFERROR(VLOOKUP($B11,'Stock Guide'!$B:$W,3,0),"") -> Kinea Indices de Preços FII | G11: =IFERROR(VLOOKUP($B11,'Stock Guide'!$B:$W,6,0),"") -> Recebível | H11: =IFERROR(VLOOKUP($B11,'Stock Guide'!$B:$W,9,0),"") -> 89.3 | I11: =IFERROR(VLOOKUP($B11,'Stock Guide'!$B:$W,8,0)/1000,"") -> 10206.473 | J11: =IFERROR(VLOOKUP($B11,'Stock Guide'!$B:$W,14,0),"") -> 0.96172851 | K11: =IFERROR(N11/H11,"") -> 0.010638298 | L11: =IFERROR(VLOOKUP($B11,'Stock Guide'!$B:$W,16,0),"") -> 0.1137738 | M11: =IFERROR((N11/H11)*12,"") -> 0.12765957 | N11: =IFERROR(VLOOKUP($B11,'Stock Guide'!$B:$W,19,0),"") -> 0.95 | O11: =IFERROR(N11*E11,"") -> 1382.25 | P11: =IFERROR(VLOOKUP($B11,'Stock Guide'!$B:$W,20,0),"") -> -0.01478376 | Q11: =IFERROR(VLOOKUP($B11,'Stock Guide'!$B:$W,21,0),"") -> 0.070350425 | R11: =IFERROR(VLOOKUP($B11,'Stock Guide'!$B:$W,22,0),"") -> 0.15124008
B12: RBRR11 | C12: 0.03 | D12: =IF(C12*$D$6=0,"",C12*$D$6) -> 30000 | E12: =IFERROR(ROUNDDOWN(D12/H12,0),"") -> 400 | F12: =IFERROR(VLOOKUP($B12,'Stock Guide'!$B:$W,3,0),"") -> FII RBR Rendimento High | G12: =IFERROR(VLOOKUP($B12,'Stock Guide'!$B:$W,6,0),"") -> Recebível | H12: =IFERROR(VLOOKUP($B12,'Stock Guide'!$B:$W,9,0),"") -> 75 | I12: =IFERROR(VLOOKUP($B12,'Stock Guide'!$B:$W,8,0)/1000,"") -> 4149.1633 | J12: =IFERROR(VLOOKUP($B12,'Stock Guide'!$B:$W,14,0),"") -> 0.81605128 | K12: =IFERROR(N12/H12,"") -> 0.012 | L12: =IFERROR(VLOOKUP($B12,'Stock Guide'!$B:$W,16,0),"") -> 0.13173333 | M12: =IFERROR((N12/H12)*12,"") -> 0.144 | N12: =IFERROR(VLOOKUP($B12,'Stock Guide'!$B:$W,19,0),"") -> 0.9 | O12: =IFERROR(N12*E12,"") -> 360 | P12: =IFERROR(VLOOKUP($B12,'Stock Guide'!$B:$W,20,0),"") -> -0.00045359409 | Q12: =IFERROR(VLOOKUP($B12,'Stock Guide'!$B:$W,21,0),"") -> -0.070281297 | R12: =IFERROR(VLOOKUP($B12,'Stock Guide'!$B:$W,22,0),"") -> -0.023658733
B13: RBRY11 | C13: 0.09 | D13: =IF(C13*$D$6=0,"",C13*$D$6) -> 90000 | E13: =IFERROR(ROUNDDOWN(D13/H13,0),"") -> 1170 | F13: =IFERROR(VLOOKUP($B13,'Stock Guide'!$B:$W,3,0),"") -> RBR Crédito Imobiliário Estruturado FII | G13: =IFERROR(VLOOKUP($B13,'Stock Guide'!$B:$W,6,0),"") -> Recebível | H13: =IFERROR(VLOOKUP($B13,'Stock Guide'!$B:$W,9,0),"") -> 76.87 | I13: =IFERROR(VLOOKUP($B13,'Stock Guide'!$B:$W,8,0)/1000,"") -> 4305.7881 | J13: =IFERROR(VLOOKUP($B13,'Stock Guide'!$B:$W,14,0),"") -> 0.76119222 | K13: =IFERROR(N13/H13,"") -> 0.013008976 | L13: =IFERROR(VLOOKUP($B13,'Stock Guide'!$B:$W,16,0),"") -> 0.17627163 | M13: =IFERROR((N13/H13)*12,"") -> 0.15610771 | N13: =IFERROR(VLOOKUP($B13,'Stock Guide'!$B:$W,19,0),"") -> 1 | O13: =IFERROR(N13*E13,"") -> 1170 | P13: =IFERROR(VLOOKUP($B13,'Stock Guide'!$B:$W,20,0),"") -> -0.081375577 | Q13: =IFERROR(VLOOKUP($B13,'Stock Guide'!$B:$W,21,0),"") -> -0.13772419 | R13: =IFERROR(VLOOKUP($B13,'Stock Guide'!$B:$W,22,0),"") -> -0.038285445
B14: MCCI11 | C14: 0.08 | D14: =IF(C14*$D$6=0,"",C14*$D$6) -> 80000 | E14: =IFERROR(ROUNDDOWN(D14/H14,0),"") -> 856 | F14: =IFERROR(VLOOKUP($B14,'Stock Guide'!$B:$W,3,0),"") -> Mauá Capital Recebíveis Imobiliários FII | G14: =IFERROR(VLOOKUP($B14,'Stock Guide'!$B:$W,6,0),"") -> Recebível | H14: =IFERROR(VLOOKUP($B14,'Stock Guide'!$B:$W,9,0),"") -> 93.38 | I14: =IFERROR(VLOOKUP($B14,'Stock Guide'!$B:$W,8,0)/1000,"") -> 4539.8289 | J14: =IFERROR(VLOOKUP($B14,'Stock Guide'!$B:$W,14,0),"") -> 0.99342629 | K14: =IFERROR(N14/H14,"") -> 0.010708931 | L14: =IFERROR(VLOOKUP($B14,'Stock Guide'!$B:$W,16,0),"") -> 0.12850717 | M14: =IFERROR((N14/H14)*12,"") -> 0.12850717 | N14: =IFERROR(VLOOKUP($B14,'Stock Guide'!$B:$W,19,0),"") -> 1 | O14: =IFERROR(N14*E14,"") -> 856 | P14: =IFERROR(VLOOKUP($B14,'Stock Guide'!$B:$W,20,0),"") -> -0.0042546667 | Q14: =IFERROR(VLOOKUP($B14,'Stock Guide'!$B:$W,21,0),"") -> 0.11080271 | R14: =IFERROR(VLOOKUP($B14,'Stock Guide'!$B:$W,22,0),"") -> 0.26147021
B15: VILG11 | C15: 0.045 | D15: =IF(C15*$D$6=0,"",C15*$D$6) -> 45000 | E15: =IFERROR(ROUNDDOWN(D15/H15,0),"") -> 490 | F15: =IFERROR(VLOOKUP($B15,'Stock Guide'!$B:$W,3,0),"") -> Vinci Logística FII | G15: =IFERROR(VLOOKUP($B15,'Stock Guide'!$B:$W,6,0),"") -> Galpão Logístico | H15: =IFERROR(VLOOKUP($B15,'Stock Guide'!$B:$W,9,0),"") -> 91.65 | I15: =IFERROR(VLOOKUP($B15,'Stock Guide'!$B:$W,8,0)/1000,"") -> 2575.8593 | J15: =IFERROR(VLOOKUP($B15,'Stock Guide'!$B:$W,14,0),"") -> 0.83834886 | K15: =IFERROR(N15/H15,"") -> 0.0089470813 | L15: =IFERROR(VLOOKUP($B15,'Stock Guide'!$B:$W,16,0),"") -> 0.10190944 | M15: =IFERROR((N15/H15)*12,"") -> 0.10736498 | N15: =IFERROR(VLOOKUP($B15,'Stock Guide'!$B:$W,19,0),"") -> 0.82 | O15: =IFERROR(N15*E15,"") -> 401.8 | P15: =IFERROR(VLOOKUP($B15,'Stock Guide'!$B:$W,20,0),"") -> 0.0058165057 | Q15: =IFERROR(VLOOKUP($B15,'Stock Guide'!$B:$W,21,0),"") -> -0.016190668 | R15: =IFERROR(VLOOKUP($B15,'Stock Guide'!$B:$W,22,0),"") -> 0.25374251
B16: BRCO11 | C16: 0.045 | D16: =IF(C16*$D$6=0,"",C16*$D$6) -> 45000 | E16: =IFERROR(ROUNDDOWN(D16/H16,0),"") -> 402 | F16: =IFERROR(VLOOKUP($B16,'Stock Guide'!$B:$W,3,0),"") -> Bresco Logística FII | G16: =IFERROR(VLOOKUP($B16,'Stock Guide'!$B:$W,6,0),"") -> Galpão Logístico | H16: =IFERROR(VLOOKUP($B16,'Stock Guide'!$B:$W,9,0),"") -> 111.84 | I16: =IFERROR(VLOOKUP($B16,'Stock Guide'!$B:$W,8,0)/1000,"") -> 5135.9864 | J16: =IFERROR(VLOOKUP($B16,'Stock Guide'!$B:$W,14,0),"") -> 0.97361058 | K16: =IFERROR(N16/H16,"") -> 0.0081366237 | L16: =IFERROR(VLOOKUP($B16,'Stock Guide'!$B:$W,16,0),"") -> 0.097639485 | M16: =IFERROR((N16/H16)*12,"") -> 0.097639485 | N16: =IFERROR(VLOOKUP($B16,'Stock Guide'!$B:$W,19,0),"") -> 0.91 | O16: =IFERROR(N16*E16,"") -> 365.82 | P16: =IFERROR(VLOOKUP($B16,'Stock Guide'!$B:$W,20,0),"") -> -0.019291477 | Q16: =IFERROR(VLOOKUP($B16,'Stock Guide'!$B:$W,21,0),"") -> 0.010814626 | R16: =IFERROR(VLOOKUP($B16,'Stock Guide'!$B:$W,22,0),"") -> 0.12894551
B17: BTLG11 | C17: 0.13 | D17: =IF(C17*$D$6=0,"",C17*$D$6) -> 130000 | E17: =IFERROR(ROUNDDOWN(D17/H17,0),"") -> 1321 | F17: =IFERROR(VLOOKUP($B17,'Stock Guide'!$B:$W,3,0),"") -> BTG Pactual Logística FII | G17: =IFERROR(VLOOKUP($B17,'Stock Guide'!$B:$W,6,0),"") -> Galpão Logístico | H17: =IFERROR(VLOOKUP($B17,'Stock Guide'!$B:$W,9,0),"") -> 98.37 | I17: =IFERROR(VLOOKUP($B17,'Stock Guide'!$B:$W,8,0)/1000,"") -> 12468.438 | J17: =IFERROR(VLOOKUP($B17,'Stock Guide'!$B:$W,14,0),"") -> 0.92052045 | K17: =IFERROR(N17/H17,"") -> 0.0082342177 | L17: =IFERROR(VLOOKUP($B17,'Stock Guide'!$B:$W,16,0),"") -> 0.097590729 | M17: =IFERROR((N17/H17)*12,"") -> 0.098810613 | N17: =IFERROR(VLOOKUP($B17,'Stock Guide'!$B:$W,19,0),"") -> 0.81 | O17: =IFERROR(N17*E17,"") -> 1070.01 | P17: =IFERROR(VLOOKUP($B17,'Stock Guide'!$B:$W,20,0),"") -> -0.016233044 | Q17: =IFERROR(VLOOKUP($B17,'Stock Guide'!$B:$W,21,0),"") -> 0.022844674 | R17: =IFERROR(VLOOKUP($B17,'Stock Guide'!$B:$W,22,0),"") -> 0.093649125
B18: BRCR11 | C18: 0.045 | D18: =IF(C18*$D$6=0,"",C18*$D$6) -> 45000 | E18: =IFERROR(ROUNDDOWN(D18/H18,0),"") -> 1148 | F18: =IFERROR(VLOOKUP($B18,'Stock Guide'!$B:$W,3,0),"") -> BTG Pactual Corporate Offices FII | G18: =IFERROR(VLOOKUP($B18,'Stock Guide'!$B:$W,6,0),"") -> Laje Corporativa | H18: =IFERROR(VLOOKUP($B18,'Stock Guide'!$B:$W,9,0),"") -> 39.19 | I18: =IFERROR(VLOOKUP($B18,'Stock Guide'!$B:$W,8,0)/1000,"") -> 1254.8978 | J18: =IFERROR(VLOOKUP($B18,'Stock Guide'!$B:$W,14,0),"") -> 0.48377811 | K18: =IFERROR(N18/H18,"") -> 0.010461853 | L18: =IFERROR(VLOOKUP($B18,'Stock Guide'!$B:$W,16,0),"") -> 0.12554223 | M18: =IFERROR((N18/H18)*12,"") -> 0.12554223 | N18: =IFERROR(VLOOKUP($B18,'Stock Guide'!$B:$W,19,0),"") -> 0.41 | O18: =IFERROR(N18*E18,"") -> 470.68 | P18: =IFERROR(VLOOKUP($B18,'Stock Guide'!$B:$W,20,0),"") -> -0.018103263 | Q18: =IFERROR(VLOOKUP($B18,'Stock Guide'!$B:$W,21,0),"") -> -0.082991445 | R18: =IFERROR(VLOOKUP($B18,'Stock Guide'!$B:$W,22,0),"") -> 0.084784476
B19: PVBI11 | C19: 0.05 | D19: =IF(C19*$D$6=0,"",C19*$D$6) -> 50000 | E19: =IFERROR(ROUNDDOWN(D19/H19,0),"") -> 750 | F19: =IFERROR(VLOOKUP($B19,'Stock Guide'!$B:$W,3,0),"") -> VBI Prime Properties | G19: =IFERROR(VLOOKUP($B19,'Stock Guide'!$B:$W,6,0),"") -> Laje Corporativa | H19: =IFERROR(VLOOKUP($B19,'Stock Guide'!$B:$W,9,0),"") -> 66.66 | I19: =IFERROR(VLOOKUP($B19,'Stock Guide'!$B:$W,8,0)/1000,"") -> 3815.4922 | J19: =IFERROR(VLOOKUP($B19,'Stock Guide'!$B:$W,14,0),"") -> 0.63782682 | K19: =IFERROR(N19/H19,"") -> 0.0060006001 | L19: =IFERROR(VLOOKUP($B19,'Stock Guide'!$B:$W,16,0),"") -> 0.077257726 | M19: =IFERROR((N19/H19)*12,"") -> 0.072007201 | N19: =IFERROR(VLOOKUP($B19,'Stock Guide'!$B:$W,19,0),"") -> 0.4 | O19: =IFERROR(N19*E19,"") -> 300 | P19: =IFERROR(VLOOKUP($B19,'Stock Guide'!$B:$W,20,0),"") -> -0.038372764 | Q19: =IFERROR(VLOOKUP($B19,'Stock Guide'!$B:$W,21,0),"") -> -0.15062473 | R19: =IFERROR(VLOOKUP($B19,'Stock Guide'!$B:$W,22,0),"") -> -0.042919195
B20: HGBS11 | C20: 0.03 | D20: =IF(C20*$D$6=0,"",C20*$D$6) -> 30000 | E20: =IFERROR(ROUNDDOWN(D20/H20,0),"") -> 1612 | F20: =IFERROR(VLOOKUP($B20,'Stock Guide'!$B:$W,3,0),"") -> Hedge Brasil Shopping FII | G20: =IFERROR(VLOOKUP($B20,'Stock Guide'!$B:$W,6,0),"") -> Shopping Center | H20: =IFERROR(VLOOKUP($B20,'Stock Guide'!$B:$W,9,0),"") -> 18.6 | I20: =IFERROR(VLOOKUP($B20,'Stock Guide'!$B:$W,8,0)/1000,"") -> 4435.5009 | J20: =IFERROR(VLOOKUP($B20,'Stock Guide'!$B:$W,14,0),"") -> 0.91869993 | K20: =IFERROR(N20/H20,"") -> 0.0091397849 | L20: =IFERROR(VLOOKUP($B20,'Stock Guide'!$B:$W,16,0),"") -> 0.10376344 | M20: =IFERROR((N20/H20)*12,"") -> 0.10967742 | N20: =IFERROR(VLOOKUP($B20,'Stock Guide'!$B:$W,19,0),"") -> 0.17 | O20: =IFERROR(N20*E20,"") -> 274.04 | P20: =IFERROR(VLOOKUP($B20,'Stock Guide'!$B:$W,20,0),"") -> -0.019504481 | Q20: =IFERROR(VLOOKUP($B20,'Stock Guide'!$B:$W,21,0),"") -> -0.0059386745 | R20: =IFERROR(VLOOKUP($B20,'Stock Guide'!$B:$W,22,0),"") -> 0.088335597
... B24: TRXF11 | C24: 0.07 | D24: =IF(C24*$D$6=0,"",C24*$D$6) -> 70000 | E24: =IFERROR(ROUNDDOWN(D24/H24,0),"") -> 974 | F24: =IFERROR(VLOOKUP($B24,'Stock Guide'!$B:$W,3,0),"") -> TRX Real Estate FII | G24: =IFERROR(VLOOKUP($B24,'Stock Guide'!$B:$W,6,0),"") -> Renda Urbana | H24: =IFERROR(VLOOKUP($B24,'Stock Guide'!$B:$W,9,0),"") -> 71.8 | I24: =IFERROR(VLOOKUP($B24,'Stock Guide'!$B:$W,8,0)/1000,"") -> 23831.971 | J24: =IFERROR(VLOOKUP($B24,'Stock Guide'!$B:$W,14,0),"") -> 0.73970401 | K24: =IFERROR(N24/H24,"") -> 0.012952646 | L24: =IFERROR(VLOOKUP($B24,'Stock Guide'!$B:$W,16,0),"") -> 0.1643454 | M24: =IFERROR((N24/H24)*12,"") -> 0.15543175 | N24: =IFERROR(VLOOKUP($B24,'Stock Guide'!$B:$W,19,0),"") -> 0.93 | O24: =IFERROR(N24*E24,"") -> 905.82 | P24: =IFERROR(VLOOKUP($B24,'Stock Guide'!$B:$W,20,0),"") -> -0.20372629 | Q24: =IFERROR(VLOOKUP($B24,'Stock Guide'!$B:$W,21,0),"") -> -0.20018374 | R24: =IFERROR(VLOOKUP($B24,'Stock Guide'!$B:$W,22,0),"") -> -0.16191836
D25: =IF(C25*$D$6=0,"",C25*$D$6) | E25: =IFERROR(ROUNDDOWN(D25/H25,0),"") | F25: =IFERROR(VLOOKUP($B25,'Stock Guide'!$B:$W,3,0),"") | G25: =IFERROR(VLOOKUP($B25,'Stock Guide'!$B:$W,6,0),"") | H25: =IFERROR(VLOOKUP($B25,'Stock Guide'!$B:$W,9,0),"") | I25: =IFERROR(VLOOKUP($B25,'Stock Guide'!$B:$W,8,0)/1000,"") | J25: =IFERROR(VLOOKUP($B25,'Stock Guide'!$B:$W,14,0),"") | K25: =IFERROR(N25/H25,"") | L25: =IFERROR(VLOOKUP($B25,'Stock Guide'!$B:$W,16,0),"") | M25: =IFERROR((N25/H25)*12,"") | N25: =IFERROR(VLOOKUP($B25,'Stock Guide'!$B:$W,19,0),"") | O25: =IFERROR(N25*E25,"") | P25: =IFERROR(VLOOKUP($B25,'Stock Guide'!$B:$W,20,0),"") | Q25: =IFERROR(VLOOKUP($B25,'Stock Guide'!$B:$W,21,0),"") | R25: =IFERROR(VLOOKUP($B25,'Stock Guide'!$B:$W,22,0),"")
D26: =IF(C26*$D$6=0,"",C26*$D$6) | E26: =IFERROR(ROUNDDOWN(D26/H26,0),"") | F26: =IFERROR(VLOOKUP($B26,'Stock Guide'!$B:$W,3,0),"") | G26: =IFERROR(VLOOKUP($B26,'Stock Guide'!$B:$W,6,0),"") | H26: =IFERROR(VLOOKUP($B26,'Stock Guide'!$B:$W,9,0),"") | I26: =IFERROR(VLOOKUP($B26,'Stock Guide'!$B:$W,8,0)/1000,"") | J26: =IFERROR(VLOOKUP($B26,'Stock Guide'!$B:$W,14,0),"") | K26: =IFERROR(N26/H26,"") | L26: =IFERROR(VLOOKUP($B26,'Stock Guide'!$B:$W,16,0),"") | M26: =IFERROR((N26/H26)*12,"") | N26: =IFERROR(VLOOKUP($B26,'Stock Guide'!$B:$W,19,0),"") | O26: =IFERROR(N26*E26,"") | P26: =IFERROR(VLOOKUP($B26,'Stock Guide'!$B:$W,20,0),"") | Q26: =IFERROR(VLOOKUP($B26,'Stock Guide'!$B:$W,21,0),"") | R26: =IFERROR(VLOOKUP($B26,'Stock Guide'!$B:$W,22,0),"")
D27: =IF(C27*$D$6=0,"",C27*$D$6) | E27: =IFERROR(ROUNDDOWN(D27/H27,0),"") | F27: =IFERROR(VLOOKUP($B27,'Stock Guide'!$B:$W,3,0),"") | G27: =IFERROR(VLOOKUP($B27,'Stock Guide'!$B:$W,6,0),"") | H27: =IFERROR(VLOOKUP($B27,'Stock Guide'!$B:$W,9,0),"") | I27: =IFERROR(VLOOKUP($B27,'Stock Guide'!$B:$W,8,0)/1000,"") | J27: =IFERROR(VLOOKUP($B27,'Stock Guide'!$B:$W,14,0),"") | K27: =IFERROR(N27/H27,"") | L27: =IFERROR(VLOOKUP($B27,'Stock Guide'!$B:$W,16,0),"") | M27: =IFERROR((N27/H27)*12,"") | N27: =IFERROR(VLOOKUP($B27,'Stock Guide'!$B:$W,19,0),"") | O27: =IFERROR(N27*E27,"") | P27: =IFERROR(VLOOKUP($B27,'Stock Guide'!$B:$W,20,0),"") | Q27: =IFERROR(VLOOKUP($B27,'Stock Guide'!$B:$W,21,0),"") | R27: =IFERROR(VLOOKUP($B27,'Stock Guide'!$B:$W,22,0),"")
D28: =IF(C28*$D$6=0,"",C28*$D$6) | E28: =IFERROR(ROUNDDOWN(D28/H28,0),"") | F28: =IFERROR(VLOOKUP($B28,'Stock Guide'!$B:$W,3,0),"") | G28: =IFERROR(VLOOKUP($B28,'Stock Guide'!$B:$W,6,0),"") | H28: =IFERROR(VLOOKUP($B28,'Stock Guide'!$B:$W,9,0),"") | I28: =IFERROR(VLOOKUP($B28,'Stock Guide'!$B:$W,8,0)/1000,"") | J28: =IFERROR(VLOOKUP($B28,'Stock Guide'!$B:$W,14,0),"") | K28: =IFERROR(N28/H28,"") | L28: =IFERROR(VLOOKUP($B28,'Stock Guide'!$B:$W,16,0),"") | M28: =IFERROR((N28/H28)*12,"") | N28: =IFERROR(VLOOKUP($B28,'Stock Guide'!$B:$W,19,0),"") | O28: =IFERROR(N28*E28,"") | P28: =IFERROR(VLOOKUP($B28,'Stock Guide'!$B:$W,20,0),"") | Q28: =IFERROR(VLOOKUP($B28,'Stock Guide'!$B:$W,21,0),"") | R28: =IFERROR(VLOOKUP($B28,'Stock Guide'!$B:$W,22,0),"")
D29: =IF(C29*$D$6=0,"",C29*$D$6) | E29: =IFERROR(ROUNDDOWN(D29/H29,0),"") | F29: =IFERROR(VLOOKUP($B29,'Stock Guide'!$B:$W,3,0),"") | G29: =IFERROR(VLOOKUP($B29,'Stock Guide'!$B:$W,6,0),"") | H29: =IFERROR(VLOOKUP($B29,'Stock Guide'!$B:$W,9,0),"") | I29: =IFERROR(VLOOKUP($B29,'Stock Guide'!$B:$W,8,0)/1000,"") | J29: =IFERROR(VLOOKUP($B29,'Stock Guide'!$B:$W,14,0),"") | K29: =IFERROR(N29/H29,"") | L29: =IFERROR(VLOOKUP($B29,'Stock Guide'!$B:$W,16,0),"") | M29: =IFERROR((N29/H29)*12,"") | N29: =IFERROR(VLOOKUP($B29,'Stock Guide'!$B:$W,19,0),"") | O29: =IFERROR(N29*E29,"") | P29: =IFERROR(VLOOKUP($B29,'Stock Guide'!$B:$W,20,0),"") | Q29: =IFERROR(VLOOKUP($B29,'Stock Guide'!$B:$W,21,0),"") | R29: =IFERROR(VLOOKUP($B29,'Stock Guide'!$B:$W,22,0),"")
D30: =IF(C30*$D$6=0,"",C30*$D$6) | E30: =IFERROR(ROUNDDOWN(D30/H30,0),"") | F30: =IFERROR(VLOOKUP($B30,'Stock Guide'!$B:$W,3,0),"") | G30: =IFERROR(VLOOKUP($B30,'Stock Guide'!$B:$W,6,0),"") | H30: =IFERROR(VLOOKUP($B30,'Stock Guide'!$B:$W,9,0),"") | I30: =IFERROR(VLOOKUP($B30,'Stock Guide'!$B:$W,8,0)/1000,"") | J30: =IFERROR(VLOOKUP($B30,'Stock Guide'!$B:$W,14,0),"") | K30: =IFERROR(N30/H30,"") | L30: =IFERROR(VLOOKUP($B30,'Stock Guide'!$B:$W,16,0),"") | M30: =IFERROR((N30/H30)*12,"") | N30: =IFERROR(VLOOKUP($B30,'Stock Guide'!$B:$W,19,0),"") | O30: =IFERROR(N30*E30,"") | P30: =IFERROR(VLOOKUP($B30,'Stock Guide'!$B:$W,20,0),"") | Q30: =IFERROR(VLOOKUP($B30,'Stock Guide'!$B:$W,21,0),"") | R30: =IFERROR(VLOOKUP($B30,'Stock Guide'!$B:$W,22,0),"")
D31: =IF(C31*$D$6=0,"",C31*$D$6) | E31: =IFERROR(ROUNDDOWN(D31/H31,0),"") | F31: =IFERROR(VLOOKUP($B31,'Stock Guide'!$B:$W,3,0),"") | G31: =IFERROR(VLOOKUP($B31,'Stock Guide'!$B:$W,6,0),"") | H31: =IFERROR(VLOOKUP($B31,'Stock Guide'!$B:$W,9,0),"") | I31: =IFERROR(VLOOKUP($B31,'Stock Guide'!$B:$W,8,0)/1000,"") | J31: =IFERROR(VLOOKUP($B31,'Stock Guide'!$B:$W,14,0),"") | K31: =IFERROR(N31/H31,"") | L31: =IFERROR(VLOOKUP($B31,'Stock Guide'!$B:$W,16,0),"") | M31: =IFERROR((N31/H31)*12,"") | N31: =IFERROR(VLOOKUP($B31,'Stock Guide'!$B:$W,19,0),"") | O31: =IFERROR(N31*E31,"") | P31: =IFERROR(VLOOKUP($B31,'Stock Guide'!$B:$W,20,0),"") | Q31: =IFERROR(VLOOKUP($B31,'Stock Guide'!$B:$W,21,0),"") | R31: =IFERROR(VLOOKUP($B31,'Stock Guide'!$B:$W,22,0),"")
D32: =IF(C32*$D$6=0,"",C32*$D$6) | E32: =IFERROR(ROUNDDOWN(D32/H32,0),"") | F32: =IFERROR(VLOOKUP($B32,'Stock Guide'!$B:$W,3,0),"") | G32: =IFERROR(VLOOKUP($B32,'Stock Guide'!$B:$W,6,0),"") | H32: =IFERROR(VLOOKUP($B32,'Stock Guide'!$B:$W,9,0),"") | I32: =IFERROR(VLOOKUP($B32,'Stock Guide'!$B:$W,8,0)/1000,"") | J32: =IFERROR(VLOOKUP($B32,'Stock Guide'!$B:$W,14,0),"") | K32: =IFERROR(N32/H32,"") | L32: =IFERROR(VLOOKUP($B32,'Stock Guide'!$B:$W,16,0),"") | M32: =IFERROR((N32/H32)*12,"") | N32: =IFERROR(VLOOKUP($B32,'Stock Guide'!$B:$W,19,0),"") | O32: =IFERROR(N32*E32,"") | P32: =IFERROR(VLOOKUP($B32,'Stock Guide'!$B:$W,20,0),"") | Q32: =IFERROR(VLOOKUP($B32,'Stock Guide'!$B:$W,21,0),"") | R32: =IFERROR(VLOOKUP($B32,'Stock Guide'!$B:$W,22,0),"")
D33: =IF(C33*$D$6=0,"",C33*$D$6) | E33: =IFERROR(ROUNDDOWN(D33/H33,0),"") | F33: =IFERROR(VLOOKUP($B33,'Stock Guide'!$B:$W,3,0),"") | G33: =IFERROR(VLOOKUP($B33,'Stock Guide'!$B:$W,6,0),"") | H33: =IFERROR(VLOOKUP($B33,'Stock Guide'!$B:$W,9,0),"") | I33: =IFERROR(VLOOKUP($B33,'Stock Guide'!$B:$W,8,0)/1000,"") | J33: =IFERROR(VLOOKUP($B33,'Stock Guide'!$B:$W,14,0),"") | K33: =IFERROR(N33/H33,"") | L33: =IFERROR(VLOOKUP($B33,'Stock Guide'!$B:$W,16,0),"") | M33: =IFERROR((N33/H33)*12,"") | N33: =IFERROR(VLOOKUP($B33,'Stock Guide'!$B:$W,19,0),"") | O33: =IFERROR(N33*E33,"") | P33: =IFERROR(VLOOKUP($B33,'Stock Guide'!$B:$W,20,0),"") | Q33: =IFERROR(VLOOKUP($B33,'Stock Guide'!$B:$W,21,0),"") | R33: =IFERROR(VLOOKUP($B33,'Stock Guide'!$B:$W,22,0),"")
B34: Média | C34: =SUM(C9:C33) -> 1 | D34: =SUM(D9:D33) -> 1000000 | I34: =SUMPRODUCT($I$9:$I$33,$C$9:$C$33) -> 9436.8489 | J34: =SUMPRODUCT(J$9:J$33,$C$9:$C$33) -> 0.86543223 | K34: =SUMPRODUCT(K$9:K$33,$C$9:$C$33) -> 0.010400808 | L34: =SUMPRODUCT(L$9:L$33,$C$9:$C$33) -> 0.12485618 | M34: =SUMPRODUCT(M$9:M$33,$C$9:$C$33) -> 0.1248097 | N34: - | O34: =SUM(O9:O33) -> 10394.158 | P34: =SUMPRODUCT(P$9:P$33,$C$9:$C$33) -> -0.033717952 | Q34: =SUMPRODUCT(Q$9:Q$33,$C$9:$C$33) -> -0.01025286 | R34: =SUMPRODUCT(R$9:R$33,$C$9:$C$33) -> 0.094273721
B36: 1- Corresponde ao último dividendo anunciado. O total leva em consideração a quantidade de cotas detidas para cada fundo.
B37: -Para adicionar mais linhas pressionar: (i) SHIFT + Espaço para selecionar a linha; (ii) CTRL + (Sinal de adição +); e (iii) arastar as formulas das colunas em branco.
B41: Composição da Carteira | H41: Liquidez
B60: Dividendos Mensais
B81: *Ressaltamos que só será possível simular carteiras cujos fundos possuam liquidez acima de R$ 50 mil/dia. **Não deixe de acessar nossos conteúdos no site https://content.btgpactual.com/research/home
C167: Atual
B168: Segmento | C168: % | F168: Nome | G168: Nome
B169: Recebível | C169: =SUMIFS($C$9:$C$33,$G$9:$G$33,B169) -> 0.52 | F169: =$B169&" ("&TEXT(C169,"0,0%")&")" -> Recebível (52,0%) | G169: =C169&" ("&TEXT(D169,"0,00%")&")" -> 0,52 (0,00%)
B170: Laje Corporativa | C170: =SUMIFS($C$9:$C$33,$G$9:$G$33,B170) -> 0.095 | F170: =$B170&" ("&TEXT(C170,"0,0%")&")" -> Laje Corporativa (9,5%) | G170: =C170&" ("&TEXT(D170,"0,00%")&")" -> 0,095 (0,00%)
B171: Galpão Logístico | C171: =SUMIFS($C$9:$C$33,$G$9:$G$33,B171) -> 0.22 | F171: =$B171&" ("&TEXT(C171,"0,0%")&")" -> Galpão Logístico (22,0%) | G171: =C171&" ("&TEXT(D171,"0,00%")&")" -> 0,22 (0,00%)
B172: Shopping Center | C172: =SUMIFS($C$9:$C$33,$G$9:$G$33,B172) -> 0.095 | F172: =$B172&" ("&TEXT(C172,"0,0%")&")" -> Shopping Center (9,5%) | G172: =C172&" ("&TEXT(D172,"0,00%")&")" -> 0,095 (0,00%)
B173: Híbrido | C173: =SUMIFS($C$9:$C$33,$G$9:$G$33,B173) -> 0 | F173: =$B173&" ("&TEXT(C173,"0,0%")&")" -> Híbrido (0,0%) | G173: =C173&" ("&TEXT(D173,"0,00%")&")" -> 0 (0,00%)
B174: Renda Urbana | C174: =SUMIFS($C$9:$C$33,$G$9:$G$33,B174) -> 0.07 | F174: =$B174&" ("&TEXT(C174,"0,0%")&")" -> Renda Urbana (7,0%) | G174: =C174&" ("&TEXT(D174,"0,00%")&")" -> 0,07 (0,00%)
B175: Fundo de Fundos | C175: =SUMIFS($C$9:$C$33,$G$9:$G$33,B175) -> 0 | F175: =$B175&" ("&TEXT(C175,"0,0%")&")" -> Fundo de Fundos (0,0%) | G175: =C175&" ("&TEXT(D175,"0,00%")&")" -> 0 (0,00%)
B176: Hedge Fund | C176: =SUMIFS($C$9:$C$33,$G$9:$G$33,B176) -> 0 | F176: =$B176&" ("&TEXT(C176,"0,0%")&")" -> Hedge Fund (0,0%) | G176: =C176&" ("&TEXT(D176,"0,00%")&")" -> 0 (0,00%)
B177: FIAgro - FII | C177: =SUMIFS($C$9:$C$33,$G$9:$G$33,B177) -> 0 | F177: =$B177&" ("&TEXT(C177,"0,0%")&")" -> FIAgro - FII (0,0%) | G177: =C177&" ("&TEXT(D177,"0,00%")&")" -> 0 (0,00%)
B178: FI-Infra | C178: =SUMIFS($C$9:$C$33,$G$9:$G$33,B178) -> 0 | F178: =$B178&" ("&TEXT(C178,"0,0%")&")" -> FI-Infra (0,0%) | G178: =C178&" ("&TEXT(D178,"0,00%")&")" -> 0 (0,00%)
B179: FIAgro - FIDC | C179: =SUMIFS($C$9:$C$33,$G$9:$G$33,B179) -> 0 | F179: =$B179&" ("&TEXT(C179,"0,0%")&")" -> FIAgro - FIDC (0,0%) | G179: =C179&" ("&TEXT(D179,"0,00%")&")" -> 0 (0,00%)
B180: Outros | C180: =SUM(C182:C198) -> 0 | F180: =$B180&" ("&TEXT(C180,"0,0%")&")" -> Outros (0,0%) | G180: =C180&" ("&TEXT(D180,"0,00%")&")" -> 0 (0,00%)
B182: Residencial | C182: =SUMIFS($C$9:$C$33,$G$9:$G$33,B182) -> 0
B183: Agência Bancária | C183: =SUMIFS($C$9:$C$33,$G$9:$G$33,B183) -> 0
B184: Agronegócio | C184: =SUMIFS($C$9:$C$33,$G$9:$G$33,B184) -> 0
B185: Educacional | C185: =SUMIFS($C$9:$C$33,$G$9:$G$33,B185) -> 0
B186: Varejo | C186: =SUMIFS($C$9:$C$33,$G$9:$G$33,B186) -> 0
B187: Hotel | C187: =SUMIFS($C$9:$C$33,$G$9:$G$33,B187) -> 0
B188: Outros | C188: =SUMIFS($C$9:$C$33,$G$9:$G$33,B188) -> 0
B189: Desenvolvimento | C189: =SUMIFS($C$9:$C$33,$G$9:$G$33,B189) -> 0
B190: Hospital | C190: =SUMIFS($C$9:$C$33,$G$9:$G$33,B190) -> 0

Sheet Simulador de Carteiras (R$)
Q2: Menu | R2: Stock Guide
B5: Simulação de Carteira
B7: Fundo | C7: Peso | D7: Financeiro | E7: Cotas | F7: Características | H7: Preço | I7: Liquidez | J7: P/VPA | K7: Dividend Yield | N7: Dividendos¹ | P7: Performance
B8: Ticker | C8: (%) | D8: R$ | E8: Qtde. | F8: Nome do Fundo | G8: Segmento | H8: R$/Cota | I8: Média (R$ milhares 3M) | J8: - | K8: Mês (%) | L8: 12M (%) | M8: Anualizado (%) | N8: R$/Cota | O8: Montante | P8: 1M (%) | Q8: No ano (%) | R8: LTM (%)
B9: BTCI11 | C9: =IF(D9=0,"",IFERROR(D9/$D$34,"")) -> 0.06 | D9: 60000 | E9: =IFERROR(ROUNDDOWN(D9/H9,0),"") -> 6666 | F9: =IFERROR(VLOOKUP($B9,'Stock Guide'!$B:$W,3,0),"") -> BTG Pactual Crédito Imobiliário FII | G9: =IFERROR(VLOOKUP($B9,'Stock Guide'!$B:$W,6,0),"") -> Recebível | H9: =IFERROR(VLOOKUP($B9,'Stock Guide'!$B:$W,9,0),"") -> 9 | I9: =IFERROR(VLOOKUP($B9,'Stock Guide'!$B:$W,8,0)/1000,"") -> 3504.8616 | J9: =IFERROR(VLOOKUP($B9,'Stock Guide'!$B:$W,14,0),"") -> 0.89215724 | K9: =IFERROR(N9/H9,"") -> 0.011444444 | L9: =IFERROR(VLOOKUP($B9,'Stock Guide'!$B:$W,16,0),"") -> 0.13055556 | M9: =IFERROR((N9/H9)*12,"") -> 0.13733333 | N9: =IFERROR(VLOOKUP($B9,'Stock Guide'!$B:$W,19,0),"") -> 0.103 | O9: =IFERROR(N9*E9,"") -> 686.598 | P9: =IFERROR(VLOOKUP($B9,'Stock Guide'!$B:$W,20,0),"") -> -0.0040443824 | Q9: =IFERROR(VLOOKUP($B9,'Stock Guide'!$B:$W,21,0),"") -> 0.048974723 | R9: =IFERROR(VLOOKUP($B9,'Stock Guide'!$B:$W,22,0),"") -> 0.12285468
B10: KNCR11 | C10: =IF(D10=0,"",IFERROR(D10/$D$34,"")) -> 0.13 | D10: 130000 | E10: =IFERROR(ROUNDDOWN(D10/H10,0),"") -> 1219 | F10: =IFERROR(VLOOKUP($B10,'Stock Guide'!$B:$W,3,0),"") -> Kinea Rendimentos Imobiliários FII | G10: =IFERROR(VLOOKUP($B10,'Stock Guide'!$B:$W,6,0),"") -> Recebível | H10: =IFERROR(VLOOKUP($B10,'Stock Guide'!$B:$W,9,0),"") -> 106.6 | I10: =IFERROR(VLOOKUP($B10,'Stock Guide'!$B:$W,8,0)/1000,"") -> 21474.426 | J10: =IFERROR(VLOOKUP($B10,'Stock Guide'!$B:$W,14,0),"") -> 1.0398102 | K10: =IFERROR(N10/H10,"") -> 0.011726079 | L10: =IFERROR(VLOOKUP($B10,'Stock Guide'!$B:$W,16,0),"") -> 0.13452158 | M10: =IFERROR((N10/H10)*12,"") -> 0.14071295 | N10: =IFERROR(VLOOKUP($B10,'Stock Guide'!$B:$W,19,0),"") -> 1.25 | O10: =IFERROR(N10*E10,"") -> 1523.75 | P10: =IFERROR(VLOOKUP($B10,'Stock Guide'!$B:$W,20,0),"") -> -0.0020595394 | Q10: =IFERROR(VLOOKUP($B10,'Stock Guide'!$B:$W,21,0),"") -> 0.080907164 | R10: =IFERROR(VLOOKUP($B10,'Stock Guide'!$B:$W,22,0),"") -> 0.18083758
B11: KNIP11 | C11: =IF(D11=0,"",IFERROR(D11/$D$34,"")) -> 0.13 | D11: 130000 | E11: =IFERROR(ROUNDDOWN(D11/H11,0),"") -> 1455 | F11: =IFERROR(VLOOKUP($B11,'Stock Guide'!$B:$W,3,0),"") -> Kinea Indices de Preços FII | G11: =IFERROR(VLOOKUP($B11,'Stock Guide'!$B:$W,6,0),"") -> Recebível | H11: =IFERROR(VLOOKUP($B11,'Stock Guide'!$B:$W,9,0),"") -> 89.3 | I11: =IFERROR(VLOOKUP($B11,'Stock Guide'!$B:$W,8,0)/1000,"") -> 10206.473 | J11: =IFERROR(VLOOKUP($B11,'Stock Guide'!$B:$W,14,0),"") -> 0.96172851 | K11: =IFERROR(N11/H11,"") -> 0.010638298 | L11: =IFERROR(VLOOKUP($B11,'Stock Guide'!$B:$W,16,0),"") -> 0.1137738 | M11: =IFERROR((N11/H11)*12,"") -> 0.12765957 | N11: =IFERROR(VLOOKUP($B11,'Stock Guide'!$B:$W,19,0),"") -> 0.95 | O11: =IFERROR(N11*E11,"") -> 1382.25 | P11: =IFERROR(VLOOKUP($B11,'Stock Guide'!$B:$W,20,0),"") -> -0.01478376 | Q11: =IFERROR(VLOOKUP($B11,'Stock Guide'!$B:$W,21,0),"") -> 0.070350425 | R11: =IFERROR(VLOOKUP($B11,'Stock Guide'!$B:$W,22,0),"") -> 0.15124008
B12: RBRR11 | C12: =IF(D12=0,"",IFERROR(D12/$D$34,"")) -> 0.03 | D12: 30000 | E12: =IFERROR(ROUNDDOWN(D12/H12,0),"") -> 400 | F12: =IFERROR(VLOOKUP($B12,'Stock Guide'!$B:$W,3,0),"") -> FII RBR Rendimento High | G12: =IFERROR(VLOOKUP($B12,'Stock Guide'!$B:$W,6,0),"") -> Recebível | H12: =IFERROR(VLOOKUP($B12,'Stock Guide'!$B:$W,9,0),"") -> 75 | I12: =IFERROR(VLOOKUP($B12,'Stock Guide'!$B:$W,8,0)/1000,"") -> 4149.1633 | J12: =IFERROR(VLOOKUP($B12,'Stock Guide'!$B:$W,14,0),"") -> 0.81605128 | K12: =IFERROR(N12/H12,"") -> 0.012 | L12: =IFERROR(VLOOKUP($B12,'Stock Guide'!$B:$W,16,0),"") -> 0.13173333 | M12: =IFERROR((N12/H12)*12,"") -> 0.144 | N12: =IFERROR(VLOOKUP($B12,'Stock Guide'!$B:$W,19,0),"") -> 0.9 | O12: =IFERROR(N12*E12,"") -> 360 | P12: =IFERROR(VLOOKUP($B12,'Stock Guide'!$B:$W,20,0),"") -> -0.00045359409 | Q12: =IFERROR(VLOOKUP($B12,'Stock Guide'!$B:$W,21,0),"") -> -0.070281297 | R12: =IFERROR(VLOOKUP($B12,'Stock Guide'!$B:$W,22,0),"") -> -0.023658733
B13: RBRY11 | C13: =IF(D13=0,"",IFERROR(D13/$D$34,"")) -> 0.09 | D13: 90000 | E13: =IFERROR(ROUNDDOWN(D13/H13,0),"") -> 1170 | F13: =IFERROR(VLOOKUP($B13,'Stock Guide'!$B:$W,3,0),"") -> RBR Crédito Imobiliário Estruturado FII | G13: =IFERROR(VLOOKUP($B13,'Stock Guide'!$B:$W,6,0),"") -> Recebível | H13: =IFERROR(VLOOKUP($B13,'Stock Guide'!$B:$W,9,0),"") -> 76.87 | I13: =IFERROR(VLOOKUP($B13,'Stock Guide'!$B:$W,8,0)/1000,"") -> 4305.7881 | J13: =IFERROR(VLOOKUP($B13,'Stock Guide'!$B:$W,14,0),"") -> 0.76119222 | K13: =IFERROR(N13/H13,"") -> 0.013008976 | L13: =IFERROR(VLOOKUP($B13,'Stock Guide'!$B:$W,16,0),"") -> 0.17627163 | M13: =IFERROR((N13/H13)*12,"") -> 0.15610771 | N13: =IFERROR(VLOOKUP($B13,'Stock Guide'!$B:$W,19,0),"") -> 1 | O13: =IFERROR(N13*E13,"") -> 1170 | P13: =IFERROR(VLOOKUP($B13,'Stock Guide'!$B:$W,20,0),"") -> -0.081375577 | Q13: =IFERROR(VLOOKUP($B13,'Stock Guide'!$B:$W,21,0),"") -> -0.13772419 | R13: =IFERROR(VLOOKUP($B13,'Stock Guide'!$B:$W,22,0),"") -> -0.038285445
B14: MCCI11 | C14: =IF(D14=0,"",IFERROR(D14/$D$34,"")) -> 0.08 | D14: 80000 | E14: =IFERROR(ROUNDDOWN(D14/H14,0),"") -> 856 | F14: =IFERROR(VLOOKUP($B14,'Stock Guide'!$B:$W,3,0),"") -> Mauá Capital Recebíveis Imobiliários FII | G14: =IFERROR(VLOOKUP($B14,'Stock Guide'!$B:$W,6,0),"") -> Recebível | H14: =IFERROR(VLOOKUP($B14,'Stock Guide'!$B:$W,9,0),"") -> 93.38 | I14: =IFERROR(VLOOKUP($B14,'Stock Guide'!$B:$W,8,0)/1000,"") -> 4539.8289 | J14: =IFERROR(VLOOKUP($B14,'Stock Guide'!$B:$W,14,0),"") -> 0.99342629 | K14: =IFERROR(N14/H14,"") -> 0.010708931 | L14: =IFERROR(VLOOKUP($B14,'Stock Guide'!$B:$W,16,0),"") -> 0.12850717 | M14: =IFERROR((N14/H14)*12,"") -> 0.12850717 | N14: =IFERROR(VLOOKUP($B14,'Stock Guide'!$B:$W,19,0),"") -> 1 | O14: =IFERROR(N14*E14,"") -> 856 | P14: =IFERROR(VLOOKUP($B14,'Stock Guide'!$B:$W,20,0),"") -> -0.0042546667 | Q14: =IFERROR(VLOOKUP($B14,'Stock Guide'!$B:$W,21,0),"") -> 0.11080271 | R14: =IFERROR(VLOOKUP($B14,'Stock Guide'!$B:$W,22,0),"") -> 0.26147021
B15: VILG11 | C15: =IF(D15=0,"",IFERROR(D15/$D$34,"")) -> 0.045 | D15: 45000 | E15: =IFERROR(ROUNDDOWN(D15/H15,0),"") -> 490 | F15: =IFERROR(VLOOKUP($B15,'Stock Guide'!$B:$W,3,0),"") -> Vinci Logística FII | G15: =IFERROR(VLOOKUP($B15,'Stock Guide'!$B:$W,6,0),"") -> Galpão Logístico | H15: =IFERROR(VLOOKUP($B15,'Stock Guide'!$B:$W,9,0),"") -> 91.65 | I15: =IFERROR(VLOOKUP($B15,'Stock Guide'!$B:$W,8,0)/1000,"") -> 2575.8593 | J15: =IFERROR(VLOOKUP($B15,'Stock Guide'!$B:$W,14,0),"") -> 0.83834886 | K15: =IFERROR(N15/H15,"") -> 0.0089470813 | L15: =IFERROR(VLOOKUP($B15,'Stock Guide'!$B:$W,16,0),"") -> 0.10190944 | M15: =IFERROR((N15/H15)*12,"") -> 0.10736498 | N15: =IFERROR(VLOOKUP($B15,'Stock Guide'!$B:$W,19,0),"") -> 0.82 | O15: =IFERROR(N15*E15,"") -> 401.8 | P15: =IFERROR(VLOOKUP($B15,'Stock Guide'!$B:$W,20,0),"") -> 0.0058165057 | Q15: =IFERROR(VLOOKUP($B15,'Stock Guide'!$B:$W,21,0),"") -> -0.016190668 | R15: =IFERROR(VLOOKUP($B15,'Stock Guide'!$B:$W,22,0),"") -> 0.25374251
B16: BRCO11 | C16: =IF(D16=0,"",IFERROR(D16/$D$34,"")) -> 0.045 | D16: 45000 | E16: =IFERROR(ROUNDDOWN(D16/H16,0),"") -> 402 | F16: =IFERROR(VLOOKUP($B16,'Stock Guide'!$B:$W,3,0),"") -> Bresco Logística FII | G16: =IFERROR(VLOOKUP($B16,'Stock Guide'!$B:$W,6,0),"") -> Galpão Logístico | H16: =IFERROR(VLOOKUP($B16,'Stock Guide'!$B:$W,9,0),"") -> 111.84 | I16: =IFERROR(VLOOKUP($B16,'Stock Guide'!$B:$W,8,0)/1000,"") -> 5135.9864 | J16: =IFERROR(VLOOKUP($B16,'Stock Guide'!$B:$W,14,0),"") -> 0.97361058 | K16: =IFERROR(N16/H16,"") -> 0.0081366237 | L16: =IFERROR(VLOOKUP($B16,'Stock Guide'!$B:$W,16,0),"") -> 0.097639485 | M16: =IFERROR((N16/H16)*12,"") -> 0.097639485 | N16: =IFERROR(VLOOKUP($B16,'Stock Guide'!$B:$W,19,0),"") -> 0.91 | O16: =IFERROR(N16*E16,"") -> 365.82 | P16: =IFERROR(VLOOKUP($B16,'Stock Guide'!$B:$W,20,0),"") -> -0.019291477 | Q16: =IFERROR(VLOOKUP($B16,'Stock Guide'!$B:$W,21,0),"") -> 0.010814626 | R16: =IFERROR(VLOOKUP($B16,'Stock Guide'!$B:$W,22,0),"") -> 0.12894551
B17: BTLG11 | C17: =IF(D17=0,"",IFERROR(D17/$D$34,"")) -> 0.13 | D17: 130000 | E17: =IFERROR(ROUNDDOWN(D17/H17,0),"") -> 1321 | F17: =IFERROR(VLOOKUP($B17,'Stock Guide'!$B:$W,3,0),"") -> BTG Pactual Logística FII | G17: =IFERROR(VLOOKUP($B17,'Stock Guide'!$B:$W,6,0),"") -> Galpão Logístico | H17: =IFERROR(VLOOKUP($B17,'Stock Guide'!$B:$W,9,0),"") -> 98.37 | I17: =IFERROR(VLOOKUP($B17,'Stock Guide'!$B:$W,8,0)/1000,"") -> 12468.438 | J17: =IFERROR(VLOOKUP($B17,'Stock Guide'!$B:$W,14,0),"") -> 0.92052045 | K17: =IFERROR(N17/H17,"") -> 0.0082342177 | L17: =IFERROR(VLOOKUP($B17,'Stock Guide'!$B:$W,16,0),"") -> 0.097590729 | M17: =IFERROR((N17/H17)*12,"") -> 0.098810613 | N17: =IFERROR(VLOOKUP($B17,'Stock Guide'!$B:$W,19,0),"") -> 0.81 | O17: =IFERROR(N17*E17,"") -> 1070.01 | P17: =IFERROR(VLOOKUP($B17,'Stock Guide'!$B:$W,20,0),"") -> -0.016233044 | Q17: =IFERROR(VLOOKUP($B17,'Stock Guide'!$B:$W,21,0),"") -> 0.022844674 | R17: =IFERROR(VLOOKUP($B17,'Stock Guide'!$B:$W,22,0),"") -> 0.093649125
B18: BRCR11 | C18: =IF(D18=0,"",IFERROR(D18/$D$34,"")) -> 0.045 | D18: 45000 | E18: =IFERROR(ROUNDDOWN(D18/H18,0),"") -> 1148 | F18: =IFERROR(VLOOKUP($B18,'Stock Guide'!$B:$W,3,0),"") -> BTG Pactual Corporate Offices FII | G18: =IFERROR(VLOOKUP($B18,'Stock Guide'!$B:$W,6,0),"") -> Laje Corporativa | H18: =IFERROR(VLOOKUP($B18,'Stock Guide'!$B:$W,9,0),"") -> 39.19 | I18: =IFERROR(VLOOKUP($B18,'Stock Guide'!$B:$W,8,0)/1000,"") -> 1254.8978 | J18: =IFERROR(VLOOKUP($B18,'Stock Guide'!$B:$W,14,0),"") -> 0.48377811 | K18: =IFERROR(N18/H18,"") -> 0.010461853 | L18: =IFERROR(VLOOKUP($B18,'Stock Guide'!$B:$W,16,0),"") -> 0.12554223 | M18: =IFERROR((N18/H18)*12,"") -> 0.12554223 | N18: =IFERROR(VLOOKUP($B18,'Stock Guide'!$B:$W,19,0),"") -> 0.41 | O18: =IFERROR(N18*E18,"") -> 470.68 | P18: =IFERROR(VLOOKUP($B18,'Stock Guide'!$B:$W,20,0),"") -> -0.018103263 | Q18: =IFERROR(VLOOKUP($B18,'Stock Guide'!$B:$W,21,0),"") -> -0.082991445 | R18: =IFERROR(VLOOKUP($B18,'Stock Guide'!$B:$W,22,0),"") -> 0.084784476
B19: PVBI11 | C19: =IF(D19=0,"",IFERROR(D19/$D$34,"")) -> 0.05 | D19: 50000 | E19: =IFERROR(ROUNDDOWN(D19/H19,0),"") -> 750 | F19: =IFERROR(VLOOKUP($B19,'Stock Guide'!$B:$W,3,0),"") -> VBI Prime Properties | G19: =IFERROR(VLOOKUP($B19,'Stock Guide'!$B:$W,6,0),"") -> Laje Corporativa | H19: =IFERROR(VLOOKUP($B19,'Stock Guide'!$B:$W,9,0),"") -> 66.66 | I19: =IFERROR(VLOOKUP($B19,'Stock Guide'!$B:$W,8,0)/1000,"") -> 3815.4922 | J19: =IFERROR(VLOOKUP($B19,'Stock Guide'!$B:$W,14,0),"") -> 0.63782682 | K19: =IFERROR(N19/H19,"") -> 0.0060006001 | L19: =IFERROR(VLOOKUP($B19,'Stock Guide'!$B:$W,16,0),"") -> 0.077257726 | M19: =IFERROR((N19/H19)*12,"") -> 0.072007201 | N19: =IFERROR(VLOOKUP($B19,'Stock Guide'!$B:$W,19,0),"") -> 0.4 | O19: =IFERROR(N19*E19,"") -> 300 | P19: =IFERROR(VLOOKUP($B19,'Stock Guide'!$B:$W,20,0),"") -> -0.038372764 | Q19: =IFERROR(VLOOKUP($B19,'Stock Guide'!$B:$W,21,0),"") -> -0.15062473 | R19: =IFERROR(VLOOKUP($B19,'Stock Guide'!$B:$W,22,0),"") -> -0.042919195
B20: HGBS11 | C20: =IF(D20=0,"",IFERROR(D20/$D$34,"")) -> 0.03 | D20: 30000 | E20: =IFERROR(ROUNDDOWN(D20/H20,0),"") -> 1612 | F20: =IFERROR(VLOOKUP($B20,'Stock Guide'!$B:$W,3,0),"") -> Hedge Brasil Shopping FII | G20: =IFERROR(VLOOKUP($B20,'Stock Guide'!$B:$W,6,0),"") -> Shopping Center | H20: =IFERROR(VLOOKUP($B20,'Stock Guide'!$B:$W,9,0),"") -> 18.6 | I20: =IFERROR(VLOOKUP($B20,'Stock Guide'!$B:$W,8,0)/1000,"") -> 4435.5009 | J20: =IFERROR(VLOOKUP($B20,'Stock Guide'!$B:$W,14,0),"") -> 0.91869993 | K20: =IFERROR(N20/H20,"") -> 0.0091397849 | L20: =IFERROR(VLOOKUP($B20,'Stock Guide'!$B:$W,16,0),"") -> 0.10376344 | M20: =IFERROR((N20/H20)*12,"") -> 0.10967742 | N20: =IFERROR(VLOOKUP($B20,'Stock Guide'!$B:$W,19,0),"") -> 0.17 | O20: =IFERROR(N20*E20,"") -> 274.04 | P20: =IFERROR(VLOOKUP($B20,'Stock Guide'!$B:$W,20,0),"") -> -0.019504481 | Q20: =IFERROR(VLOOKUP($B20,'Stock Guide'!$B:$W,21,0),"") -> -0.0059386745 | R20: =IFERROR(VLOOKUP($B20,'Stock Guide'!$B:$W,22,0),"") -> 0.088335597
... B24: TRXF11 | C24: =IF(D24=0,"",IFERROR(D24/$D$34,"")) -> 0.07 | D24: 70000 | E24: =IFERROR(ROUNDDOWN(D24/H24,0),"") -> 974 | F24: =IFERROR(VLOOKUP($B24,'Stock Guide'!$B:$W,3,0),"") -> TRX Real Estate FII | G24: =IFERROR(VLOOKUP($B24,'Stock Guide'!$B:$W,6,0),"") -> Renda Urbana | H24: =IFERROR(VLOOKUP($B24,'Stock Guide'!$B:$W,9,0),"") -> 71.8 | I24: =IFERROR(VLOOKUP($B24,'Stock Guide'!$B:$W,8,0)/1000,"") -> 23831.971 | J24: =IFERROR(VLOOKUP($B24,'Stock Guide'!$B:$W,14,0),"") -> 0.73970401 | K24: =IFERROR(N24/H24,"") -> 0.012952646 | L24: =IFERROR(VLOOKUP($B24,'Stock Guide'!$B:$W,16,0),"") -> 0.1643454 | M24: =IFERROR((N24/H24)*12,"") -> 0.15543175 | N24: =IFERROR(VLOOKUP($B24,'Stock Guide'!$B:$W,19,0),"") -> 0.93 | O24: =IFERROR(N24*E24,"") -> 905.82 | P24: =IFERROR(VLOOKUP($B24,'Stock Guide'!$B:$W,20,0),"") -> -0.20372629 | Q24: =IFERROR(VLOOKUP($B24,'Stock Guide'!$B:$W,21,0),"") -> -0.20018374 | R24: =IFERROR(VLOOKUP($B24,'Stock Guide'!$B:$W,22,0),"") -> -0.16191836
C25: =IF(D25=0,"",IFERROR(D25/$D$34,"")) | E25: =IFERROR(ROUNDDOWN(D25/H25,0),"") | F25: =IFERROR(VLOOKUP($B25,'Stock Guide'!$B:$W,3,0),"") | G25: =IFERROR(VLOOKUP($B25,'Stock Guide'!$B:$W,6,0),"") | H25: =IFERROR(VLOOKUP($B25,'Stock Guide'!$B:$W,9,0),"") | I25: =IFERROR(VLOOKUP($B25,'Stock Guide'!$B:$W,8,0)/1000,"") | J25: =IFERROR(VLOOKUP($B25,'Stock Guide'!$B:$W,14,0),"") | K25: =IFERROR(N25/H25,"") | L25: =IFERROR(VLOOKUP($B25,'Stock Guide'!$B:$W,16,0),"") | M25: =IFERROR((N25/H25)*12,"") | N25: =IFERROR(VLOOKUP($B25,'Stock Guide'!$B:$W,19,0),"") | O25: =IFERROR(N25*E25,"") | P25: =IFERROR(VLOOKUP($B25,'Stock Guide'!$B:$W,20,0),"") | Q25: =IFERROR(VLOOKUP($B25,'Stock Guide'!$B:$W,21,0),"") | R25: =IFERROR(VLOOKUP($B25,'Stock Guide'!$B:$W,22,0),"")
C26: =IF(D26=0,"",IFERROR(D26/$D$34,"")) | E26: =IFERROR(ROUNDDOWN(D26/H26,0),"") | F26: =IFERROR(VLOOKUP($B26,'Stock Guide'!$B:$W,3,0),"") | G26: =IFERROR(VLOOKUP($B26,'Stock Guide'!$B:$W,6,0),"") | H26: =IFERROR(VLOOKUP($B26,'Stock Guide'!$B:$W,9,0),"") | I26: =IFERROR(VLOOKUP($B26,'Stock Guide'!$B:$W,8,0)/1000,"") | J26: =IFERROR(VLOOKUP($B26,'Stock Guide'!$B:$W,14,0),"") | K26: =IFERROR(N26/H26,"") | L26: =IFERROR(VLOOKUP($B26,'Stock Guide'!$B:$W,16,0),"") | M26: =IFERROR((N26/H26)*12,"") | N26: =IFERROR(VLOOKUP($B26,'Stock Guide'!$B:$W,19,0),"") | O26: =IFERROR(N26*E26,"") | P26: =IFERROR(VLOOKUP($B26,'Stock Guide'!$B:$W,20,0),"") | Q26: =IFERROR(VLOOKUP($B26,'Stock Guide'!$B:$W,21,0),"") | R26: =IFERROR(VLOOKUP($B26,'Stock Guide'!$B:$W,22,0),"")
C27: =IF(D27=0,"",IFERROR(D27/$D$34,"")) | E27: =IFERROR(ROUNDDOWN(D27/H27,0),"") | F27: =IFERROR(VLOOKUP($B27,'Stock Guide'!$B:$W,3,0),"") | G27: =IFERROR(VLOOKUP($B27,'Stock Guide'!$B:$W,6,0),"") | H27: =IFERROR(VLOOKUP($B27,'Stock Guide'!$B:$W,9,0),"") | I27: =IFERROR(VLOOKUP($B27,'Stock Guide'!$B:$W,8,0)/1000,"") | J27: =IFERROR(VLOOKUP($B27,'Stock Guide'!$B:$W,14,0),"") | K27: =IFERROR(N27/H27,"") | L27: =IFERROR(VLOOKUP($B27,'Stock Guide'!$B:$W,16,0),"") | M27: =IFERROR((N27/H27)*12,"") | N27: =IFERROR(VLOOKUP($B27,'Stock Guide'!$B:$W,19,0),"") | O27: =IFERROR(N27*E27,"") | P27: =IFERROR(VLOOKUP($B27,'Stock Guide'!$B:$W,20,0),"") | Q27: =IFERROR(VLOOKUP($B27,'Stock Guide'!$B:$W,21,0),"") | R27: =IFERROR(VLOOKUP($B27,'Stock Guide'!$B:$W,22,0),"")
C28: =IF(D28=0,"",IFERROR(D28/$D$34,"")) | E28: =IFERROR(ROUNDDOWN(D28/H28,0),"") | F28: =IFERROR(VLOOKUP($B28,'Stock Guide'!$B:$W,3,0),"") | G28: =IFERROR(VLOOKUP($B28,'Stock Guide'!$B:$W,6,0),"") | H28: =IFERROR(VLOOKUP($B28,'Stock Guide'!$B:$W,9,0),"") | I28: =IFERROR(VLOOKUP($B28,'Stock Guide'!$B:$W,8,0)/1000,"") | J28: =IFERROR(VLOOKUP($B28,'Stock Guide'!$B:$W,14,0),"") | K28: =IFERROR(N28/H28,"") | L28: =IFERROR(VLOOKUP($B28,'Stock Guide'!$B:$W,16,0),"") | M28: =IFERROR((N28/H28)*12,"") | N28: =IFERROR(VLOOKUP($B28,'Stock Guide'!$B:$W,19,0),"") | O28: =IFERROR(N28*E28,"") | P28: =IFERROR(VLOOKUP($B28,'Stock Guide'!$B:$W,20,0),"") | Q28: =IFERROR(VLOOKUP($B28,'Stock Guide'!$B:$W,21,0),"") | R28: =IFERROR(VLOOKUP($B28,'Stock Guide'!$B:$W,22,0),"")
C29: =IF(D29=0,"",IFERROR(D29/$D$34,"")) | E29: =IFERROR(ROUNDDOWN(D29/H29,0),"") | F29: =IFERROR(VLOOKUP($B29,'Stock Guide'!$B:$W,3,0),"") | G29: =IFERROR(VLOOKUP($B29,'Stock Guide'!$B:$W,6,0),"") | H29: =IFERROR(VLOOKUP($B29,'Stock Guide'!$B:$W,9,0),"") | I29: =IFERROR(VLOOKUP($B29,'Stock Guide'!$B:$W,8,0)/1000,"") | J29: =IFERROR(VLOOKUP($B29,'Stock Guide'!$B:$W,14,0),"") | K29: =IFERROR(N29/H29,"") | L29: =IFERROR(VLOOKUP($B29,'Stock Guide'!$B:$W,16,0),"") | M29: =IFERROR((N29/H29)*12,"") | N29: =IFERROR(VLOOKUP($B29,'Stock Guide'!$B:$W,19,0),"") | O29: =IFERROR(N29*E29,"") | P29: =IFERROR(VLOOKUP($B29,'Stock Guide'!$B:$W,20,0),"") | Q29: =IFERROR(VLOOKUP($B29,'Stock Guide'!$B:$W,21,0),"") | R29: =IFERROR(VLOOKUP($B29,'Stock Guide'!$B:$W,22,0),"")
C30: =IF(D30=0,"",IFERROR(D30/$D$34,"")) | E30: =IFERROR(ROUNDDOWN(D30/H30,0),"") | F30: =IFERROR(VLOOKUP($B30,'Stock Guide'!$B:$W,3,0),"") | G30: =IFERROR(VLOOKUP($B30,'Stock Guide'!$B:$W,6,0),"") | H30: =IFERROR(VLOOKUP($B30,'Stock Guide'!$B:$W,9,0),"") | I30: =IFERROR(VLOOKUP($B30,'Stock Guide'!$B:$W,8,0)/1000,"") | J30: =IFERROR(VLOOKUP($B30,'Stock Guide'!$B:$W,14,0),"") | K30: =IFERROR(N30/H30,"") | L30: =IFERROR(VLOOKUP($B30,'Stock Guide'!$B:$W,16,0),"") | M30: =IFERROR((N30/H30)*12,"") | N30: =IFERROR(VLOOKUP($B30,'Stock Guide'!$B:$W,19,0),"") | O30: =IFERROR(N30*E30,"") | P30: =IFERROR(VLOOKUP($B30,'Stock Guide'!$B:$W,20,0),"") | Q30: =IFERROR(VLOOKUP($B30,'Stock Guide'!$B:$W,21,0),"") | R30: =IFERROR(VLOOKUP($B30,'Stock Guide'!$B:$W,22,0),"")
C31: =IF(D31=0,"",IFERROR(D31/$D$34,"")) | E31: =IFERROR(ROUNDDOWN(D31/H31,0),"") | F31: =IFERROR(VLOOKUP($B31,'Stock Guide'!$B:$W,3,0),"") | G31: =IFERROR(VLOOKUP($B31,'Stock Guide'!$B:$W,6,0),"") | H31: =IFERROR(VLOOKUP($B31,'Stock Guide'!$B:$W,9,0),"") | I31: =IFERROR(VLOOKUP($B31,'Stock Guide'!$B:$W,8,0)/1000,"") | J31: =IFERROR(VLOOKUP($B31,'Stock Guide'!$B:$W,14,0),"") | K31: =IFERROR(N31/H31,"") | L31: =IFERROR(VLOOKUP($B31,'Stock Guide'!$B:$W,16,0),"") | M31: =IFERROR((N31/H31)*12,"") | N31: =IFERROR(VLOOKUP($B31,'Stock Guide'!$B:$W,19,0),"") | O31: =IFERROR(N31*E31,"") | P31: =IFERROR(VLOOKUP($B31,'Stock Guide'!$B:$W,20,0),"") | Q31: =IFERROR(VLOOKUP($B31,'Stock Guide'!$B:$W,21,0),"") | R31: =IFERROR(VLOOKUP($B31,'Stock Guide'!$B:$W,22,0),"")
C32: =IF(D32=0,"",IFERROR(D32/$D$34,"")) | E32: =IFERROR(ROUNDDOWN(D32/H32,0),"") | F32: =IFERROR(VLOOKUP($B32,'Stock Guide'!$B:$W,3,0),"") | G32: =IFERROR(VLOOKUP($B32,'Stock Guide'!$B:$W,6,0),"") | H32: =IFERROR(VLOOKUP($B32,'Stock Guide'!$B:$W,9,0),"") | I32: =IFERROR(VLOOKUP($B32,'Stock Guide'!$B:$W,8,0)/1000,"") | J32: =IFERROR(VLOOKUP($B32,'Stock Guide'!$B:$W,14,0),"") | K32: =IFERROR(N32/H32,"") | L32: =IFERROR(VLOOKUP($B32,'Stock Guide'!$B:$W,16,0),"") | M32: =IFERROR((N32/H32)*12,"") | N32: =IFERROR(VLOOKUP($B32,'Stock Guide'!$B:$W,19,0),"") | O32: =IFERROR(N32*E32,"") | P32: =IFERROR(VLOOKUP($B32,'Stock Guide'!$B:$W,20,0),"") | Q32: =IFERROR(VLOOKUP($B32,'Stock Guide'!$B:$W,21,0),"") | R32: =IFERROR(VLOOKUP($B32,'Stock Guide'!$B:$W,22,0),"")
C33: =IF(D33=0,"",IFERROR(D33/$D$34,"")) | E33: =IFERROR(ROUNDDOWN(D33/H33,0),"") | F33: =IFERROR(VLOOKUP($B33,'Stock Guide'!$B:$W,3,0),"") | G33: =IFERROR(VLOOKUP($B33,'Stock Guide'!$B:$W,6,0),"") | H33: =IFERROR(VLOOKUP($B33,'Stock Guide'!$B:$W,9,0),"") | I33: =IFERROR(VLOOKUP($B33,'Stock Guide'!$B:$W,8,0)/1000,"") | J33: =IFERROR(VLOOKUP($B33,'Stock Guide'!$B:$W,14,0),"") | K33: =IFERROR(N33/H33,"") | L33: =IFERROR(VLOOKUP($B33,'Stock Guide'!$B:$W,16,0),"") | M33: =IFERROR((N33/H33)*12,"") | N33: =IFERROR(VLOOKUP($B33,'Stock Guide'!$B:$W,19,0),"") | O33: =IFERROR(N33*E33,"") | P33: =IFERROR(VLOOKUP($B33,'Stock Guide'!$B:$W,20,0),"") | Q33: =IFERROR(VLOOKUP($B33,'Stock Guide'!$B:$W,21,0),"") | R33: =IFERROR(VLOOKUP($B33,'Stock Guide'!$B:$W,22,0),"")
B34: Média | C34: =SUM(C9:C33) -> 1 | D34: =SUM(D9:D33) -> 1000000 | I34: =SUMPRODUCT($I$9:$I$33,$C$9:$C$33) -> 9436.8489 | J34: =SUMPRODUCT(J$9:J$33,$C$9:$C$33) -> 0.86543223 | K34: =SUMPRODUCT(K$9:K$33,$C$9:$C$33) -> 0.010400808 | L34: =SUMPRODUCT(L$9:L$33,$C$9:$C$33) -> 0.12485618 | M34: =SUMPRODUCT(M$9:M$33,$C$9:$C$33) -> 0.1248097 | N34: - | O34: =SUM(O9:O33) -> 10394.158 | P34: =SUMPRODUCT(P$9:P$33,$C$9:$C$33) -> -0.033717952 | Q34: =SUMPRODUCT(Q$9:Q$33,$C$9:$C$33) -> -0.01025286 | R34: =SUMPRODUCT(R$9:R$33,$C$9:$C$33) -> 0.094273721
B36: 1- Corresponde ao último dividendo anunciado. O total leva em consideração a quantidade de cotas detidas para cada fundo.
B37: -Para adicionar mais linhas pressionar: (i) SHIFT + Espaço para selecionar a linha; (ii) CTRL + (Sinal de adição +); e (iii) arastar as formulas das colunas em branco.
B41: Composição da Carteira | H41: Liquidez
B60: Dividendos Mensais
B81: *Ressaltamos que só será possível simular carteiras cujos fundos possuam liquidez acima de R$ 50 mil/dia. **Não deixe de acessar nossos conteúdos no site https://content.btgpactual.com/research/home
B168: Segmento | C168: % | D168: Nome
B169: Recebível | C169: =SUMIFS($C$9:$C$33,$G$9:$G$33,B169) -> 0.52 | D169: =B169&" ("&TEXT(C169,"0,00%")&")" -> Recebível (52,00%)
B170: Laje Corporativa | C170: =SUMIFS($C$9:$C$33,$G$9:$G$33,B170) -> 0.095 | D170: =B170&" ("&TEXT(C170,"0,00%")&")" -> Laje Corporativa (9,50%)
B171: Galpão Logístico | C171: =SUMIFS($C$9:$C$33,$G$9:$G$33,B171) -> 0.22 | D171: =B171&" ("&TEXT(C171,"0,00%")&")" -> Galpão Logístico (22,00%)
B172: Shopping Center | C172: =SUMIFS($C$9:$C$33,$G$9:$G$33,B172) -> 0.095 | D172: =B172&" ("&TEXT(C172,"0,00%")&")" -> Shopping Center (9,50%)
B173: Híbrido | C173: =SUMIFS($C$9:$C$33,$G$9:$G$33,B173) -> 0 | D173: =B173&" ("&TEXT(C173,"0,00%")&")" -> Híbrido (0,00%)
B174: Renda Urbana | C174: =SUMIFS($C$9:$C$33,$G$9:$G$33,B174) -> 0.07 | D174: =B174&" ("&TEXT(C174,"0,00%")&")" -> Renda Urbana (7,00%)
B175: Fundo de Fundos | C175: =SUMIFS($C$9:$C$33,$G$9:$G$33,B175) -> 0 | D175: =B175&" ("&TEXT(C175,"0,00%")&")" -> Fundo de Fundos (0,00%)
B176: Hedge Fund | C176: =SUMIFS($C$9:$C$33,$G$9:$G$33,B176) -> 0 | D176: =B176&" ("&TEXT(C176,"0,00%")&")" -> Hedge Fund (0,00%)
B177: FIAgro - FII | C177: =SUMIFS($C$9:$C$33,$G$9:$G$33,B177) -> 0 | D177: =B177&" ("&TEXT(C177,"0,00%")&")" -> FIAgro - FII (0,00%)
B178: FI-Infra | C178: =SUMIFS($C$9:$C$33,$G$9:$G$33,B178) -> 0 | D178: =B178&" ("&TEXT(C178,"0,00%")&")" -> FI-Infra (0,00%)
B179: FIAgro - FIDC | C179: =SUMIFS($C$9:$C$33,$G$9:$G$33,B179) -> 0 | D179: =B179&" ("&TEXT(C179,"0,00%")&")" -> FIAgro - FIDC (0,00%)
B180: Outros | C180: =SUM(C182:C191) -> 0 | D180: =B180&" ("&TEXT(C180,"0,00%")&")" -> Outros (0,00%)
B182: Residencial | C182: =SUMIFS($C$9:$C$33,$G$9:$G$33,B182) -> 0
B183: Agência Bancária | C183: =SUMIFS($C$9:$C$33,$G$9:$G$33,B183) -> 0
B184: Agronegócio | C184: =SUMIFS($C$9:$C$33,$G$9:$G$33,B184) -> 0
B185: Educacional | C185: =SUMIFS($C$9:$C$33,$G$9:$G$33,B185) -> 0
B186: Varejo | C186: =SUMIFS($C$9:$C$33,$G$9:$G$33,B186) -> 0
B187: Hotel | C187: =SUMIFS($C$9:$C$33,$G$9:$G$33,B187) -> 0
B188: Outros | C188: =SUMIFS($C$9:$C$33,$G$9:$G$33,B188) -> 0
B189: Desenvolvimento | C189: =SUMIFS($C$9:$C$33,$G$9:$G$33,B189) -> 0
B190: Hospital | C190: =SUMIFS($C$9:$C$33,$G$9:$G$33,B190) -> 0

Sheet Simulador de Aportes (R$)
T2: Menu | U2: Stock Guide
B5: Simulação de Aporte
C7: Carteira Atual | F7: Aporte
B8: Fundo | C8: Peso | D8: Financeiro | E8: Cotas | F8: Aporte | G8: Financeiro² | H8: Peso | I8: Cotas | J8: Características | L8: Preço | M8: Liquidez | N8: P/VPA | O8: Dividend Yield | R8: Dividendos | S8: Performance
B9: Ticker | C9: Atual (%) | D9: Atual R$ | E9: Atuais (%) | F9: R$ | G9: Pós Aporte R$ | H9: Pós Aporte (%) | I9: Pós Aporte (%) | J9: Nome do Fundo | K9: Segmento | L9: R$/Cota | M9: Média (R$ milhares 3M) | N9: - | O9: Mês (%) | P9: 12M (%) | Q9: Anualizado (%) | R9: R$/Cota¹ | S9: 1M (%) | T9: No ano (%) | U9: LTM (%)
B10: BTCI11 | C10: =IF(D10=0,"",IFERROR(D10/$D$35,"")) -> 0.06 | D10: 60000 | E10: =IFERROR(ROUNDDOWN(D10/L10,0),"") -> 6666 | F10: 85000 | G10: =IFERROR(D10+F10,"") -> 145000 | H10: =IF(G10=0,"",IFERROR(G10/$G$36,"")) -> 0.095709571 | I10: =IFERROR(ROUNDDOWN(G10/L10,0),"") -> 16111 | J10: =IFERROR(VLOOKUP($B10,'Stock Guide'!$B:$W,3,0),"") -> BTG Pactual Crédito Imobiliário FII | K10: =IFERROR(VLOOKUP($B10,'Stock Guide'!$B:$W,6,0),"") -> Recebível | L10: =IFERROR(VLOOKUP($B10,'Stock Guide'!$B:$W,9,0),"") -> 9 | M10: =IFERROR(VLOOKUP($B10,'Stock Guide'!$B:$W,8,0)/1000,"") -> 3504.8616 | N10: =IFERROR(VLOOKUP($B10,'Stock Guide'!$B:$W,14,0),"") -> 0.89215724 | O10: =IFERROR(R10/L10,"") -> 0.011444444 | P10: =IFERROR(VLOOKUP($B10,'Stock Guide'!$B:$W,16,0),"") -> 0.13055556 | Q10: =IFERROR((R10/L10)*12,"") -> 0.13733333 | R10: =IFERROR(VLOOKUP($B10,'Stock Guide'!$B:$W,19,0),"") -> 0.103 | S10: =IFERROR(VLOOKUP($B10,'Stock Guide'!$B:$W,20,0),"") -> -0.0040443824 | T10: =IFERROR(VLOOKUP($B10,'Stock Guide'!$B:$W,21,0),"") -> 0.048974723 | U10: =IFERROR(VLOOKUP($B10,'Stock Guide'!$B:$W,22,0),"") -> 0.12285468
B11: KNCR11 | C11: =IF(D11=0,"",IFERROR(D11/$D$35,"")) -> 0.13 | D11: 130000 | E11: =IFERROR(ROUNDDOWN(D11/L11,0),"") -> 1219 | G11: =IFERROR(D11+F11,"") -> 130000 | H11: =IF(G11=0,"",IFERROR(G11/$G$36,"")) -> 0.085808581 | I11: =IFERROR(ROUNDDOWN(G11/L11,0),"") -> 1219 | J11: =IFERROR(VLOOKUP($B11,'Stock Guide'!$B:$W,3,0),"") -> Kinea Rendimentos Imobiliários FII | K11: =IFERROR(VLOOKUP($B11,'Stock Guide'!$B:$W,6,0),"") -> Recebível | L11: =IFERROR(VLOOKUP($B11,'Stock Guide'!$B:$W,9,0),"") -> 106.6 | M11: =IFERROR(VLOOKUP($B11,'Stock Guide'!$B:$W,8,0)/1000,"") -> 21474.426 | N11: =IFERROR(VLOOKUP($B11,'Stock Guide'!$B:$W,14,0),"") -> 1.0398102 | O11: =IFERROR(R11/L11,"") -> 0.011726079 | P11: =IFERROR(VLOOKUP($B11,'Stock Guide'!$B:$W,16,0),"") -> 0.13452158 | Q11: =IFERROR((R11/L11)*12,"") -> 0.14071295 | R11: =IFERROR(VLOOKUP($B11,'Stock Guide'!$B:$W,19,0),"") -> 1.25 | S11: =IFERROR(VLOOKUP($B11,'Stock Guide'!$B:$W,20,0),"") -> -0.0020595394 | T11: =IFERROR(VLOOKUP($B11,'Stock Guide'!$B:$W,21,0),"") -> 0.080907164 | U11: =IFERROR(VLOOKUP($B11,'Stock Guide'!$B:$W,22,0),"") -> 0.18083758
B12: KNIP11 | C12: =IF(D12=0,"",IFERROR(D12/$D$35,"")) -> 0.13 | D12: 130000 | E12: =IFERROR(ROUNDDOWN(D12/L12,0),"") -> 1455 | F12: 50000 | G12: =IFERROR(D12+F12,"") -> 180000 | H12: =IF(G12=0,"",IFERROR(G12/$G$36,"")) -> 0.11881188 | I12: =IFERROR(ROUNDDOWN(G12/L12,0),"") -> 2015 | J12: =IFERROR(VLOOKUP($B12,'Stock Guide'!$B:$W,3,0),"") -> Kinea Indices de Preços FII | K12: =IFERROR(VLOOKUP($B12,'Stock Guide'!$B:$W,6,0),"") -> Recebível | L12: =IFERROR(VLOOKUP($B12,'Stock Guide'!$B:$W,9,0),"") -> 89.3 | M12: =IFERROR(VLOOKUP($B12,'Stock Guide'!$B:$W,8,0)/1000,"") -> 10206.473 | N12: =IFERROR(VLOOKUP($B12,'Stock Guide'!$B:$W,14,0),"") -> 0.96172851 | O12: =IFERROR(R12/L12,"") -> 0.010638298 | P12: =IFERROR(VLOOKUP($B12,'Stock Guide'!$B:$W,16,0),"") -> 0.1137738 | Q12: =IFERROR((R12/L12)*12,"") -> 0.12765957 | R12: =IFERROR(VLOOKUP($B12,'Stock Guide'!$B:$W,19,0),"") -> 0.95 | S12: =IFERROR(VLOOKUP($B12,'Stock Guide'!$B:$W,20,0),"") -> -0.01478376 | T12: =IFERROR(VLOOKUP($B12,'Stock Guide'!$B:$W,21,0),"") -> 0.070350425 | U12: =IFERROR(VLOOKUP($B12,'Stock Guide'!$B:$W,22,0),"") -> 0.15124008
B13: RBRR11 | C13: =IF(D13=0,"",IFERROR(D13/$D$35,"")) -> 0.03 | D13: 30000 | E13: =IFERROR(ROUNDDOWN(D13/L13,0),"") -> 400 | G13: =IFERROR(D13+F13,"") -> 30000 | H13: =IF(G13=0,"",IFERROR(G13/$G$36,"")) -> 0.01980198 | I13: =IFERROR(ROUNDDOWN(G13/L13,0),"") -> 400 | J13: =IFERROR(VLOOKUP($B13,'Stock Guide'!$B:$W,3,0),"") -> FII RBR Rendimento High | K13: =IFERROR(VLOOKUP($B13,'Stock Guide'!$B:$W,6,0),"") -> Recebível | L13: =IFERROR(VLOOKUP($B13,'Stock Guide'!$B:$W,9,0),"") -> 75 | M13: =IFERROR(VLOOKUP($B13,'Stock Guide'!$B:$W,8,0)/1000,"") -> 4149.1633 | N13: =IFERROR(VLOOKUP($B13,'Stock Guide'!$B:$W,14,0),"") -> 0.81605128 | O13: =IFERROR(R13/L13,"") -> 0.012 | P13: =IFERROR(VLOOKUP($B13,'Stock Guide'!$B:$W,16,0),"") -> 0.13173333 | Q13: =IFERROR((R13/L13)*12,"") -> 0.144 | R13: =IFERROR(VLOOKUP($B13,'Stock Guide'!$B:$W,19,0),"") -> 0.9 | S13: =IFERROR(VLOOKUP($B13,'Stock Guide'!$B:$W,20,0),"") -> -0.00045359409 | T13: =IFERROR(VLOOKUP($B13,'Stock Guide'!$B:$W,21,0),"") -> -0.070281297 | U13: =IFERROR(VLOOKUP($B13,'Stock Guide'!$B:$W,22,0),"") -> -0.023658733
B14: RBRY11 | C14: =IF(D14=0,"",IFERROR(D14/$D$35,"")) -> 0.09 | D14: 90000 | E14: =IFERROR(ROUNDDOWN(D14/L14,0),"") -> 1170 | G14: =IFERROR(D14+F14,"") -> 90000 | H14: =IF(G14=0,"",IFERROR(G14/$G$36,"")) -> 0.059405941 | I14: =IFERROR(ROUNDDOWN(G14/L14,0),"") -> 1170 | J14: =IFERROR(VLOOKUP($B14,'Stock Guide'!$B:$W,3,0),"") -> RBR Crédito Imobiliário Estruturado FII | K14: =IFERROR(VLOOKUP($B14,'Stock Guide'!$B:$W,6,0),"") -> Recebível | L14: =IFERROR(VLOOKUP($B14,'Stock Guide'!$B:$W,9,0),"") -> 76.87 | M14: =IFERROR(VLOOKUP($B14,'Stock Guide'!$B:$W,8,0)/1000,"") -> 4305.7881 | N14: =IFERROR(VLOOKUP($B14,'Stock Guide'!$B:$W,14,0),"") -> 0.76119222 | O14: =IFERROR(R14/L14,"") -> 0.013008976 | P14: =IFERROR(VLOOKUP($B14,'Stock Guide'!$B:$W,16,0),"") -> 0.17627163 | Q14: =IFERROR((R14/L14)*12,"") -> 0.15610771 | R14: =IFERROR(VLOOKUP($B14,'Stock Guide'!$B:$W,19,0),"") -> 1 | S14: =IFERROR(VLOOKUP($B14,'Stock Guide'!$B:$W,20,0),"") -> -0.081375577 | T14: =IFERROR(VLOOKUP($B14,'Stock Guide'!$B:$W,21,0),"") -> -0.13772419 | U14: =IFERROR(VLOOKUP($B14,'Stock Guide'!$B:$W,22,0),"") -> -0.038285445
B15: MCCI11 | C15: =IF(D15=0,"",IFERROR(D15/$D$35,"")) -> 0.08 | D15: 80000 | E15: =IFERROR(ROUNDDOWN(D15/L15,0),"") -> 856 | G15: =IFERROR(D15+F15,"") -> 80000 | H15: =IF(G15=0,"",IFERROR(G15/$G$36,"")) -> 0.052805281 | I15: =IFERROR(ROUNDDOWN(G15/L15,0),"") -> 856 | J15: =IFERROR(VLOOKUP($B15,'Stock Guide'!$B:$W,3,0),"") -> Mauá Capital Recebíveis Imobiliários FII | K15: =IFERROR(VLOOKUP($B15,'Stock Guide'!$B:$W,6,0),"") -> Recebível | L15: =IFERROR(VLOOKUP($B15,'Stock Guide'!$B:$W,9,0),"") -> 93.38 | M15: =IFERROR(VLOOKUP($B15,'Stock Guide'!$B:$W,8,0)/1000,"") -> 4539.8289 | N15: =IFERROR(VLOOKUP($B15,'Stock Guide'!$B:$W,14,0),"") -> 0.99342629 | O15: =IFERROR(R15/L15,"") -> 0.010708931 | P15: =IFERROR(VLOOKUP($B15,'Stock Guide'!$B:$W,16,0),"") -> 0.12850717 | Q15: =IFERROR((R15/L15)*12,"") -> 0.12850717 | R15: =IFERROR(VLOOKUP($B15,'Stock Guide'!$B:$W,19,0),"") -> 1 | S15: =IFERROR(VLOOKUP($B15,'Stock Guide'!$B:$W,20,0),"") -> -0.0042546667 | T15: =IFERROR(VLOOKUP($B15,'Stock Guide'!$B:$W,21,0),"") -> 0.11080271 | U15: =IFERROR(VLOOKUP($B15,'Stock Guide'!$B:$W,22,0),"") -> 0.26147021
B16: VILG11 | C16: =IF(D16=0,"",IFERROR(D16/$D$35,"")) -> 0.045 | D16: 45000 | E16: =IFERROR(ROUNDDOWN(D16/L16,0),"") -> 490 | G16: =IFERROR(D16+F16,"") -> 45000 | H16: =IF(G16=0,"",IFERROR(G16/$G$36,"")) -> 0.02970297 | I16: =IFERROR(ROUNDDOWN(G16/L16,0),"") -> 490 | J16: =IFERROR(VLOOKUP($B16,'Stock Guide'!$B:$W,3,0),"") -> Vinci Logística FII | K16: =IFERROR(VLOOKUP($B16,'Stock Guide'!$B:$W,6,0),"") -> Galpão Logístico | L16: =IFERROR(VLOOKUP($B16,'Stock Guide'!$B:$W,9,0),"") -> 91.65 | M16: =IFERROR(VLOOKUP($B16,'Stock Guide'!$B:$W,8,0)/1000,"") -> 2575.8593 | N16: =IFERROR(VLOOKUP($B16,'Stock Guide'!$B:$W,14,0),"") -> 0.83834886 | O16: =IFERROR(R16/L16,"") -> 0.0089470813 | P16: =IFERROR(VLOOKUP($B16,'Stock Guide'!$B:$W,16,0),"") -> 0.10190944 | Q16: =IFERROR((R16/L16)*12,"") -> 0.10736498 | R16: =IFERROR(VLOOKUP($B16,'Stock Guide'!$B:$W,19,0),"") -> 0.82 | S16: =IFERROR(VLOOKUP($B16,'Stock Guide'!$B:$W,20,0),"") -> 0.0058165057 | T16: =IFERROR(VLOOKUP($B16,'Stock Guide'!$B:$W,21,0),"") -> -0.016190668 | U16: =IFERROR(VLOOKUP($B16,'Stock Guide'!$B:$W,22,0),"") -> 0.25374251
B17: BRCO11 | C17: =IF(D17=0,"",IFERROR(D17/$D$35,"")) -> 0.045 | D17: 45000 | E17: =IFERROR(ROUNDDOWN(D17/L17,0),"") -> 402 | F17: 30000 | G17: =IFERROR(D17+F17,"") -> 75000 | H17: =IF(G17=0,"",IFERROR(G17/$G$36,"")) -> 0.04950495 | I17: =IFERROR(ROUNDDOWN(G17/L17,0),"") -> 670 | J17: =IFERROR(VLOOKUP($B17,'Stock Guide'!$B:$W,3,0),"") -> Bresco Logística FII | K17: =IFERROR(VLOOKUP($B17,'Stock Guide'!$B:$W,6,0),"") -> Galpão Logístico | L17: =IFERROR(VLOOKUP($B17,'Stock Guide'!$B:$W,9,0),"") -> 111.84 | M17: =IFERROR(VLOOKUP($B17,'Stock Guide'!$B:$W,8,0)/1000,"") -> 5135.9864 | N17: =IFERROR(VLOOKUP($B17,'Stock Guide'!$B:$W,14,0),"") -> 0.97361058 | O17: =IFERROR(R17/L17,"") -> 0.0081366237 | P17: =IFERROR(VLOOKUP($B17,'Stock Guide'!$B:$W,16,0),"") -> 0.097639485 | Q17: =IFERROR((R17/L17)*12,"") -> 0.097639485 | R17: =IFERROR(VLOOKUP($B17,'Stock Guide'!$B:$W,19,0),"") -> 0.91 | S17: =IFERROR(VLOOKUP($B17,'Stock Guide'!$B:$W,20,0),"") -> -0.019291477 | T17: =IFERROR(VLOOKUP($B17,'Stock Guide'!$B:$W,21,0),"") -> 0.010814626 | U17: =IFERROR(VLOOKUP($B17,'Stock Guide'!$B:$W,22,0),"") -> 0.12894551
B18: BTLG11 | C18: =IF(D18=0,"",IFERROR(D18/$D$35,"")) -> 0.13 | D18: 130000 | E18: =IFERROR(ROUNDDOWN(D18/L18,0),"") -> 1321 | G18: =IFERROR(D18+F18,"") -> 130000 | H18: =IF(G18=0,"",IFERROR(G18/$G$36,"")) -> 0.085808581 | I18: =IFERROR(ROUNDDOWN(G18/L18,0),"") -> 1321 | J18: =IFERROR(VLOOKUP($B18,'Stock Guide'!$B:$W,3,0),"") -> BTG Pactual Logística FII | K18: =IFERROR(VLOOKUP($B18,'Stock Guide'!$B:$W,6,0),"") -> Galpão Logístico | L18: =IFERROR(VLOOKUP($B18,'Stock Guide'!$B:$W,9,0),"") -> 98.37 | M18: =IFERROR(VLOOKUP($B18,'Stock Guide'!$B:$W,8,0)/1000,"") -> 12468.438 | N18: =IFERROR(VLOOKUP($B18,'Stock Guide'!$B:$W,14,0),"") -> 0.92052045 | O18: =IFERROR(R18/L18,"") -> 0.0082342177 | P18: =IFERROR(VLOOKUP($B18,'Stock Guide'!$B:$W,16,0),"") -> 0.097590729 | Q18: =IFERROR((R18/L18)*12,"") -> 0.098810613 | R18: =IFERROR(VLOOKUP($B18,'Stock Guide'!$B:$W,19,0),"") -> 0.81 | S18: =IFERROR(VLOOKUP($B18,'Stock Guide'!$B:$W,20,0),"") -> -0.016233044 | T18: =IFERROR(VLOOKUP($B18,'Stock Guide'!$B:$W,21,0),"") -> 0.022844674 | U18: =IFERROR(VLOOKUP($B18,'Stock Guide'!$B:$W,22,0),"") -> 0.093649125
B19: BRCR11 | C19: =IF(D19=0,"",IFERROR(D19/$D$35,"")) -> 0.045 | D19: 45000 | E19: =IFERROR(ROUNDDOWN(D19/L19,0),"") -> 1148 | F19: 100000 | G19: =IFERROR(D19+F19,"") -> 145000 | H19: =IF(G19=0,"",IFERROR(G19/$G$36,"")) -> 0.095709571 | I19: =IFERROR(ROUNDDOWN(G19/L19,0),"") -> 3699 | J19: =IFERROR(VLOOKUP($B19,'Stock Guide'!$B:$W,3,0),"") -> BTG Pactual Corporate Offices FII | K19: =IFERROR(VLOOKUP($B19,'Stock Guide'!$B:$W,6,0),"") -> Laje Corporativa | L19: =IFERROR(VLOOKUP($B19,'Stock Guide'!$B:$W,9,0),"") -> 39.19 | M19: =IFERROR(VLOOKUP($B19,'Stock Guide'!$B:$W,8,0)/1000,"") -> 1254.8978 | N19: =IFERROR(VLOOKUP($B19,'Stock Guide'!$B:$W,14,0),"") -> 0.48377811 | O19: =IFERROR(R19/L19,"") -> 0.010461853 | P19: =IFERROR(VLOOKUP($B19,'Stock Guide'!$B:$W,16,0),"") -> 0.12554223 | Q19: =IFERROR((R19/L19)*12,"") -> 0.12554223 | R19: =IFERROR(VLOOKUP($B19,'Stock Guide'!$B:$W,19,0),"") -> 0.41 | S19: =IFERROR(VLOOKUP($B19,'Stock Guide'!$B:$W,20,0),"") -> -0.018103263 | T19: =IFERROR(VLOOKUP($B19,'Stock Guide'!$B:$W,21,0),"") -> -0.082991445 | U19: =IFERROR(VLOOKUP($B19,'Stock Guide'!$B:$W,22,0),"") -> 0.084784476
B20: PVBI11 | C20: =IF(D20=0,"",IFERROR(D20/$D$35,"")) -> 0.05 | D20: 50000 | E20: =IFERROR(ROUNDDOWN(D20/L20,0),"") -> 750 | G20: =IFERROR(D20+F20,"") -> 50000 | H20: =IF(G20=0,"",IFERROR(G20/$G$36,"")) -> 0.0330033 | I20: =IFERROR(ROUNDDOWN(G20/L20,0),"") -> 750 | J20: =IFERROR(VLOOKUP($B20,'Stock Guide'!$B:$W,3,0),"") -> VBI Prime Properties | K20: =IFERROR(VLOOKUP($B20,'Stock Guide'!$B:$W,6,0),"") -> Laje Corporativa | L20: =IFERROR(VLOOKUP($B20,'Stock Guide'!$B:$W,9,0),"") -> 66.66 | M20: =IFERROR(VLOOKUP($B20,'Stock Guide'!$B:$W,8,0)/1000,"") -> 3815.4922 | N20: =IFERROR(VLOOKUP($B20,'Stock Guide'!$B:$W,14,0),"") -> 0.63782682 | O20: =IFERROR(R20/L20,"") -> 0.0060006001 | P20: =IFERROR(VLOOKUP($B20,'Stock Guide'!$B:$W,16,0),"") -> 0.077257726 | Q20: =IFERROR((R20/L20)*12,"") -> 0.072007201 | R20: =IFERROR(VLOOKUP($B20,'Stock Guide'!$B:$W,19,0),"") -> 0.4 | S20: =IFERROR(VLOOKUP($B20,'Stock Guide'!$B:$W,20,0),"") -> -0.038372764 | T20: =IFERROR(VLOOKUP($B20,'Stock Guide'!$B:$W,21,0),"") -> -0.15062473 | U20: =IFERROR(VLOOKUP($B20,'Stock Guide'!$B:$W,22,0),"") -> -0.042919195
B21: HGBS11 | C21: =IF(D21=0,"",IFERROR(D21/$D$35,"")) -> 0.03 | D21: 30000 | E21: =IFERROR(ROUNDDOWN(D21/L21,0),"") -> 1612 | F21: 150000 | G21: =IFERROR(D21+F21,"") -> 180000 | H21: =IF(G21=0,"",IFERROR(G21/$G$36,"")) -> 0.11881188 | I21: =IFERROR(ROUNDDOWN(G21/L21,0),"") -> 9677 | J21: =IFERROR(VLOOKUP($B21,'Stock Guide'!$B:$W,3,0),"") -> Hedge Brasil Shopping FII | K21: =IFERROR(VLOOKUP($B21,'Stock Guide'!$B:$W,6,0),"") -> Shopping Center | L21: =IFERROR(VLOOKUP($B21,'Stock Guide'!$B:$W,9,0),"") -> 18.6 | M21: =IFERROR(VLOOKUP($B21,'Stock Guide'!$B:$W,8,0)/1000,"") -> 4435.5009 | N21: =IFERROR(VLOOKUP($B21,'Stock Guide'!$B:$W,14,0),"") -> 0.91869993 | O21: =IFERROR(R21/L21,"") -> 0.0091397849 | P21: =IFERROR(VLOOKUP($B21,'Stock Guide'!$B:$W,16,0),"") -> 0.10376344 | Q21: =IFERROR((R21/L21)*12,"") -> 0.10967742 | R21: =IFERROR(VLOOKUP($B21,'Stock Guide'!$B:$W,19,0),"") -> 0.17 | S21: =IFERROR(VLOOKUP($B21,'Stock Guide'!$B:$W,20,0),"") -> -0.019504481 | T21: =IFERROR(VLOOKUP($B21,'Stock Guide'!$B:$W,21,0),"") -> -0.0059386745 | U21: =IFERROR(VLOOKUP($B21,'Stock Guide'!$B:$W,22,0),"") -> 0.088335597
B22: GZIT11 | C22: =IF(D22=0,"",IFERROR(D22/$D$35,"")) -> 0.025 | D22: 25000 | E22: =IFERROR(ROUNDDOWN(D22/L22,0),"") -> 675 | G22: =IFERROR(D22+F22,"") -> 25000 | H22: =IF(G22=0,"",IFERROR(G22/$G$36,"")) -> 0.01650165 | I22: =IFERROR(ROUNDDOWN(G22/L22,0),"") -> 675 | J22: =IFERROR(VLOOKUP($B22,'Stock Guide'!$B:$W,3,0),"") -> Gazit Malls FII | K22: =IFERROR(VLOOKUP($B22,'Stock Guide'!$B:$W,6,0),"") -> Shopping Center | L22: =IFERROR(VLOOKUP($B22,'Stock Guide'!$B:$W,9,0),"") -> 37.03 | M22: =IFERROR(VLOOKUP($B22,'Stock Guide'!$B:$W,8,0)/1000,"") -> 408.06677 | N22: =IFERROR(VLOOKUP($B22,'Stock Guide'!$B:$W,14,0),"") -> 0.42614957 | O22: =IFERROR(R22/L22,"") -> 0.011342155 | P22: =IFERROR(VLOOKUP($B22,'Stock Guide'!$B:$W,16,0),"") -> 0.19443694 | Q22: =IFERROR((R22/L22)*12,"") -> 0.13610586 | R22: =IFERROR(VLOOKUP($B22,'Stock Guide'!$B:$W,19,0),"") -> 0.42 | S22: =IFERROR(VLOOKUP($B22,'Stock Guide'!$B:$W,20,0),"") -> -0.086581154 | T22: =IFERROR(VLOOKUP($B22,'Stock Guide'!$B:$W,21,0),"") -> -0.14218843 | U22: =IFERROR(VLOOKUP($B22,'Stock Guide'!$B:$W,22,0),"") -> -0.0020717713
B23: HSML11 | C23: =IF(D23=0,"",IFERROR(D23/$D$35,"")) -> 0.02 | D23: 20000 | E23: =IFERROR(ROUNDDOWN(D23/L23,0),"") -> 239 | G23: =IFERROR(D23+F23,"") -> 20000 | H23: =IF(G23=0,"",IFERROR(G23/$G$36,"")) -> 0.01320132 | I23: =IFERROR(ROUNDDOWN(G23/L23,0),"") -> 239 | J23: =IFERROR(VLOOKUP($B23,'Stock Guide'!$B:$W,3,0),"") -> HSI Malls FII | K23: =IFERROR(VLOOKUP($B23,'Stock Guide'!$B:$W,6,0),"") -> Shopping Center | L23: =IFERROR(VLOOKUP($B23,'Stock Guide'!$B:$W,9,0),"") -> 83.52 | M23: =IFERROR(VLOOKUP($B23,'Stock Guide'!$B:$W,8,0)/1000,"") -> 4261.611 | N23: =IFERROR(VLOOKUP($B23,'Stock Guide'!$B:$W,14,0),"") -> 0.83794419 | O23: =IFERROR(R23/L23,"") -> 0.0089798851 | P23: =IFERROR(VLOOKUP($B23,'Stock Guide'!$B:$W,16,0),"") -> 0.10189176 | Q23: =IFERROR((R23/L23)*12,"") -> 0.10775862 | R23: =IFERROR(VLOOKUP($B23,'Stock Guide'!$B:$W,19,0),"") -> 0.75 | S23: =IFERROR(VLOOKUP($B23,'Stock Guide'!$B:$W,20,0),"") -> -0.034785623 | T23: =IFERROR(VLOOKUP($B23,'Stock Guide'!$B:$W,21,0),"") -> -0.038807954 | U23: =IFERROR(VLOOKUP($B23,'Stock Guide'!$B:$W,22,0),"") -> 0.14833052
B24: VISC11 | C24: =IF(D24=0,"",IFERROR(D24/$D$35,"")) -> 0.02 | D24: 20000 | E24: =IFERROR(ROUNDDOWN(D24/L24,0),"") -> 196 | G24: =IFERROR(D24+F24,"") -> 20000 | H24: =IF(G24=0,"",IFERROR(G24/$G$36,"")) -> 0.01320132 | I24: =IFERROR(ROUNDDOWN(G24/L24,0),"") -> 196 | J24: =IFERROR(VLOOKUP($B24,'Stock Guide'!$B:$W,3,0),"") -> Vinci Shopping Centers FII | K24: =IFERROR(VLOOKUP($B24,'Stock Guide'!$B:$W,6,0),"") -> Shopping Center | L24: =IFERROR(VLOOKUP($B24,'Stock Guide'!$B:$W,9,0),"") -> 101.7 | M24: =IFERROR(VLOOKUP($B24,'Stock Guide'!$B:$W,8,0)/1000,"") -> 6047.314 | N24: =IFERROR(VLOOKUP($B24,'Stock Guide'!$B:$W,14,0),"") -> 0.88098644 | O24: =IFERROR(R24/L24,"") -> 0.008259587 | P24: =IFERROR(VLOOKUP($B24,'Stock Guide'!$B:$W,16,0),"") -> 0.097640118 | Q24: =IFERROR((R24/L24)*12,"") -> 0.099115044 | R24: =IFERROR(VLOOKUP($B24,'Stock Guide'!$B:$W,19,0),"") -> 0.84 | S24: =IFERROR(VLOOKUP($B24,'Stock Guide'!$B:$W,20,0),"") -> -0.022585296 | T24: =IFERROR(VLOOKUP($B24,'Stock Guide'!$B:$W,21,0),"") -> -0.0077786218 | U24: =IFERROR(VLOOKUP($B24,'Stock Guide'!$B:$W,22,0),"") -> 0.083744613
B25: TRXF11 | C25: =IF(D25=0,"",IFERROR(D25/$D$35,"")) -> 0.07 | D25: 70000 | E25: =IFERROR(ROUNDDOWN(D25/L25,0),"") -> 974 | F25: 100000 | G25: =IFERROR(D25+F25,"") -> 170000 | H25: =IF(G25=0,"",IFERROR(G25/$G$36,"")) -> 0.11221122 | I25: =IFERROR(ROUNDDOWN(G25/L25,0),"") -> 2367 | J25: =IFERROR(VLOOKUP($B25,'Stock Guide'!$B:$W,3,0),"") -> TRX Real Estate FII | K25: =IFERROR(VLOOKUP($B25,'Stock Guide'!$B:$W,6,0),"") -> Renda Urbana | L25: =IFERROR(VLOOKUP($B25,'Stock Guide'!$B:$W,9,0),"") -> 71.8 | M25: =IFERROR(VLOOKUP($B25,'Stock Guide'!$B:$W,8,0)/1000,"") -> 23831.971 | N25: =IFERROR(VLOOKUP($B25,'Stock Guide'!$B:$W,14,0),"") -> 0.73970401 | O25: =IFERROR(R25/L25,"") -> 0.012952646 | P25: =IFERROR(VLOOKUP($B25,'Stock Guide'!$B:$W,16,0),"") -> 0.1643454 | Q25: =IFERROR((R25/L25)*12,"") -> 0.15543175 | R25: =IFERROR(VLOOKUP($B25,'Stock Guide'!$B:$W,19,0),"") -> 0.93 | S25: =IFERROR(VLOOKUP($B25,'Stock Guide'!$B:$W,20,0),"") -> -0.20372629 | T25: =IFERROR(VLOOKUP($B25,'Stock Guide'!$B:$W,21,0),"") -> -0.20018374 | U25: =IFERROR(VLOOKUP($B25,'Stock Guide'!$B:$W,22,0),"") -> -0.16191836
C26: =IF(D26=0,"",IFERROR(D26/$D$35,"")) | E26: =IFERROR(ROUNDDOWN(D26/L26,0),"") | G26: =IFERROR(D26+F26,"") -> 0 | H26: =IF(G26=0,"",IFERROR(G26/$G$36,"")) | I26: =IFERROR(ROUNDDOWN(G26/L26,0),"") | J26: =IFERROR(VLOOKUP($B26,'Stock Guide'!$B:$W,3,0),"") | K26: =IFERROR(VLOOKUP($B26,'Stock Guide'!$B:$W,6,0),"") | L26: =IFERROR(VLOOKUP($B26,'Stock Guide'!$B:$W,9,0),"") | M26: =IFERROR(VLOOKUP($B26,'Stock Guide'!$B:$W,8,0)/1000,"") | N26: =IFERROR(VLOOKUP($B26,'Stock Guide'!$B:$W,14,0),"") | O26: =IFERROR(R26/L26,"") | P26: =IFERROR(VLOOKUP($B26,'Stock Guide'!$B:$W,16,0),"") | Q26: =IFERROR((R26/L26)*12,"") | R26: =IFERROR(VLOOKUP($B26,'Stock Guide'!$B:$W,19,0),"") | S26: =IFERROR(VLOOKUP($B26,'Stock Guide'!$B:$W,20,0),"") | T26: =IFERROR(VLOOKUP($B26,'Stock Guide'!$B:$W,21,0),"") | U26: =IFERROR(VLOOKUP($B26,'Stock Guide'!$B:$W,22,0),"")
C27: =IF(D27=0,"",IFERROR(D27/$D$35,"")) | E27: =IFERROR(ROUNDDOWN(D27/L27,0),"") | G27: =IFERROR(D27+F27,"") -> 0 | H27: =IF(G27=0,"",IFERROR(G27/$G$36,"")) | I27: =IFERROR(ROUNDDOWN(G27/L27,0),"") | J27: =IFERROR(VLOOKUP($B27,'Stock Guide'!$B:$W,3,0),"") | K27: =IFERROR(VLOOKUP($B27,'Stock Guide'!$B:$W,6,0),"") | L27: =IFERROR(VLOOKUP($B27,'Stock Guide'!$B:$W,9,0),"") | M27: =IFERROR(VLOOKUP($B27,'Stock Guide'!$B:$W,8,0)/1000,"") | N27: =IFERROR(VLOOKUP($B27,'Stock Guide'!$B:$W,14,0),"") | O27: =IFERROR(R27/L27,"") | P27: =IFERROR(VLOOKUP($B27,'Stock Guide'!$B:$W,16,0),"") | Q27: =IFERROR((R27/L27)*12,"") | R27: =IFERROR(VLOOKUP($B27,'Stock Guide'!$B:$W,19,0),"") | S27: =IFERROR(VLOOKUP($B27,'Stock Guide'!$B:$W,20,0),"") | T27: =IFERROR(VLOOKUP($B27,'Stock Guide'!$B:$W,21,0),"") | U27: =IFERROR(VLOOKUP($B27,'Stock Guide'!$B:$W,22,0),"")
C28: =IF(D28=0,"",IFERROR(D28/$D$35,"")) | E28: =IFERROR(ROUNDDOWN(D28/L28,0),"") | G28: =IFERROR(D28+F28,"") -> 0 | H28: =IF(G28=0,"",IFERROR(G28/$G$36,"")) | I28: =IFERROR(ROUNDDOWN(G28/L28,0),"") | J28: =IFERROR(VLOOKUP($B28,'Stock Guide'!$B:$W,3,0),"") | K28: =IFERROR(VLOOKUP($B28,'Stock Guide'!$B:$W,6,0),"") | L28: =IFERROR(VLOOKUP($B28,'Stock Guide'!$B:$W,9,0),"") | M28: =IFERROR(VLOOKUP($B28,'Stock Guide'!$B:$W,8,0)/1000,"") | N28: =IFERROR(VLOOKUP($B28,'Stock Guide'!$B:$W,14,0),"") | O28: =IFERROR(R28/L28,"") | P28: =IFERROR(VLOOKUP($B28,'Stock Guide'!$B:$W,16,0),"") | Q28: =IFERROR((R28/L28)*12,"") | R28: =IFERROR(VLOOKUP($B28,'Stock Guide'!$B:$W,19,0),"") | S28: =IFERROR(VLOOKUP($B28,'Stock Guide'!$B:$W,20,0),"") | T28: =IFERROR(VLOOKUP($B28,'Stock Guide'!$B:$W,21,0),"") | U28: =IFERROR(VLOOKUP($B28,'Stock Guide'!$B:$W,22,0),"")
C29: =IF(D29=0,"",IFERROR(D29/$D$35,"")) | E29: =IFERROR(ROUNDDOWN(D29/L29,0),"") | G29: =IFERROR(D29+F29,"") -> 0 | H29: =IF(G29=0,"",IFERROR(G29/$G$36,"")) | I29: =IFERROR(ROUNDDOWN(G29/L29,0),"") | J29: =IFERROR(VLOOKUP($B29,'Stock Guide'!$B:$W,3,0),"") | K29: =IFERROR(VLOOKUP($B29,'Stock Guide'!$B:$W,6,0),"") | L29: =IFERROR(VLOOKUP($B29,'Stock Guide'!$B:$W,9,0),"") | M29: =IFERROR(VLOOKUP($B29,'Stock Guide'!$B:$W,8,0)/1000,"") | N29: =IFERROR(VLOOKUP($B29,'Stock Guide'!$B:$W,14,0),"") | O29: =IFERROR(R29/L29,"") | P29: =IFERROR(VLOOKUP($B29,'Stock Guide'!$B:$W,16,0),"") | Q29: =IFERROR((R29/L29)*12,"") | R29: =IFERROR(VLOOKUP($B29,'Stock Guide'!$B:$W,19,0),"") | S29: =IFERROR(VLOOKUP($B29,'Stock Guide'!$B:$W,20,0),"") | T29: =IFERROR(VLOOKUP($B29,'Stock Guide'!$B:$W,21,0),"") | U29: =IFERROR(VLOOKUP($B29,'Stock Guide'!$B:$W,22,0),"")
C30: =IF(D30=0,"",IFERROR(D30/$D$35,"")) | E30: =IFERROR(ROUNDDOWN(D30/L30,0),"") | G30: =IFERROR(D30+F30,"") -> 0 | H30: =IF(G30=0,"",IFERROR(G30/$G$36,"")) | I30: =IFERROR(ROUNDDOWN(G30/L30,0),"") | J30: =IFERROR(VLOOKUP($B30,'Stock Guide'!$B:$W,3,0),"") | K30: =IFERROR(VLOOKUP($B30,'Stock Guide'!$B:$W,6,0),"") | L30: =IFERROR(VLOOKUP($B30,'Stock Guide'!$B:$W,9,0),"") | M30: =IFERROR(VLOOKUP($B30,'Stock Guide'!$B:$W,8,0)/1000,"") | N30: =IFERROR(VLOOKUP($B30,'Stock Guide'!$B:$W,14,0),"") | O30: =IFERROR(R30/L30,"") | P30: =IFERROR(VLOOKUP($B30,'Stock Guide'!$B:$W,16,0),"") | Q30: =IFERROR((R30/L30)*12,"") | R30: =IFERROR(VLOOKUP($B30,'Stock Guide'!$B:$W,19,0),"") | S30: =IFERROR(VLOOKUP($B30,'Stock Guide'!$B:$W,20,0),"") | T30: =IFERROR(VLOOKUP($B30,'Stock Guide'!$B:$W,21,0),"") | U30: =IFERROR(VLOOKUP($B30,'Stock Guide'!$B:$W,22,0),"")
C31: =IF(D31=0,"",IFERROR(D31/$D$35,"")) | E31: =IFERROR(ROUNDDOWN(D31/L31,0),"") | G31: =IFERROR(D31+F31,"") -> 0 | H31: =IF(G31=0,"",IFERROR(G31/$G$36,"")) | I31: =IFERROR(ROUNDDOWN(G31/L31,0),"") | J31: =IFERROR(VLOOKUP($B31,'Stock Guide'!$B:$W,3,0),"") | K31: =IFERROR(VLOOKUP($B31,'Stock Guide'!$B:$W,6,0),"") | L31: =IFERROR(VLOOKUP($B31,'Stock Guide'!$B:$W,9,0),"") | M31: =IFERROR(VLOOKUP($B31,'Stock Guide'!$B:$W,8,0)/1000,"") | N31: =IFERROR(VLOOKUP($B31,'Stock Guide'!$B:$W,14,0),"") | O31: =IFERROR(R31/L31,"") | P31: =IFERROR(VLOOKUP($B31,'Stock Guide'!$B:$W,16,0),"") | Q31: =IFERROR((R31/L31)*12,"") | R31: =IFERROR(VLOOKUP($B31,'Stock Guide'!$B:$W,19,0),"") | S31: =IFERROR(VLOOKUP($B31,'Stock Guide'!$B:$W,20,0),"") | T31: =IFERROR(VLOOKUP($B31,'Stock Guide'!$B:$W,21,0),"") | U31: =IFERROR(VLOOKUP($B31,'Stock Guide'!$B:$W,22,0),"")
C32: =IF(D32=0,"",IFERROR(D32/$D$35,"")) | E32: =IFERROR(ROUNDDOWN(D32/L32,0),"") | G32: =IFERROR(D32+F32,"") -> 0 | H32: =IF(G32=0,"",IFERROR(G32/$G$36,"")) | I32: =IFERROR(ROUNDDOWN(G32/L32,0),"") | J32: =IFERROR(VLOOKUP($B32,'Stock Guide'!$B:$W,3,0),"") | K32: =IFERROR(VLOOKUP($B32,'Stock Guide'!$B:$W,6,0),"") | L32: =IFERROR(VLOOKUP($B32,'Stock Guide'!$B:$W,9,0),"") | M32: =IFERROR(VLOOKUP($B32,'Stock Guide'!$B:$W,8,0)/1000,"") | N32: =IFERROR(VLOOKUP($B32,'Stock Guide'!$B:$W,14,0),"") | O32: =IFERROR(R32/L32,"") | P32: =IFERROR(VLOOKUP($B32,'Stock Guide'!$B:$W,16,0),"") | Q32: =IFERROR((R32/L32)*12,"") | R32: =IFERROR(VLOOKUP($B32,'Stock Guide'!$B:$W,19,0),"") | S32: =IFERROR(VLOOKUP($B32,'Stock Guide'!$B:$W,20,0),"") | T32: =IFERROR(VLOOKUP($B32,'Stock Guide'!$B:$W,21,0),"") | U32: =IFERROR(VLOOKUP($B32,'Stock Guide'!$B:$W,22,0),"")
C33: =IF(D33=0,"",IFERROR(D33/$D$35,"")) | E33: =IFERROR(ROUNDDOWN(D33/L33,0),"") | G33: =IFERROR(D33+F33,"") -> 0 | H33: =IF(G33=0,"",IFERROR(G33/$G$36,"")) | I33: =IFERROR(ROUNDDOWN(G33/L33,0),"") | J33: =IFERROR(VLOOKUP($B33,'Stock Guide'!$B:$W,3,0),"") | K33: =IFERROR(VLOOKUP($B33,'Stock Guide'!$B:$W,6,0),"") | L33: =IFERROR(VLOOKUP($B33,'Stock Guide'!$B:$W,9,0),"") | M33: =IFERROR(VLOOKUP($B33,'Stock Guide'!$B:$W,8,0)/1000,"") | N33: =IFERROR(VLOOKUP($B33,'Stock Guide'!$B:$W,14,0),"") | O33: =IFERROR(R33/L33,"") | P33: =IFERROR(VLOOKUP($B33,'Stock Guide'!$B:$W,16,0),"") | Q33: =IFERROR((R33/L33)*12,"") | R33: =IFERROR(VLOOKUP($B33,'Stock Guide'!$B:$W,19,0),"") | S33: =IFERROR(VLOOKUP($B33,'Stock Guide'!$B:$W,20,0),"") | T33: =IFERROR(VLOOKUP($B33,'Stock Guide'!$B:$W,21,0),"") | U33: =IFERROR(VLOOKUP($B33,'Stock Guide'!$B:$W,22,0),"")
C34: =IF(D34=0,"",IFERROR(D34/$D$35,"")) | E34: =IFERROR(ROUNDDOWN(D34/L34,0),"") | G34: =IFERROR(D34+F34,"") -> 0 | H34: =IF(G34=0,"",IFERROR(G34/$G$36,"")) | I34: =IFERROR(ROUNDDOWN(G34/L34,0),"") | J34: =IFERROR(VLOOKUP($B34,'Stock Guide'!$B:$W,3,0),"") | K34: =IFERROR(VLOOKUP($B34,'Stock Guide'!$B:$W,6,0),"") | L34: =IFERROR(VLOOKUP($B34,'Stock Guide'!$B:$W,9,0),"") | M34: =IFERROR(VLOOKUP($B34,'Stock Guide'!$B:$W,8,0)/1000,"") | N34: =IFERROR(VLOOKUP($B34,'Stock Guide'!$B:$W,14,0),"") | O34: =IFERROR(R34/L34,"") | P34: =IFERROR(VLOOKUP($B34,'Stock Guide'!$B:$W,16,0),"") | Q34: =IFERROR((R34/L34)*12,"") | R34: =IFERROR(VLOOKUP($B34,'Stock Guide'!$B:$W,19,0),"") | S34: =IFERROR(VLOOKUP($B34,'Stock Guide'!$B:$W,20,0),"") | T34: =IFERROR(VLOOKUP($B34,'Stock Guide'!$B:$W,21,0),"") | U34: =IFERROR(VLOOKUP($B34,'Stock Guide'!$B:$W,22,0),"")
B35: Carteira Atual | C35: =SUM(C10:C34) -> 1 | D35: =SUM(D10:D34) -> 1000000 | E35: - | F35: - | G35: - | H35: - | I35: - | J35: - | K35: - | L35: - | M35: =SUMPRODUCT($M$10:$M$34,$C$10:$C$34) -> 9436.8489 | N35: =SUMPRODUCT(N$10:N$34,$C$10:$C$34) -> 0.86543223 | O35: =SUMPRODUCT(O$10:O$34,$C$10:$C$34) -> 0.010400808 | P35: =SUMPRODUCT(P$10:P$34,$C$10:$C$34) -> 0.12485618 | Q35: =SUMPRODUCT(Q$10:Q$34,$C$10:$C$34) -> 0.1248097 | R35: =SUMPRODUCT($R$10:$R$34,$E$10:$E$34) -> 10394.158 | S35: =SUMPRODUCT(S$10:S$34,$C$10:$C$34) -> -0.033717952 | T35: =SUMPRODUCT(T$10:T$34,$C$10:$C$34) -> -0.01025286 | U35: =SUMPRODUCT(U$10:U$34,$C$10:$C$34) -> 0.094273721
B36: Após Aporte | C36: =SUM(H10:H34) -> 1 | D36: =SUM(D10:D34) -> 1000000 | E36: - | F36: =SUM(F10:F34) -> 515000 | G36: =SUM(G10:G34) -> 1515000 | H36: - | I36: - | J36: - | K36: - | L36: - | M36: =SUMPRODUCT($M$10:$M$34,$H$10:$H$34) -> 8959.193 | N36: =SUMPRODUCT(N$10:N$34,$H$10:$H$34) -> 0.84403534 | O36: =SUMPRODUCT(O$10:O$34,$H$10:$H$34) -> 0.010469979 | P36: =SUMPRODUCT(P$10:P$34,$H$10:$H$34) -> 0.12483469 | Q36: =SUMPRODUCT(Q$10:Q$34,$H$10:$H$34) -> 0.12563974 | R36: =SUMPRODUCT($R$10:$R$34,$I$10:$I$34) -> 15855.323 | S36: =SUMPRODUCT(S$10:S$34,$H$10:$H$34) -> -0.03992626 | T36: =SUMPRODUCT(T$10:T$34,$H$10:$H$34) -> -0.020763279 | U36: =SUMPRODUCT(U$10:U$34,$H$10:$H$34) -> 0.080319267
B38: 1- Corresponde ao último dividendo anunciado. O total leva em consideração a quantidade de cotas detidas para cada fundo. 2- A simulação não leva em consideração o pagamento de IR em caso de ganho de capital.
B39: -Para adicionar mais linhas pressionar: (i) SHIFT + Espaço para selecionar a linha; (ii) CTRL + (Sinal de adição +); e (iii) arastar as formulas das colunas em branco.
B41: Carteira Atual | I41: Carteira Pós Aporte | N41: Mudanças
B64: Comparativo de Indicadores
B86: *Ressaltamos que só será possível simular carteiras cujos fundos possuam liquidez acima de R$ 50 mil/dia. **Não deixe de acessar nossos conteúdos no site https://content.btgpactual.com/research/home
B173: Segmento | C173: Atual | D173: Aporte | E173: Segmento1 | F173: Atual | G173: Aporte | H173: Delta | K173: Indicadores | L173: Atual | M173: Aporte
B174: Recebível | C174: =SUMIFS($C$10:$C$34,$K$10:$K$34,B174) -> 0.52 | D174: =SUMIFS($H$10:$H$34,$K$10:$K$34,B174) -> 0.43234323 | E174: Recebíveis | F174: =$E174&" ("&TEXT(C174,"0,0%")&")" -> Recebíveis (52,0%) | G174: =$E174&" ("&TEXT(D174,"0,0%")&")" -> Recebíveis (43,2%) | H174: =D174-C174 -> -0.087656766 | K174: Nº de Ativos | L174: =COUNT(C10:C34)-COUNTIF(C10:C34,0%) -> 16 | M174: =COUNT(G10:G34)-COUNTIF(G10:G34,0%) -> 16
B175: Laje Corporativa | C175: =SUMIFS($C$10:$C$34,$K$10:$K$34,B175) -> 0.095 | D175: =SUMIFS($H$10:$H$34,$K$10:$K$34,B175) -> 0.12871287 | E175: Lajes | F175: =$E175&" ("&TEXT(C175,"0,0%")&")" -> Lajes (9,5%) | G175: =$E175&" ("&TEXT(D175,"0,0%")&")" -> Lajes (12,9%) | H175: =D175-C175 -> 0.033712871 | K175: Liquidez | L175: =M35 -> 9436.8489 | M175: =M36 -> 8959.193
B176: Galpão Logístico | C176: =SUMIFS($C$10:$C$34,$K$10:$K$34,B176) -> 0.22 | D176: =SUMIFS($H$10:$H$34,$K$10:$K$34,B176) -> 0.1650165 | E176: Galpões | F176: =$E176&" ("&TEXT(C176,"0,0%")&")" -> Galpões (22,0%) | G176: =$E176&" ("&TEXT(D176,"0,0%")&")" -> Galpões (16,5%) | H176: =D176-C176 -> -0.054983498 | K176: P/VPA | L176: =N35 -> 0.86543223 | M176: =N36 -> 0.84403534
B177: Shopping Center | C177: =SUMIFS($C$10:$C$34,$K$10:$K$34,B177) -> 0.095 | D177: =SUMIFS($H$10:$H$34,$K$10:$K$34,B177) -> 0.16171617 | E177: Shoppings | F177: =$E177&" ("&TEXT(C177,"0,0%")&")" -> Shoppings (9,5%) | G177: =$E177&" ("&TEXT(D177,"0,0%")&")" -> Shoppings (16,2%) | H177: =D177-C177 -> 0.066716172 | K177: DY Anualizado | L177: =Q35 -> 0.1248097 | M177: =Q36 -> 0.12563974
B178: Híbrido | C178: =SUMIFS($C$10:$C$34,$K$10:$K$34,B178) -> 0 | D178: =SUMIFS($H$10:$H$34,$K$10:$K$34,B178) -> 0 | E178: Híbridos | F178: =$E178&" ("&TEXT(C178,"0,0%")&")" -> Híbridos (0,0%) | G178: =$E178&" ("&TEXT(D178,"0,0%")&")" -> Híbridos (0,0%) | H178: =D178-C178 -> 0 | K178: DY 12 meses | L178: =P35 -> 0.12485618 | M178: =P36 -> 0.12483469
B179: Renda Urbana | C179: =SUMIFS($C$10:$C$34,$K$10:$K$34,B179) -> 0.07 | D179: =SUMIFS($H$10:$H$34,$K$10:$K$34,B179) -> 0.11221122 | E179: Renda Urbana | F179: =$E179&" ("&TEXT(C179,"0,0%")&")" -> Renda Urbana (7,0%) | G179: =$E179&" ("&TEXT(D179,"0,0%")&")" -> Renda Urbana (11,2%) | H179: =D179-C179 -> 0.042211221 | K179: Rendimentos | L179: =R35 -> 10394.158 | M179: =R36 -> 15855.323
B180: Hedge Fund | C180: =SUMIFS($C$10:$C$34,$K$10:$K$34,B180) -> 0 | D180: =SUMIFS($H$10:$H$34,$K$10:$K$34,B180) -> 0 | E180: Hedge Fund | F180: =$E180&" ("&TEXT(C180,"0,0%")&")" -> Hedge Fund (0,0%) | G180: =$E180&" ("&TEXT(D180,"0,0%")&")" -> Hedge Fund (0,0%) | H180: =D180-C180 -> 0
B181: Fundo de Fundos | C181: =SUMIFS($C$10:$C$34,$K$10:$K$34,B181) -> 0 | D181: =SUMIFS($H$10:$H$34,$K$10:$K$34,B181) -> 0 | E181: FOFs | F181: =$E181&" ("&TEXT(C181,"0,0%")&")" -> FOFs (0,0%) | G181: =$E181&" ("&TEXT(D181,"0,0%")&")" -> FOFs (0,0%) | H181: =D181-C181 -> 0
B182: FIAgro - FII | C182: =SUMIFS($C$10:$C$34,$K$10:$K$34,B182) -> 0 | D182: =SUMIFS($H$10:$H$34,$K$10:$K$34,B182) -> 0 | E182: Fiagro FII | F182: =$E182&" ("&TEXT(C182,"0,0%")&")" -> Fiagro FII (0,0%) | G182: =$E182&" ("&TEXT(D182,"0,0%")&")" -> Fiagro FII (0,0%) | H182: =D182-C182 -> 0
B183: FI-Infra | C183: =SUMIFS($C$10:$C$34,$K$10:$K$34,B183) -> 0 | D183: =SUMIFS($H$10:$H$34,$K$10:$K$34,B183) -> 0 | E183: FI-Infras | F183: =$E183&" ("&TEXT(C183,"0,0%")&")" -> FI-Infras (0,0%) | G183: =$E183&" ("&TEXT(D183,"0,0%")&")" -> FI-Infras (0,0%) | H183: =D183-C183 -> 0
B184: FIAgro - FIDC | C184: =SUMIFS($C$10:$C$34,$K$10:$K$34,B184) -> 0 | D184: =SUMIFS($H$10:$H$34,$K$10:$K$34,B184) -> 0 | E184: Fiagro FIDC | F184: =$E184&" ("&TEXT(C184,"0,0%")&")" -> Fiagro FIDC (0,0%) | G184: =$E184&" ("&TEXT(D184,"0,0%")&")" -> Fiagro FIDC (0,0%) | H184: =D184-C184 -> 0
B185: Outros | C185: =SUM(C187:C203) -> 0 | D185: =SUM(D187:D203) -> 0 | E185: Outros | F185: =$E185&" ("&TEXT(C185,"0,0%")&")" -> Outros (0,0%) | G185: =$E185&" ("&TEXT(D185,"0,0%")&")" -> Outros (0,0%) | H185: =D185-C185 -> 0
B187: Residencial | C187: =SUMIFS($C$10:$C$34,$K$10:$K$34,B187) -> 0 | D187: =SUMIFS($H$10:$H$34,$K$10:$K$34,B187) -> 0
B188: Agência Bancária | C188: =SUMIFS($C$10:$C$34,$K$10:$K$34,B188) -> 0 | D188: =SUMIFS($H$10:$H$34,$K$10:$K$34,B188) -> 0
B189: Agronegócio | C189: =SUMIFS($C$10:$C$34,$K$10:$K$34,B189) -> 0 | D189: =SUMIFS($H$10:$H$34,$K$10:$K$34,B189) -> 0
B190: Educacional | C190: =SUMIFS($C$10:$C$34,$K$10:$K$34,B190) -> 0 | D190: =SUMIFS($H$10:$H$34,$K$10:$K$34,B190) -> 0
B191: Varejo | C191: =SUMIFS($C$10:$C$34,$K$10:$K$34,B191) -> 0 | D191: =SUMIFS($H$10:$H$34,$K$10:$K$34,B191) -> 0
B192: Hotel | C192: =SUMIFS($C$10:$C$34,$K$10:$K$34,B192) -> 0 | D192: =SUMIFS($H$10:$H$34,$K$10:$K$34,B192) -> 0
B193: Outros | C193: =SUMIFS($C$10:$C$34,$K$10:$K$34,B193) -> 0 | D193: =SUMIFS($H$10:$H$34,$K$10:$K$34,B193) -> 0
B194: Desenvolvimento | C194: =SUMIFS($C$10:$C$34,$K$10:$K$34,B194) -> 0 | D194: =SUMIFS($H$10:$H$34,$K$10:$K$34,B194) -> 0
B195: Hospital | C195: =SUMIFS($C$10:$C$34,$K$10:$K$34,B195) -> 0 | D195: =SUMIFS($H$10:$H$34,$K$10:$K$34,B195) -> 0

Sheet Recebível (CRI)
O2: Menu | P2: Stock Guide
B4: =B8 -> Recebível
B6: Fundo | D6: Fechamento | E6: Part. IFIX | F6: Volume de Negociação | G6: Valor de Mercado | H6: Valor Patrimonial | I6: P/VPA Atual | J6: P/VPA 2025 | K6: Dividend Yield LTM | L6: Dividend Yield Anualizado | M6: Último Dividendo | N6: Retorno no Mês | O6: Retorno no Ano | P6: Retorno LTM
B7: Segmento | D7: R$ | E7: Total (%) | F7: Média Diária (R$) | G7: Média (R$) | H7: Média (R$) | I7: Média | J7: Média | K7: Média (% ao ano) | L7: Média (% ao ano) | M7: R$ | N7: Média (%) | O7: Média (%) | P7: Média (%)
B8: Recebível | D8: - | E8: =SUMIFS('Stock Guide'!$H:$H,'Stock Guide'!$G:$G,B8) -> 0.36761 | F8: =AVERAGEIFS('Stock Guide'!I:I,'Stock Guide'!$G:$G,B8) -> 1876793.9 | G8: =AVERAGEIFS('Stock Guide'!$M:$M,'Stock Guide'!$G:$G,B8) -> 8.7493607e+08 | H8: =AVERAGEIFS('Stock Guide'!$N:$N,'Stock Guide'!$G:$G,B8) -> 1.0227551e+09 | I8: =AVERAGEIFS('Stock Guide'!$O:$O,'Stock Guide'!$G:$G,B8) -> 0.78179103 | J8: =AVERAGEIFS('Stock Guide'!$P:$P,'Stock Guide'!$G:$G,B8) -> 0.86063519 | K8: =AVERAGEIFS('Stock Guide'!$Q:$Q,'Stock Guide'!$G:$G,B8) -> 0.16614556 | L8: =AVERAGEIFS('Stock Guide'!$R:$R,'Stock Guide'!$G:$G,B8) -> 0.15990203 | M8: - | N8: =AVERAGEIFS('Stock Guide'!$U:$U,'Stock Guide'!$G:$G,$B8) -> -0.03196602 | O8: =AVERAGEIFS('Stock Guide'!$V:$V,'Stock Guide'!$G:$G,$B8) -> -0.027109577 | P8: =AVERAGEIFS('Stock Guide'!$W:$W,'Stock Guide'!$G:$G,$B8) -> 0.048648218
B9: Código | C9: Recebível | D9: R$ | E9: (%) | F9: Média Diária (R$) | G9: R$ | H9: R$ | I9: - | J9: - | K9: (% ao ano) | L9: (% ao ano) | M9: R$/cota | N9: (%) | O9: (%) | P9: (%)
B10: AFHI11 | C10: =IF(B10="","",(VLOOKUP(B10,'Stock Guide'!$B:$D,3,0))) -> AF Invest CRI Recebíveis FII | D10: =IF(B10="","",SUMIFS('Stock Guide'!$J:$J,'Stock Guide'!$B:$B,B10)) -> 93.15 | E10: =IF(B10="","",SUMIFS('Stock Guide'!$H:$H,'Stock Guide'!$B:$B,B10)) -> 0.00354 | F10: =IF(B10="","",SUMIFS('Stock Guide'!I:I,'Stock Guide'!$B:$B,B10)) -> 681268.43 | G10: =IF(B10="","",SUMIFS('Stock Guide'!$M:$M,'Stock Guide'!$B:$B,B10)) -> 4.9265274e+08 | H10: =IF(B10="","",SUMIFS('Stock Guide'!$N:$N,'Stock Guide'!$B:$B,B10)) -> 5.0353984e+08 | I10: =IF(B10="","",SUMIFS('Stock Guide'!$O:$O,'Stock Guide'!$B:$B,B10)) -> 0.97837887 | J10: =IF(B10="","",SUMIFS('Stock Guide'!$P:$P,'Stock Guide'!$B:$B,B10)) -> 1.0130099 | K10: =IF(B10="","",SUMIFS('Stock Guide'!$Q:$Q,'Stock Guide'!$B:$B,B10)) -> 0.1294686 | L10: =IF(B10="","",SUMIFS('Stock Guide'!$R:$R,'Stock Guide'!$B:$B,B10)) -> 0.12882448 | M10: =IF(B10="","",SUMIFS('Stock Guide'!$T:$T,'Stock Guide'!$B:$B,B10)) -> 1 | N10: =IFERROR(IF(B10="","",AVERAGEIFS('Stock Guide'!$U:$U,'Stock Guide'!$B:$B,B10)),"-") -> -0.002619798 | O10: =IFERROR(IF(B10="","",AVERAGEIFS('Stock Guide'!$V:$V,'Stock Guide'!$B:$B,B10)),"-") -> 0.058189061 | P10: =IFERROR(IF(B10="","",AVERAGEIFS('Stock Guide'!$W:$W,'Stock Guide'!$B:$B,B10)),"-") -> 0.16238602
B11: ALZC11 | C11: =IF(B11="","",(VLOOKUP(B11,'Stock Guide'!$B:$D,3,0))) -> Alianza Crédito Imobiliário FII | D11: =IF(B11="","",SUMIFS('Stock Guide'!$J:$J,'Stock Guide'!$B:$B,B11)) -> 7.47 | E11: =IF(B11="","",SUMIFS('Stock Guide'!$H:$H,'Stock Guide'!$B:$B,B11)) -> 0 | F11: =IF(B11="","",SUMIFS('Stock Guide'!I:I,'Stock Guide'!$B:$B,B11)) -> 225645.14 | G11: =IF(B11="","",SUMIFS('Stock Guide'!$M:$M,'Stock Guide'!$B:$B,B11)) -> 1.8189573e+08 | H11: =IF(B11="","",SUMIFS('Stock Guide'!$N:$N,'Stock Guide'!$B:$B,B11)) -> 2.2282429e+08 | I11: =IF(B11="","",SUMIFS('Stock Guide'!$O:$O,'Stock Guide'!$B:$B,B11)) -> 0.81631911 | J11: =IF(B11="","",SUMIFS('Stock Guide'!$P:$P,'Stock Guide'!$B:$B,B11)) -> 0.82419992 | K11: =IF(B11="","",SUMIFS('Stock Guide'!$Q:$Q,'Stock Guide'!$B:$B,B11)) -> 0.16291834 | L11: =IF(B11="","",SUMIFS('Stock Guide'!$R:$R,'Stock Guide'!$B:$B,B11)) -> 0.16064257 | M11: =IF(B11="","",SUMIFS('Stock Guide'!$T:$T,'Stock Guide'!$B:$B,B11)) -> 0.1 | N11: =IFERROR(IF(B11="","",AVERAGEIFS('Stock Guide'!$U:$U,'Stock Guide'!$B:$B,B11)),"-") -> 0.019347241 | O11: =IFERROR(IF(B11="","",AVERAGEIFS('Stock Guide'!$V:$V,'Stock Guide'!$B:$B,B11)),"-") -> 0.072841592 | P11: =IFERROR(IF(B11="","",AVERAGEIFS('Stock Guide'!$W:$W,'Stock Guide'!$B:$B,B11)),"-") -> 0.16597329
B12: ARRI11 | C12: =IF(B12="","",(VLOOKUP(B12,'Stock Guide'!$B:$D,3,0))) -> Open K Ativos e Recebíveis Imobiliários FII | D12: =IF(B12="","",SUMIFS('Stock Guide'!$J:$J,'Stock Guide'!$B:$B,B12)) -> 4.64 | E12: =IF(B12="","",SUMIFS('Stock Guide'!$H:$H,'Stock Guide'!$B:$B,B12)) -> 0 | F12: =IF(B12="","",SUMIFS('Stock Guide'!I:I,'Stock Guide'!$B:$B,B12)) -> 176289.94 | G12: =IF(B12="","",SUMIFS('Stock Guide'!$M:$M,'Stock Guide'!$B:$B,B12)) -> 96173155 | H12: =IF(B12="","",SUMIFS('Stock Guide'!$N:$N,'Stock Guide'!$B:$B,B12)) -> 1.7512428e+08 | I12: =IF(B12="","",SUMIFS('Stock Guide'!$O:$O,'Stock Guide'!$B:$B,B12)) -> 0.54917088 | J12: =IF(B12="","",SUMIFS('Stock Guide'!$P:$P,'Stock Guide'!$B:$B,B12)) -> 0.808837 | K12: =IF(B12="","",SUMIFS('Stock Guide'!$Q:$Q,'Stock Guide'!$B:$B,B12)) -> 0.2112069 | L12: =IF(B12="","",SUMIFS('Stock Guide'!$R:$R,'Stock Guide'!$B:$B,B12)) -> 0.18103448 | M12: =IF(B12="","",SUMIFS('Stock Guide'!$T:$T,'Stock Guide'!$B:$B,B12)) -> 0.07 | N12: =IFERROR(IF(B12="","",AVERAGEIFS('Stock Guide'!$U:$U,'Stock Guide'!$B:$B,B12)),"-") -> 0.01754386 | O12: =IFERROR(IF(B12="","",AVERAGEIFS('Stock Guide'!$V:$V,'Stock Guide'!$B:$B,B12)),"-") -> -0.24690251 | P12: =IFERROR(IF(B12="","",AVERAGEIFS('Stock Guide'!$W:$W,'Stock Guide'!$B:$B,B12)),"-") -> -0.18560782
B13: ARTE11 | C13: =IF(B13="","",(VLOOKUP(B13,'Stock Guide'!$B:$D,3,0))) -> - | D13: =IF(B13="","",SUMIFS('Stock Guide'!$J:$J,'Stock Guide'!$B:$B,B13)) -> 7.15 | E13: =IF(B13="","",SUMIFS('Stock Guide'!$H:$H,'Stock Guide'!$B:$B,B13)) -> 0 | F13: =IF(B13="","",SUMIFS('Stock Guide'!I:I,'Stock Guide'!$B:$B,B13)) -> 67940.721 | G13: =IF(B13="","",SUMIFS('Stock Guide'!$M:$M,'Stock Guide'!$B:$B,B13)) -> 67922447 | H13: =IF(B13="","",SUMIFS('Stock Guide'!$N:$N,'Stock Guide'!$B:$B,B13)) -> 96287693 | I13: =IF(B13="","",SUMIFS('Stock Guide'!$O:$O,'Stock Guide'!$B:$B,B13)) -> 0.70541152 | J13: =IF(B13="","",SUMIFS('Stock Guide'!$P:$P,'Stock Guide'!$B:$B,B13)) -> 0 | K13: =IF(B13="","",SUMIFS('Stock Guide'!$Q:$Q,'Stock Guide'!$B:$B,B13)) -> 0 | L13: =IF(B13="","",SUMIFS('Stock Guide'!$R:$R,'Stock Guide'!$B:$B,B13)) -> 0.18461538 | M13: =IF(B13="","",SUMIFS('Stock Guide'!$T:$T,'Stock Guide'!$B:$B,B13)) -> 0.11 | N13: =IFERROR(IF(B13="","",AVERAGEIFS('Stock Guide'!$U:$U,'Stock Guide'!$B:$B,B13)),"-") -> -0.011385885 | O13: =IFERROR(IF(B13="","",AVERAGEIFS('Stock Guide'!$V:$V,'Stock Guide'!$B:$B,B13)),"-") -> - | P13: =IFERROR(IF(B13="","",AVERAGEIFS('Stock Guide'!$W:$W,'Stock Guide'!$B:$B,B13)),"-") -> -
B14: ARXD11 | C14: =IF(B14="","",(VLOOKUP(B14,'Stock Guide'!$B:$D,3,0))) -> ARX Dover Recebíveis FII | D14: =IF(B14="","",SUMIFS('Stock Guide'!$J:$J,'Stock Guide'!$B:$B,B14)) -> 7.58 | E14: =IF(B14="","",SUMIFS('Stock Guide'!$H:$H,'Stock Guide'!$B:$B,B14)) -> 0 | F14: =IF(B14="","",SUMIFS('Stock Guide'!I:I,'Stock Guide'!$B:$B,B14)) -> 63631.76 | G14: =IF(B14="","",SUMIFS('Stock Guide'!$M:$M,'Stock Guide'!$B:$B,B14)) -> 65596797 | H14: =IF(B14="","",SUMIFS('Stock Guide'!$N:$N,'Stock Guide'!$B:$B,B14)) -> 78715004 | I14: =IF(B14="","",SUMIFS('Stock Guide'!$O:$O,'Stock Guide'!$B:$B,B14)) -> 0.83334553 | J14: =IF(B14="","",SUMIFS('Stock Guide'!$P:$P,'Stock Guide'!$B:$B,B14)) -> 0.84061424 | K14: =IF(B14="","",SUMIFS('Stock Guide'!$Q:$Q,'Stock Guide'!$B:$B,B14)) -> 0.14577836 | L14: =IF(B14="","",SUMIFS('Stock Guide'!$R:$R,'Stock Guide'!$B:$B,B14)) -> 0.14248021 | M14: =IF(B14="","",SUMIFS('Stock Guide'!$T:$T,'Stock Guide'!$B:$B,B14)) -> 0.09 | N14: =IFERROR(IF(B14="","",AVERAGEIFS('Stock Guide'!$U:$U,'Stock Guide'!$B:$B,B14)),"-") -> -0.023195876 | O14: =IFERROR(IF(B14="","",AVERAGEIFS('Stock Guide'!$V:$V,'Stock Guide'!$B:$B,B14)),"-") -> 0.07392603 | P14: =IFERROR(IF(B14="","",AVERAGEIFS('Stock Guide'!$W:$W,'Stock Guide'!$B:$B,B14)),"-") -> 0.17499247
B15: BCRI11 | C15: =IF(B15="","",(VLOOKUP(B15,'Stock Guide'!$B:$D,3,0))) -> Banestes Recebíveis Imobiliários FII | D15: =IF(B15="","",SUMIFS('Stock Guide'!$J:$J,'Stock Guide'!$B:$B,B15)) -> 57.5 | E15: =IF(B15="","",SUMIFS('Stock Guide'!$H:$H,'Stock Guide'!$B:$B,B15)) -> 0.00244 | F15: =IF(B15="","",SUMIFS('Stock Guide'!I:I,'Stock Guide'!$B:$B,B15)) -> 346838.47 | G15: =IF(B15="","",SUMIFS('Stock Guide'!$M:$M,'Stock Guide'!$B:$B,B15)) -> 3.598277e+08 | H15: =IF(B15="","",SUMIFS('Stock Guide'!$N:$N,'Stock Guide'!$B:$B,B15)) -> 5.3406451e+08 | I15: =IF(B15="","",SUMIFS('Stock Guide'!$O:$O,'Stock Guide'!$B:$B,B15)) -> 0.67375325 | J15: =IF(B15="","",SUMIFS('Stock Guide'!$P:$P,'Stock Guide'!$B:$B,B15)) -> 0.80474643 | K15: =IF(B15="","",SUMIFS('Stock Guide'!$Q:$Q,'Stock Guide'!$B:$B,B15)) -> 0.16713043 | L15: =IF(B15="","",SUMIFS('Stock Guide'!$R:$R,'Stock Guide'!$B:$B,B15)) -> 0.16695652 | M15: =IF(B15="","",SUMIFS('Stock Guide'!$T:$T,'Stock Guide'!$B:$B,B15)) -> 0.8 | N15: =IFERROR(IF(B15="","",AVERAGEIFS('Stock Guide'!$U:$U,'Stock Guide'!$B:$B,B15)),"-") -> -0.026908106 | O15: =IFERROR(IF(B15="","",AVERAGEIFS('Stock Guide'!$V:$V,'Stock Guide'!$B:$B,B15)),"-") -> -0.082624692 | P15: =IFERROR(IF(B15="","",AVERAGEIFS('Stock Guide'!$W:$W,'Stock Guide'!$B:$B,B15)),"-") -> 0.048343213
B16: BTCI11 | C16: =IF(B16="","",(VLOOKUP(B16,'Stock Guide'!$B:$D,3,0))) -> BTG Pactual Crédito Imobiliário FII | D16: =IF(B16="","",SUMIFS('Stock Guide'!$J:$J,'Stock Guide'!$B:$B,B16)) -> 9 | E16: =IF(B16="","",SUMIFS('Stock Guide'!$H:$H,'Stock Guide'!$B:$B,B16)) -> 0.00606 | F16: =IF(B16="","",SUMIFS('Stock Guide'!I:I,'Stock Guide'!$B:$B,B16)) -> 3504861.6 | G16: =IF(B16="","",SUMIFS('Stock Guide'!$M:$M,'Stock Guide'!$B:$B,B16)) -> 895690548 | H16: =IF(B16="","",SUMIFS('Stock Guide'!$N:$N,'Stock Guide'!$B:$B,B16)) -> 1.0039604e+09 | I16: =IF(B16="","",SUMIFS('Stock Guide'!$O:$O,'Stock Guide'!$B:$B,B16)) -> 0.89215724 | J16: =IF(B16="","",SUMIFS('Stock Guide'!$P:$P,'Stock Guide'!$B:$B,B16)) -> 0.92960381 | K16: =IF(B16="","",SUMIFS('Stock Guide'!$Q:$Q,'Stock Guide'!$B:$B,B16)) -> 0.13055556 | L16: =IF(B16="","",SUMIFS('Stock Guide'!$R:$R,'Stock Guide'!$B:$B,B16)) -> 0.13733333 | M16: =IF(B16="","",SUMIFS('Stock Guide'!$T:$T,'Stock Guide'!$B:$B,B16)) -> 0.103 | N16: =IFERROR(IF(B16="","",AVERAGEIFS('Stock Guide'!$U:$U,'Stock Guide'!$B:$B,B16)),"-") -> -0.0040443824 | O16: =IFERROR(IF(B16="","",AVERAGEIFS('Stock Guide'!$V:$V,'Stock Guide'!$B:$B,B16)),"-") -> 0.048974723 | P16: =IFERROR(IF(B16="","",AVERAGEIFS('Stock Guide'!$W:$W,'Stock Guide'!$B:$B,B16)),"-") -> 0.12285468
B17: CACR11 | C17: =IF(B17="","",(VLOOKUP(B17,'Stock Guide'!$B:$D,3,0))) -> Cartesia Recebíveis Imobiliários FII | D17: =IF(B17="","",SUMIFS('Stock Guide'!$J:$J,'Stock Guide'!$B:$B,B17)) -> 16.51 | E17: =IF(B17="","",SUMIFS('Stock Guide'!$H:$H,'Stock Guide'!$B:$B,B17)) -> 0.0005 | F17: =IF(B17="","",SUMIFS('Stock Guide'!I:I,'Stock Guide'!$B:$B,B17)) -> 883117.86 | G17: =IF(B17="","",SUMIFS('Stock Guide'!$M:$M,'Stock Guide'!$B:$B,B17)) -> 79847709 | H17: =IF(B17="","",SUMIFS('Stock Guide'!$N:$N,'Stock Guide'!$B:$B,B17)) -> 4.9405528e+08 | I17: =IF(B17="","",SUMIFS('Stock Guide'!$O:$O,'Stock Guide'!$B:$B,B17)) -> 0.16161695 | J17: =IF(B17="","",SUMIFS('Stock Guide'!$P:$P,'Stock Guide'!$B:$B,B17)) -> 1.0516692 | K17: =IF(B17="","",SUMIFS('Stock Guide'!$Q:$Q,'Stock Guide'!$B:$B,B17)) -> 0.6359782 | L17: =IF(B17="","",SUMIFS('Stock Guide'!$R:$R,'Stock Guide'!$B:$B,B17)) -> 0 | M17: =IF(B17="","",SUMIFS('Stock Guide'!$T:$T,'Stock Guide'!$B:$B,B17)) -> 0 | N17: =IFERROR(IF(B17="","",AVERAGEIFS('Stock Guide'!$U:$U,'Stock Guide'!$B:$B,B17)),"-") -> 0.048253968 | O17: =IFERROR(IF(B17="","",AVERAGEIFS('Stock Guide'!$V:$V,'Stock Guide'!$B:$B,B17)),"-") -> -0.77838584 | P17: =IFERROR(IF(B17="","",AVERAGEIFS('Stock Guide'!$W:$W,'Stock Guide'!$B:$B,B17)),"-") -> -0.76894412
B18: CLIN11 | C18: =IF(B18="","",(VLOOKUP(B18,'Stock Guide'!$B:$D,3,0))) -> Clave Índices de Preços FII | D18: =IF(B18="","",SUMIFS('Stock Guide'!$J:$J,'Stock Guide'!$B:$B,B18)) -> 83.99 | E18: =IF(B18="","",SUMIFS('Stock Guide'!$H:$H,'Stock Guide'!$B:$B,B18)) -> 0.00247 | F18: =IF(B18="","",SUMIFS('Stock Guide'!I:I,'Stock Guide'!$B:$B,B18)) -> 2115819.4 | G18: =IF(B18="","",SUMIFS('Stock Guide'!$M:$M,'Stock Guide'!$B:$B,B18)) -> 3.6508462e+08 | H18: =IF(B18="","",SUMIFS('Stock Guide'!$N:$N,'Stock Guide'!$B:$B,B18)) -> 4.2944977e+08 | I18: =IF(B18="","",SUMIFS('Stock Guide'!$O:$O,'Stock Guide'!$B:$B,B18)) -> 0.85012184 | J18: =IF(B18="","",SUMIFS('Stock Guide'!$P:$P,'Stock Guide'!$B:$B,B18)) -> 0.90246951 | K18: =IF(B18="","",SUMIFS('Stock Guide'!$Q:$Q,'Stock Guide'!$B:$B,B18)) -> 0.14358852 | L18: =IF(B18="","",SUMIFS('Stock Guide'!$R:$R,'Stock Guide'!$B:$B,B18)) -> 0.14287415 | M18: =IF(B18="","",SUMIFS('Stock Guide'!$T:$T,'Stock Guide'!$B:$B,B18)) -> 1 | N18: =IFERROR(IF(B18="","",AVERAGEIFS('Stock Guide'!$U:$U,'Stock Guide'!$B:$B,B18)),"-") -> -0.038184029 | O18: =IFERROR(IF(B18="","",AVERAGEIFS('Stock Guide'!$V:$V,'Stock Guide'!$B:$B,B18)),"-") -> 0.043573507 | P18: =IFERROR(IF(B18="","",AVERAGEIFS('Stock Guide'!$W:$W,'Stock Guide'!$B:$B,B18)),"-") -> 0.082571829
B19: CYCR11 | C19: =IF(B19="","",(VLOOKUP(B19,'Stock Guide'!$B:$D,3,0))) -> Cyrela Crédito FII | D19: =IF(B19="","",SUMIFS('Stock Guide'!$J:$J,'Stock Guide'!$B:$B,B19)) -> 8.35 | E19: =IF(B19="","",SUMIFS('Stock Guide'!$H:$H,'Stock Guide'!$B:$B,B19)) -> 0.00206 | F19: =IF(B19="","",SUMIFS('Stock Guide'!I:I,'Stock Guide'!$B:$B,B19)) -> 617540.53 | G19: =IF(B19="","",SUMIFS('Stock Guide'!$M:$M,'Stock Guide'!$B:$B,B19)) -> 3.0518787e+08 | H19: =IF(B19="","",SUMIFS('Stock Guide'!$N:$N,'Stock Guide'!$B:$B,B19)) -> 3.4608618e+08 | I19: =IF(B19="","",SUMIFS('Stock Guide'!$O:$O,'Stock Guide'!$B:$B,B19)) -> 0.88182621 | J19: =IF(B19="","",SUMIFS('Stock Guide'!$P:$P,'Stock Guide'!$B:$B,B19)) -> 0.92843586 | K19: =IF(B19="","",SUMIFS('Stock Guide'!$Q:$Q,'Stock Guide'!$B:$B,B19)) -> 0.15233533 | L19: =IF(B19="","",SUMIFS('Stock Guide'!$R:$R,'Stock Guide'!$B:$B,B19)) -> 0.15233533 | M19: =IF(B19="","",SUMIFS('Stock Guide'!$T:$T,'Stock Guide'!$B:$B,B19)) -> 0.106 | N19: =IFERROR(IF(B19="","",AVERAGEIFS('Stock Guide'!$U:$U,'Stock Guide'!$B:$B,B19)),"-") -> -0.018109125 | O19: =IFERROR(IF(B19="","",AVERAGEIFS('Stock Guide'!$V:$V,'Stock Guide'!$B:$B,B19)),"-") -> 0.037433233 | P19: =IFERROR(IF(B19="","",AVERAGEIFS('Stock Guide'!$W:$W,'Stock Guide'!$B:$B,B19)),"-") -> 0.12705179
B20: DEVA11 | C20: =IF(B20="","",(VLOOKUP(B20,'Stock Guide'!$B:$D,3,0))) -> Devant Recebíveis Imobiliários FII | D20: =IF(B20="","",SUMIFS('Stock Guide'!$J:$J,'Stock Guide'!$B:$B,B20)) -> 16.78 | E20: =IF(B20="","",SUMIFS('Stock Guide'!$H:$H,'Stock Guide'!$B:$B,B20)) -> 0.00159 | F20: =IF(B20="","",SUMIFS('Stock Guide'!I:I,'Stock Guide'!$B:$B,B20)) -> 523631.75 | G20: =IF(B20="","",SUMIFS('Stock Guide'!$M:$M,'Stock Guide'!$B:$B,B20)) -> 2.3567356e+08 | H20: =IF(B20="","",SUMIFS('Stock Guide'!$N:$N,'Stock Guide'!$B:$B,B20)) -> 1.3548673e+09 | I20: =IF(B20="","",SUMIFS('Stock Guide'!$O:$O,'Stock Guide'!$B:$B,B20)) -> 0.17394585 | J20: =IF(B20="","",SUMIFS('Stock Guide'!$P:$P,'Stock Guide'!$B:$B,B20)) -> 0.26498992 | K20: =IF(B20="","",SUMIFS('Stock Guide'!$Q:$Q,'Stock Guide'!$B:$B,B20)) -> 0.23718713 | L20: =IF(B20="","",SUMIFS('Stock Guide'!$R:$R,'Stock Guide'!$B:$B,B20)) -> 0.21454112 | M20: =IF(B20="","",SUMIFS('Stock Guide'!$T:$T,'Stock Guide'!$B:$B,B20)) -> 0.3 | N20: =IFERROR(IF(B20="","",AVERAGEIFS('Stock Guide'!$U:$U,'Stock Guide'!$B:$B,B20)),"-") -> -0.092178394 | O20: =IFERROR(IF(B20="","",AVERAGEIFS('Stock Guide'!$V:$V,'Stock Guide'!$B:$B,B20)),"-") -> -0.27469494 | P20: =IFERROR(IF(B20="","",AVERAGEIFS('Stock Guide'!$W:$W,'Stock Guide'!$B:$B,B20)),"-") -> -0.29300822
B21: EQIR11 | C21: =IF(B21="","",(VLOOKUP(B21,'Stock Guide'!$B:$D,3,0))) -> EQI Recebíveis Imobiliários FII | D21: =IF(B21="","",SUMIFS('Stock Guide'!$J:$J,'Stock Guide'!$B:$B,B21)) -> 7.9 | E21: =IF(B21="","",SUMIFS('Stock Guide'!$H:$H,'Stock Guide'!$B:$B,B21)) -> 0 | F21: =IF(B21="","",SUMIFS('Stock Guide'!I:I,'Stock Guide'!$B:$B,B21)) -> 61523.661 | G21: =IF(B21="","",SUMIFS('Stock Guide'!$M:$M,'Stock Guide'!$B:$B,B21)) -> 86183588 | H21: =IF(B21="","",SUMIFS('Stock Guide'!$N:$N,'Stock Guide'!$B:$B,B21)) -> 1.0515852e+08 | I21: =IF(B21="","",SUMIFS('Stock Guide'!$O:$O,'Stock Guide'!$B:$B,B21)) -> 0.81955878 | J21: =IF(B21="","",SUMIFS('Stock Guide'!$P:$P,'Stock Guide'!$B:$B,B21)) -> 0.85865282 | K21: =IF(B21="","",SUMIFS('Stock Guide'!$Q:$Q,'Stock Guide'!$B:$B,B21)) -> 0.15198666 | L21: =IF(B21="","",SUMIFS('Stock Guide'!$R:$R,'Stock Guide'!$B:$B,B21)) -> 0.15189873 | M21: =IF(B21="","",SUMIFS('Stock Guide'!$T:$T,'Stock Guide'!$B:$B,B21)) -> 0.1 | N21: =IFERROR(IF(B21="","",AVERAGEIFS('Stock Guide'!$U:$U,'Stock Guide'!$B:$B,B21)),"-") -> -0.036190158 | O21: =IFERROR(IF(B21="","",AVERAGEIFS('Stock Guide'!$V:$V,'Stock Guide'!$B:$B,B21)),"-") -> 0.052225671 | P21: =IFERROR(IF(B21="","",AVERAGEIFS('Stock Guide'!$W:$W,'Stock Guide'!$B:$B,B21)),"-") -> 0.18929684
... B74: XPCI11 | C74: =IF(B74="","",(VLOOKUP(B74,'Stock Guide'!$B:$D,3,0))) -> XP Crédito Imobiliário FII | D74: =IF(B74="","",SUMIFS('Stock Guide'!$J:$J,'Stock Guide'!$B:$B,B74)) -> 76.99 | E74: =IF(B74="","",SUMIFS('Stock Guide'!$H:$H,'Stock Guide'!$B:$B,B74)) -> 0.00453 | F74: =IF(B74="","",SUMIFS('Stock Guide'!I:I,'Stock Guide'!$B:$B,B74)) -> 1835113 | G74: =IF(B74="","",SUMIFS('Stock Guide'!$M:$M,'Stock Guide'!$B:$B,B74)) -> 6.6993249e+08 | H74: =IF(B74="","",SUMIFS('Stock Guide'!$N:$N,'Stock Guide'!$B:$B,B74)) -> 7.5754369e+08 | I74: =IF(B74="","",SUMIFS('Stock Guide'!$O:$O,'Stock Guide'!$B:$B,B74)) -> 0.88434832 | J74: =IF(B74="","",SUMIFS('Stock Guide'!$P:$P,'Stock Guide'!$B:$B,B74)) -> 0.91979796 | K74: =IF(B74="","",SUMIFS('Stock Guide'!$Q:$Q,'Stock Guide'!$B:$B,B74)) -> 0.14079751 | L74: =IF(B74="","",SUMIFS('Stock Guide'!$R:$R,'Stock Guide'!$B:$B,B74)) -> 0.14495389 | M74: =IF(B74="","",SUMIFS('Stock Guide'!$T:$T,'Stock Guide'!$B:$B,B74)) -> 0.93 | N74: =IFERROR(IF(B74="","",AVERAGEIFS('Stock Guide'!$U:$U,'Stock Guide'!$B:$B,B74)),"-") -> -0.056610709 | O74: =IFERROR(IF(B74="","",AVERAGEIFS('Stock Guide'!$V:$V,'Stock Guide'!$B:$B,B74)),"-") -> 0.01048662 | P74: =IFERROR(IF(B74="","",AVERAGEIFS('Stock Guide'!$W:$W,'Stock Guide'!$B:$B,B74)),"-") -> 0.074142623
C75: =IF(B75="","",(VLOOKUP(B75,'Stock Guide'!$B:$D,3,0))) | D75: =IF(B75="","",SUMIFS('Stock Guide'!$J:$J,'Stock Guide'!$B:$B,B75)) | E75: =IF(B75="","",SUMIFS('Stock Guide'!$H:$H,'Stock Guide'!$B:$B,B75)) | F75: =IF(B75="","",SUMIFS('Stock Guide'!I:I,'Stock Guide'!$B:$B,B75)) | G75: =IF(B75="","",SUMIFS('Stock Guide'!$M:$M,'Stock Guide'!$B:$B,B75)) | H75: =IF(B75="","",SUMIFS('Stock Guide'!$N:$N,'Stock Guide'!$B:$B,B75)) | I75: =IF(B75="","",SUMIFS('Stock Guide'!$O:$O,'Stock Guide'!$B:$B,B75)) | J75: =IF(B75="","",SUMIFS('Stock Guide'!$P:$P,'Stock Guide'!$B:$B,B75)) | K75: =IF(B75="","",SUMIFS('Stock Guide'!$Q:$Q,'Stock Guide'!$B:$B,B75)) | L75: =IF(B75="","",SUMIFS('Stock Guide'!$R:$R,'Stock Guide'!$B:$B,B75)) | M75: =IF(B75="","",SUMIFS('Stock Guide'!$T:$T,'Stock Guide'!$B:$B,B75)) | N75: =IFERROR(IF(B75="","",AVERAGEIFS('Stock Guide'!$U:$U,'Stock Guide'!$B:$B,B75)),"-") | O75: =IFERROR(IF(B75="","",AVERAGEIFS('Stock Guide'!$V:$V,'Stock Guide'!$B:$B,B75)),"-") | P75: =IFERROR(IF(B75="","",AVERAGEIFS('Stock Guide'!$W:$W,'Stock Guide'!$B:$B,B75)),"-")
C76: =IF(B76="","",(VLOOKUP(B76,'Stock Guide'!$B:$D,3,0))) | D76: =IF(B76="","",SUMIFS('Stock Guide'!$J:$J,'Stock Guide'!$B:$B,B76)) | E76: =IF(B76="","",SUMIFS('Stock Guide'!$H:$H,'Stock Guide'!$B:$B,B76)) | F76: =IF(B76="","",SUMIFS('Stock Guide'!I:I,'Stock Guide'!$B:$B,B76)) | G76: =IF(B76="","",SUMIFS('Stock Guide'!$M:$M,'Stock Guide'!$B:$B,B76)) | H76: =IF(B76="","",SUMIFS('Stock Guide'!$N:$N,'Stock Guide'!$B:$B,B76)) | I76: =IF(B76="","",SUMIFS('Stock Guide'!$O:$O,'Stock Guide'!$B:$B,B76)) | J76: =IF(B76="","",SUMIFS('Stock Guide'!$P:$P,'Stock Guide'!$B:$B,B76)) | K76: =IF(B76="","",SUMIFS('Stock Guide'!$Q:$Q,'Stock Guide'!$B:$B,B76)) | L76: =IF(B76="","",SUMIFS('Stock Guide'!$R:$R,'Stock Guide'!$B:$B,B76)) | M76: =IF(B76="","",SUMIFS('Stock Guide'!$T:$T,'Stock Guide'!$B:$B,B76)) | N76: =IFERROR(IF(B76="","",AVERAGEIFS('Stock Guide'!$U:$U,'Stock Guide'!$B:$B,B76)),"-") | O76: =IFERROR(IF(B76="","",AVERAGEIFS('Stock Guide'!$V:$V,'Stock Guide'!$B:$B,B76)),"-") | P76: =IFERROR(IF(B76="","",AVERAGEIFS('Stock Guide'!$W:$W,'Stock Guide'!$B:$B,B76)),"-")
C77: =IF(B77="","",(VLOOKUP(B77,'Stock Guide'!$B:$D,3,0))) | D77: =IF(B77="","",SUMIFS('Stock Guide'!$J:$J,'Stock Guide'!$B:$B,B77)) | E77: =IF(B77="","",SUMIFS('Stock Guide'!$H:$H,'Stock Guide'!$B:$B,B77)) | F77: =IF(B77="","",SUMIFS('Stock Guide'!I:I,'Stock Guide'!$B:$B,B77)) | G77: =IF(B77="","",SUMIFS('Stock Guide'!$M:$M,'Stock Guide'!$B:$B,B77)) | H77: =IF(B77="","",SUMIFS('Stock Guide'!$N:$N,'Stock Guide'!$B:$B,B77)) | I77: =IF(B77="","",SUMIFS('Stock Guide'!$O:$O,'Stock Guide'!$B:$B,B77)) | J77: =IF(B77="","",SUMIFS('Stock Guide'!$P:$P,'Stock Guide'!$B:$B,B77)) | K77: =IF(B77="","",SUMIFS('Stock Guide'!$Q:$Q,'Stock Guide'!$B:$B,B77)) | L77: =IF(B77="","",SUMIFS('Stock Guide'!$R:$R,'Stock Guide'!$B:$B,B77)) | M77: =IF(B77="","",SUMIFS('Stock Guide'!$T:$T,'Stock Guide'!$B:$B,B77)) | N77: =IFERROR(IF(B77="","",AVERAGEIFS('Stock Guide'!$U:$U,'Stock Guide'!$B:$B,B77)),"-") | O77: =IFERROR(IF(B77="","",AVERAGEIFS('Stock Guide'!$V:$V,'Stock Guide'!$B:$B,B77)),"-") | P77: =IFERROR(IF(B77="","",AVERAGEIFS('Stock Guide'!$W:$W,'Stock Guide'!$B:$B,B77)),"-")
C78: =IF(B78="","",(VLOOKUP(B78,'Stock Guide'!$B:$D,3,0))) | D78: =IF(B78="","",SUMIFS('Stock Guide'!$J:$J,'Stock Guide'!$B:$B,B78)) | E78: =IF(B78="","",SUMIFS('Stock Guide'!$H:$H,'Stock Guide'!$B:$B,B78)) | F78: =IF(B78="","",SUMIFS('Stock Guide'!I:I,'Stock Guide'!$B:$B,B78)) | G78: =IF(B78="","",SUMIFS('Stock Guide'!$M:$M,'Stock Guide'!$B:$B,B78)) | H78: =IF(B78="","",SUMIFS('Stock Guide'!$N:$N,'Stock Guide'!$B:$B,B78)) | I78: =IF(B78="","",SUMIFS('Stock Guide'!$O:$O,'Stock Guide'!$B:$B,B78)) | J78: =IF(B78="","",SUMIFS('Stock Guide'!$P:$P,'Stock Guide'!$B:$B,B78)) | K78: =IF(B78="","",SUMIFS('Stock Guide'!$Q:$Q,'Stock Guide'!$B:$B,B78)) | L78: =IF(B78="","",SUMIFS('Stock Guide'!$R:$R,'Stock Guide'!$B:$B,B78)) | M78: =IF(B78="","",SUMIFS('Stock Guide'!$T:$T,'Stock Guide'!$B:$B,B78)) | N78: =IFERROR(IF(B78="","",AVERAGEIFS('Stock Guide'!$U:$U,'Stock Guide'!$B:$B,B78)),"-") | O78: =IFERROR(IF(B78="","",AVERAGEIFS('Stock Guide'!$V:$V,'Stock Guide'!$B:$B,B78)),"-") | P78: =IFERROR(IF(B78="","",AVERAGEIFS('Stock Guide'!$W:$W,'Stock Guide'!$B:$B,B78)),"-")
C79: =IF(B79="","",(VLOOKUP(B79,'Stock Guide'!$B:$D,3,0))) | D79: =IF(B79="","",SUMIFS('Stock Guide'!$J:$J,'Stock Guide'!$B:$B,B79)) | E79: =IF(B79="","",SUMIFS('Stock Guide'!$H:$H,'Stock Guide'!$B:$B,B79)) | F79: =IF(B79="","",SUMIFS('Stock Guide'!I:I,'Stock Guide'!$B:$B,B79)) | G79: =IF(B79="","",SUMIFS('Stock Guide'!$M:$M,'Stock Guide'!$B:$B,B79)) | H79: =IF(B79="","",SUMIFS('Stock Guide'!$N:$N,'Stock Guide'!$B:$B,B79)) | I79: =IF(B79="","",SUMIFS('Stock Guide'!$O:$O,'Stock Guide'!$B:$B,B79)) | J79: =IF(B79="","",SUMIFS('Stock Guide'!$P:$P,'Stock Guide'!$B:$B,B79)) | K79: =IF(B79="","",SUMIFS('Stock Guide'!$Q:$Q,'Stock Guide'!$B:$B,B79)) | L79: =IF(B79="","",SUMIFS('Stock Guide'!$R:$R,'Stock Guide'!$B:$B,B79)) | M79: =IF(B79="","",SUMIFS('Stock Guide'!$T:$T,'Stock Guide'!$B:$B,B79)) | N79: =IFERROR(IF(B79="","",AVERAGEIFS('Stock Guide'!$U:$U,'Stock Guide'!$B:$B,B79)),"-") | O79: =IFERROR(IF(B79="","",AVERAGEIFS('Stock Guide'!$V:$V,'Stock Guide'!$B:$B,B79)),"-") | P79: =IFERROR(IF(B79="","",AVERAGEIFS('Stock Guide'!$W:$W,'Stock Guide'!$B:$B,B79)),"-")
C80: =IF(B80="","",(VLOOKUP(B80,'Stock Guide'!$B:$D,3,0))) | H80: =IF(B80="","",SUMIFS('Stock Guide'!$N:$N,'Stock Guide'!$B:$B,B80))
C81: =IF(B81="","",(VLOOKUP(B81,'Stock Guide'!$B:$D,3,0))) | H81: =IF(B81="","",SUMIFS('Stock Guide'!$N:$N,'Stock Guide'!$B:$B,B81))
C82: =IF(B82="","",(VLOOKUP(B82,'Stock Guide'!$B:$D,3,0))) | H82: =IF(B82="","",SUMIFS('Stock Guide'!$N:$N,'Stock Guide'!$B:$B,B82))
C83: =IF(B83="","",(VLOOKUP(B83,'Stock Guide'!$B:$D,3,0)))
C84: =IF(B84="","",(VLOOKUP(B84,'Stock Guide'!$B:$D,3,0)))
C85: =IF(B85="","",(VLOOKUP(B85,'Stock Guide'!$B:$D,3,0)))
C86: =IF(B86="","",(VLOOKUP(B86,'Stock Guide'!$B:$D,3,0)))
C87: =IF(B87="","",(VLOOKUP(B87,'Stock Guide'!$B:$D,3,0)))
C88: =IF(B88="","",(VLOOKUP(B88,'Stock Guide'!$B:$D,3,0)))
C89: =IF(B89="","",(VLOOKUP(B89,'Stock Guide'!$B:$D,3,0)))

Sheet Laje Corporativa
O2: Menu | P2: Stock Guide
B4: =B8 -> Laje Corporativa
B6: Fundo | D6: Fechamento | E6: Part. IFIX | F6: Volume de Negociação | G6: Valor de Mercado | H6: Valor Patrimonial | I6: P/VPA Atual | J6: P/VPA 2025 | K6: Dividend Yield LTM | L6: Dividend Yield Anualizado | M6: Último Dividendo | N6: Retorno no Mês | O6: Retorno no Ano | P6: Retorno LTM
B7: Segmento | D7: R$ | E7: Total (%) | F7: Média Diária (R$) | G7: Média (R$) | H7: Média (R$) | I7: Média | J7: Média | K7: Média (% ao ano) | L7: Média (% ao ano) | M7: R$ | N7: Média (%) | O7: Média (%) | P7: Média (%)
